Workbook

Sheet 00 - Kapak
A4: TARODAN
A7: Koleksiyoner Modeli & İkinci El Pazarı
A9: KULLANICI KABUL TESTİ (UAT) PLANI
A12: Web Platformu (tarodan.shop) + Admin Paneli (admin.tarodan.shop)
B15: Proje Adı | C15: Tarodan E-Ticaret Platformu
B16: Doküman Türü | C16: Kabul Testi (UAT) — Resmi Onay Belgesi
B17: Versiyon | C17: 1.0
B18: Hazırlayan | C18: Tarodan Geliştirme Ekibi
B19: Müşteri
B20: Hazırlanma Tarihi | C20: 01.05.2026
B21: Test Başlangıç Tarihi
B22: Test Bitiş Tarihi
B23: Toplam Sheet Sayısı | C23: Bkz. 01 - Özet
B24: Toplam Test Senaryosu | C24: Bkz. 01 - Özet
B28: RESMİ ONAY VE TESLİM
B29: İşbu doküman, Tarodan platformunun (web ve admin) tüm fonksiyonel kapsamını kapsayan kabul testi (UAT) senaryolarını içermektedir. Her sheet bir modül/sayfa için detaylı test adımları, beklenen sonuçlar ve sonuç işaretleme alanları sunar. Tüm sheet'lerin sonunda Tarodan ekibi ve Müşteri için ayrı imza alanları bulunmaktadır. Aşağıdaki imzalar, müşterinin platformun belirtilen tüm senaryoları başarıyla geçtiğini ve teslim alındığını teyit eder. Sheet bazlı detay sonuçlar için ilgili sayfayı, modül bazlı özet için '01 - Özet' sayfasını inceleyiniz.
B35: Tarodan — Proje Sorumlusu | F35: Müşteri — Yetkili
B36: Ad Soyad | F36: Ad Soyad
B37: Tarih | F37: Tarih
B38: İmza / Kaşe | F38: İmza / Kaşe

Sheet 01 - Özet
A1: TEST SONUÇLARI ÖZETİ
A4: # | B4: Sheet | C4: Açıklama | D4: Toplam | E4: Geçti | F4: Kaldı | G4: Bloke | H4: Yapılamadı | I4: N/A | J4: Beklemede
A5: 1 | B5: W01 - Auth Kayıt-Giriş | C5: W01 — Kayıt, Giriş ve Çıkış | D5: 13 | E5: =COUNTIF('W01 - Auth Kayıt-Giriş'!H4:H16,"Geçti") | F5: =COUNTIF('W01 - Auth Kayıt-Giriş'!H4:H16,"Kaldı") | G5: =COUNTIF('W01 - Auth Kayıt-Giriş'!H4:H16,"Bloke") | H5: =COUNTIF('W01 - Auth Kayıt-Giriş'!H4:H16,"Yapılamadı") | I5: =COUNTIF('W01 - Auth Kayıt-Giriş'!H4:H16,"N/A") | J5: =COUNTIF('W01 - Auth Kayıt-Giriş'!H4:H16,"Beklemede")
A6: 2 | B6: W02 - Şifre & Email Doğrulama | C6: W02 — Şifre Sıfırlama, E-posta ve OTP Doğrulama | D6: 13 | E6: =COUNTIF('W02 - Şifre & Email Doğrulama'!H4:H16,"Geçti") | F6: =COUNTIF('W02 - Şifre & Email Doğrulama'!H4:H16,"Kaldı") | G6: =COUNTIF('W02 - Şifre & Email Doğrulama'!H4:H16,"Bloke") | H6: =COUNTIF('W02 - Şifre & Email Doğrulama'!H4:H16,"Yapılamadı") | I6: =COUNTIF('W02 - Şifre & Email Doğrulama'!H4:H16,"N/A") | J6: =COUNTIF('W02 - Şifre & Email Doğrulama'!H4:H16,"Beklemede")
A7: 3 | B7: W03 - Anasayfa & Keşif | C7: W03 — Anasayfa, Listeleme, Arama, Kategori, Marka, Üretici | D7: 14 | E7: =COUNTIF('W03 - Anasayfa & Keşif'!H4:H17,"Geçti") | F7: =COUNTIF('W03 - Anasayfa & Keşif'!H4:H17,"Kaldı") | G7: =COUNTIF('W03 - Anasayfa & Keşif'!H4:H17,"Bloke") | H7: =COUNTIF('W03 - Anasayfa & Keşif'!H4:H17,"Yapılamadı") | I7: =COUNTIF('W03 - Anasayfa & Keşif'!H4:H17,"N/A") | J7: =COUNTIF('W03 - Anasayfa & Keşif'!H4:H17,"Beklemede")
A8: 4 | B8: W04 - Ürün Detay | C8: W04 — Ürün Detay Sayfası | D8: 14 | E8: =COUNTIF('W04 - Ürün Detay'!H4:H17,"Geçti") | F8: =COUNTIF('W04 - Ürün Detay'!H4:H17,"Kaldı") | G8: =COUNTIF('W04 - Ürün Detay'!H4:H17,"Bloke") | H8: =COUNTIF('W04 - Ürün Detay'!H4:H17,"Yapılamadı") | I8: =COUNTIF('W04 - Ürün Detay'!H4:H17,"N/A") | J8: =COUNTIF('W04 - Ürün Detay'!H4:H17,"Beklemede")
A9: 5 | B9: W05 - Sepet | C9: W05 — Sepet İşlemleri | D9: 10 | E9: =COUNTIF('W05 - Sepet'!H4:H13,"Geçti") | F9: =COUNTIF('W05 - Sepet'!H4:H13,"Kaldı") | G9: =COUNTIF('W05 - Sepet'!H4:H13,"Bloke") | H9: =COUNTIF('W05 - Sepet'!H4:H13,"Yapılamadı") | I9: =COUNTIF('W05 - Sepet'!H4:H13,"N/A") | J9: =COUNTIF('W05 - Sepet'!H4:H13,"Beklemede")
A10: 6 | B10: W06 - Misafir Checkout | C10: W06 — Misafir Checkout Akışı (E-posta OTP) | D10: 8 | E10: =COUNTIF('W06 - Misafir Checkout'!H4:H11,"Geçti") | F10: =COUNTIF('W06 - Misafir Checkout'!H4:H11,"Kaldı") | G10: =COUNTIF('W06 - Misafir Checkout'!H4:H11,"Bloke") | H10: =COUNTIF('W06 - Misafir Checkout'!H4:H11,"Yapılamadı") | I10: =COUNTIF('W06 - Misafir Checkout'!H4:H11,"N/A") | J10: =COUNTIF('W06 - Misafir Checkout'!H4:H11,"Beklemede")
A11: 7 | B11: W07 - Üye Checkout | C11: W07 — Üye Checkout Akışı | D11: 7 | E11: =COUNTIF('W07 - Üye Checkout'!H4:H10,"Geçti") | F11: =COUNTIF('W07 - Üye Checkout'!H4:H10,"Kaldı") | G11: =COUNTIF('W07 - Üye Checkout'!H4:H10,"Bloke") | H11: =COUNTIF('W07 - Üye Checkout'!H4:H10,"Yapılamadı") | I11: =COUNTIF('W07 - Üye Checkout'!H4:H10,"N/A") | J11: =COUNTIF('W07 - Üye Checkout'!H4:H10,"Beklemede")
A12: 8 | B12: W08 - Ödeme PayTR | C12: W08 — PayTR Ödeme Akışı | D12: 8 | E12: =COUNTIF('W08 - Ödeme PayTR'!H4:H11,"Geçti") | F12: =COUNTIF('W08 - Ödeme PayTR'!H4:H11,"Kaldı") | G12: =COUNTIF('W08 - Ödeme PayTR'!H4:H11,"Bloke") | H12: =COUNTIF('W08 - Ödeme PayTR'!H4:H11,"Yapılamadı") | I12: =COUNTIF('W08 - Ödeme PayTR'!H4:H11,"N/A") | J12: =COUNTIF('W08 - Ödeme PayTR'!H4:H11,"Beklemede")
A13: 9 | B13: W09 - Siparişlerim Listesi | C13: W09 — Siparişlerim (Alıcı) Listesi | D13: 6 | E13: =COUNTIF('W09 - Siparişlerim Listesi'!H4:H9,"Geçti") | F13: =COUNTIF('W09 - Siparişlerim Listesi'!H4:H9,"Kaldı") | G13: =COUNTIF('W09 - Siparişlerim Listesi'!H4:H9,"Bloke") | H13: =COUNTIF('W09 - Siparişlerim Listesi'!H4:H9,"Yapılamadı") | I13: =COUNTIF('W09 - Siparişlerim Listesi'!H4:H9,"N/A") | J13: =COUNTIF('W09 - Siparişlerim Listesi'!H4:H9,"Beklemede")
A14: 10 | B14: W10 - Sipariş Detay & Takip | C14: W10 — Sipariş Detayı, Kargo Takibi, Yorum | D14: 7 | E14: =COUNTIF('W10 - Sipariş Detay & Takip'!H4:H10,"Geçti") | F14: =COUNTIF('W10 - Sipariş Detay & Takip'!H4:H10,"Kaldı") | G14: =COUNTIF('W10 - Sipariş Detay & Takip'!H4:H10,"Bloke") | H14: =COUNTIF('W10 - Sipariş Detay & Takip'!H4:H10,"Yapılamadı") | I14: =COUNTIF('W10 - Sipariş Detay & Takip'!H4:H10,"N/A") | J14: =COUNTIF('W10 - Sipariş Detay & Takip'!H4:H10,"Beklemede")
A15: 11 | B15: W11 - Sipariş İptal | C15: W11 — Sipariş İptal Akışı | D15: 6 | E15: =COUNTIF('W11 - Sipariş İptal'!H4:H9,"Geçti") | F15: =COUNTIF('W11 - Sipariş İptal'!H4:H9,"Kaldı") | G15: =COUNTIF('W11 - Sipariş İptal'!H4:H9,"Bloke") | H15: =COUNTIF('W11 - Sipariş İptal'!H4:H9,"Yapılamadı") | I15: =COUNTIF('W11 - Sipariş İptal'!H4:H9,"N/A") | J15: =COUNTIF('W11 - Sipariş İptal'!H4:H9,"Beklemede")
A16: 12 | B16: W12 - İade Talebi | C16: W12 — İade ve Değişim Akışı | D16: 10 | E16: =COUNTIF('W12 - İade Talebi'!H4:H13,"Geçti") | F16: =COUNTIF('W12 - İade Talebi'!H4:H13,"Kaldı") | G16: =COUNTIF('W12 - İade Talebi'!H4:H13,"Bloke") | H16: =COUNTIF('W12 - İade Talebi'!H4:H13,"Yapılamadı") | I16: =COUNTIF('W12 - İade Talebi'!H4:H13,"N/A") | J16: =COUNTIF('W12 - İade Talebi'!H4:H13,"Beklemede")
A17: 13 | B17: W13 - Profil & Ayarlar | C17: W13 — Profil, Adres, Şifre, Ödeme Yöntemleri | D17: 12 | E17: =COUNTIF('W13 - Profil & Ayarlar'!H4:H15,"Geçti") | F17: =COUNTIF('W13 - Profil & Ayarlar'!H4:H15,"Kaldı") | G17: =COUNTIF('W13 - Profil & Ayarlar'!H4:H15,"Bloke") | H17: =COUNTIF('W13 - Profil & Ayarlar'!H4:H15,"Yapılamadı") | I17: =COUNTIF('W13 - Profil & Ayarlar'!H4:H15,"N/A") | J17: =COUNTIF('W13 - Profil & Ayarlar'!H4:H15,"Beklemede")
A18: 14 | B18: W14 - Satıcı İlan Yönetimi | C18: W14 — Satıcı: İlan Oluşturma ve Yönetimi | D18: 9 | E18: =COUNTIF('W14 - Satıcı İlan Yönetimi'!H4:H12,"Geçti") | F18: =COUNTIF('W14 - Satıcı İlan Yönetimi'!H4:H12,"Kaldı") | G18: =COUNTIF('W14 - Satıcı İlan Yönetimi'!H4:H12,"Bloke") | H18: =COUNTIF('W14 - Satıcı İlan Yönetimi'!H4:H12,"Yapılamadı") | I18: =COUNTIF('W14 - Satıcı İlan Yönetimi'!H4:H12,"N/A") | J18: =COUNTIF('W14 - Satıcı İlan Yönetimi'!H4:H12,"Beklemede")
A19: 15 | B19: W15 - Satıcı Sipariş Yönetimi | C19: W15 — Satıcı: Sipariş İşleme ve Kargolama | D19: 8 | E19: =COUNTIF('W15 - Satıcı Sipariş Yönetimi'!H4:H11,"Geçti") | F19: =COUNTIF('W15 - Satıcı Sipariş Yönetimi'!H4:H11,"Kaldı") | G19: =COUNTIF('W15 - Satıcı Sipariş Yönetimi'!H4:H11,"Bloke") | H19: =COUNTIF('W15 - Satıcı Sipariş Yönetimi'!H4:H11,"Yapılamadı") | I19: =COUNTIF('W15 - Satıcı Sipariş Yönetimi'!H4:H11,"N/A") | J19: =COUNTIF('W15 - Satıcı Sipariş Yönetimi'!H4:H11,"Beklemede")
A20: 16 | B20: W16 - Teklifler | C20: W16 — Teklif (Offer) Akışı | D20: 9 | E20: =COUNTIF('W16 - Teklifler'!H4:H12,"Geçti") | F20: =COUNTIF('W16 - Teklifler'!H4:H12,"Kaldı") | G20: =COUNTIF('W16 - Teklifler'!H4:H12,"Bloke") | H20: =COUNTIF('W16 - Teklifler'!H4:H12,"Yapılamadı") | I20: =COUNTIF('W16 - Teklifler'!H4:H12,"N/A") | J20: =COUNTIF('W16 - Teklifler'!H4:H12,"Beklemede")
A21: 17 | B21: W17 - Takas Trade | C21: W17 — Takas (Trade) Akışı | D21: 8 | E21: =COUNTIF('W17 - Takas Trade'!H4:H11,"Geçti") | F21: =COUNTIF('W17 - Takas Trade'!H4:H11,"Kaldı") | G21: =COUNTIF('W17 - Takas Trade'!H4:H11,"Bloke") | H21: =COUNTIF('W17 - Takas Trade'!H4:H11,"Yapılamadı") | I21: =COUNTIF('W17 - Takas Trade'!H4:H11,"N/A") | J21: =COUNTIF('W17 - Takas Trade'!H4:H11,"Beklemede")
A22: 18 | B22: W18 - Mesajlar | C22: W18 — Mesajlaşma | D22: 9 | E22: =COUNTIF('W18 - Mesajlar'!H4:H12,"Geçti") | F22: =COUNTIF('W18 - Mesajlar'!H4:H12,"Kaldı") | G22: =COUNTIF('W18 - Mesajlar'!H4:H12,"Bloke") | H22: =COUNTIF('W18 - Mesajlar'!H4:H12,"Yapılamadı") | I22: =COUNTIF('W18 - Mesajlar'!H4:H12,"N/A") | J22: =COUNTIF('W18 - Mesajlar'!H4:H12,"Beklemede")
A23: 19 | B23: W19 - Bildirimler | C23: W19 — Bildirim Merkezi | D23: 6 | E23: =COUNTIF('W19 - Bildirimler'!H4:H9,"Geçti") | F23: =COUNTIF('W19 - Bildirimler'!H4:H9,"Kaldı") | G23: =COUNTIF('W19 - Bildirimler'!H4:H9,"Bloke") | H23: =COUNTIF('W19 - Bildirimler'!H4:H9,"Yapılamadı") | I23: =COUNTIF('W19 - Bildirimler'!H4:H9,"N/A") | J23: =COUNTIF('W19 - Bildirimler'!H4:H9,"Beklemede")
A24: 20 | B24: W20 - Favori Wishlist Koleksiyo | C24: W20 — Favoriler, Wishlist, Koleksiyonlar | D24: 8 | E24: =COUNTIF('W20 - Favori Wishlist Koleksiyo'!H4:H11,"Geçti") | F24: =COUNTIF('W20 - Favori Wishlist Koleksiyo'!H4:H11,"Kaldı") | G24: =COUNTIF('W20 - Favori Wishlist Koleksiyo'!H4:H11,"Bloke") | H24: =COUNTIF('W20 - Favori Wishlist Koleksiyo'!H4:H11,"Yapılamadı") | I24: =COUNTIF('W20 - Favori Wishlist Koleksiyo'!H4:H11,"N/A") | J24: =COUNTIF('W20 - Favori Wishlist Koleksiyo'!H4:H11,"Beklemede")
A25: 21 | B25: W21 - Üyelik Membership | C25: W21 — Üyelik Planları | D25: 8 | E25: =COUNTIF('W21 - Üyelik Membership'!H4:H11,"Geçti") | F25: =COUNTIF('W21 - Üyelik Membership'!H4:H11,"Kaldı") | G25: =COUNTIF('W21 - Üyelik Membership'!H4:H11,"Bloke") | H25: =COUNTIF('W21 - Üyelik Membership'!H4:H11,"Yapılamadı") | I25: =COUNTIF('W21 - Üyelik Membership'!H4:H11,"N/A") | J25: =COUNTIF('W21 - Üyelik Membership'!H4:H11,"Beklemede")
A26: 22 | B26: W22 - Statik & Yasal | C26: W22 — Statik ve Yasal Sayfalar | D26: 10 | E26: =COUNTIF('W22 - Statik & Yasal'!H4:H13,"Geçti") | F26: =COUNTIF('W22 - Statik & Yasal'!H4:H13,"Kaldı") | G26: =COUNTIF('W22 - Statik & Yasal'!H4:H13,"Bloke") | H26: =COUNTIF('W22 - Statik & Yasal'!H4:H13,"Yapılamadı") | I26: =COUNTIF('W22 - Statik & Yasal'!H4:H13,"N/A") | J26: =COUNTIF('W22 - Statik & Yasal'!H4:H13,"Beklemede")
A27: 23 | B27: W23 - Mobil & Responsive | C27: W23 — Mobil Görünüm ve Responsive | D27: 6 | E27: =COUNTIF('W23 - Mobil & Responsive'!H4:H9,"Geçti") | F27: =COUNTIF('W23 - Mobil & Responsive'!H4:H9,"Kaldı") | G27: =COUNTIF('W23 - Mobil & Responsive'!H4:H9,"Bloke") | H27: =COUNTIF('W23 - Mobil & Responsive'!H4:H9,"Yapılamadı") | I27: =COUNTIF('W23 - Mobil & Responsive'!H4:H9,"N/A") | J27: =COUNTIF('W23 - Mobil & Responsive'!H4:H9,"Beklemede")
A28: 24 | B28: A01 - Admin Login & Yetki | C28: A01 — Admin Girişi ve Yetkilendirme | D28: 7 | E28: =COUNTIF('A01 - Admin Login & Yetki'!H4:H10,"Geçti") | F28: =COUNTIF('A01 - Admin Login & Yetki'!H4:H10,"Kaldı") | G28: =COUNTIF('A01 - Admin Login & Yetki'!H4:H10,"Bloke") | H28: =COUNTIF('A01 - Admin Login & Yetki'!H4:H10,"Yapılamadı") | I28: =COUNTIF('A01 - Admin Login & Yetki'!H4:H10,"N/A") | J28: =COUNTIF('A01 - Admin Login & Yetki'!H4:H10,"Beklemede")
A29: 25 | B29: A02 - Dashboard & Analitik | C29: A02 — Dashboard, Analytics, Raporlar | D29: 5 | E29: =COUNTIF('A02 - Dashboard & Analitik'!H4:H8,"Geçti") | F29: =COUNTIF('A02 - Dashboard & Analitik'!H4:H8,"Kaldı") | G29: =COUNTIF('A02 - Dashboard & Analitik'!H4:H8,"Bloke") | H29: =COUNTIF('A02 - Dashboard & Analitik'!H4:H8,"Yapılamadı") | I29: =COUNTIF('A02 - Dashboard & Analitik'!H4:H8,"N/A") | J29: =COUNTIF('A02 - Dashboard & Analitik'!H4:H8,"Beklemede")
A30: 26 | B30: A03 - Ürün Yönetimi | C30: A03 — Ürün Listesi, Detay, Onay, Yorum | D30: 10 | E30: =COUNTIF('A03 - Ürün Yönetimi'!H4:H13,"Geçti") | F30: =COUNTIF('A03 - Ürün Yönetimi'!H4:H13,"Kaldı") | G30: =COUNTIF('A03 - Ürün Yönetimi'!H4:H13,"Bloke") | H30: =COUNTIF('A03 - Ürün Yönetimi'!H4:H13,"Yapılamadı") | I30: =COUNTIF('A03 - Ürün Yönetimi'!H4:H13,"N/A") | J30: =COUNTIF('A03 - Ürün Yönetimi'!H4:H13,"Beklemede")
A31: 27 | B31: A04 - Katalog Master | C31: A04 — Kategori, Marka, Attribute, Tag, Üretici, Model | D31: 8 | E31: =COUNTIF('A04 - Katalog Master'!H4:H11,"Geçti") | F31: =COUNTIF('A04 - Katalog Master'!H4:H11,"Kaldı") | G31: =COUNTIF('A04 - Katalog Master'!H4:H11,"Bloke") | H31: =COUNTIF('A04 - Katalog Master'!H4:H11,"Yapılamadı") | I31: =COUNTIF('A04 - Katalog Master'!H4:H11,"N/A") | J31: =COUNTIF('A04 - Katalog Master'!H4:H11,"Beklemede")
A32: 28 | B32: A05 - Sipariş Yönetimi | C32: A05 — Admin: Sipariş Listesi ve İşlemler | D32: 8 | E32: =COUNTIF('A05 - Sipariş Yönetimi'!H4:H11,"Geçti") | F32: =COUNTIF('A05 - Sipariş Yönetimi'!H4:H11,"Kaldı") | G32: =COUNTIF('A05 - Sipariş Yönetimi'!H4:H11,"Bloke") | H32: =COUNTIF('A05 - Sipariş Yönetimi'!H4:H11,"Yapılamadı") | I32: =COUNTIF('A05 - Sipariş Yönetimi'!H4:H11,"N/A") | J32: =COUNTIF('A05 - Sipariş Yönetimi'!H4:H11,"Beklemede")
A33: 29 | B33: A06 - Ödeme & İade & Payout | C33: A06 — Admin: Ödeme, İade, Payout Yönetimi | D33: 9 | E33: =COUNTIF('A06 - Ödeme & İade & Payout'!H4:H12,"Geçti") | F33: =COUNTIF('A06 - Ödeme & İade & Payout'!H4:H12,"Kaldı") | G33: =COUNTIF('A06 - Ödeme & İade & Payout'!H4:H12,"Bloke") | H33: =COUNTIF('A06 - Ödeme & İade & Payout'!H4:H12,"Yapılamadı") | I33: =COUNTIF('A06 - Ödeme & İade & Payout'!H4:H12,"N/A") | J33: =COUNTIF('A06 - Ödeme & İade & Payout'!H4:H12,"Beklemede")
A34: 30 | B34: A07 - Komisyon Vergi Kargo | C34: A07 — Komisyon, Vergi, Kargo Ayarları | D34: 5 | E34: =COUNTIF('A07 - Komisyon Vergi Kargo'!H4:H8,"Geçti") | F34: =COUNTIF('A07 - Komisyon Vergi Kargo'!H4:H8,"Kaldı") | G34: =COUNTIF('A07 - Komisyon Vergi Kargo'!H4:H8,"Bloke") | H34: =COUNTIF('A07 - Komisyon Vergi Kargo'!H4:H8,"Yapılamadı") | I34: =COUNTIF('A07 - Komisyon Vergi Kargo'!H4:H8,"N/A") | J34: =COUNTIF('A07 - Komisyon Vergi Kargo'!H4:H8,"Beklemede")
A35: 31 | B35: A08 - Kullanıcı Yönetimi | C35: A08 — Kullanıcı Listesi ve Detayı | D35: 7 | E35: =COUNTIF('A08 - Kullanıcı Yönetimi'!H4:H10,"Geçti") | F35: =COUNTIF('A08 - Kullanıcı Yönetimi'!H4:H10,"Kaldı") | G35: =COUNTIF('A08 - Kullanıcı Yönetimi'!H4:H10,"Bloke") | H35: =COUNTIF('A08 - Kullanıcı Yönetimi'!H4:H10,"Yapılamadı") | I35: =COUNTIF('A08 - Kullanıcı Yönetimi'!H4:H10,"N/A") | J35: =COUNTIF('A08 - Kullanıcı Yönetimi'!H4:H10,"Beklemede")
A36: 32 | B36: A09 - Satıcı Başvuru & Performa | C36: A09 — Satıcı Başvuruları ve Performans | D36: 6 | E36: =COUNTIF('A09 - Satıcı Başvuru & Performa'!H4:H9,"Geçti") | F36: =COUNTIF('A09 - Satıcı Başvuru & Performa'!H4:H9,"Kaldı") | G36: =COUNTIF('A09 - Satıcı Başvuru & Performa'!H4:H9,"Bloke") | H36: =COUNTIF('A09 - Satıcı Başvuru & Performa'!H4:H9,"Yapılamadı") | I36: =COUNTIF('A09 - Satıcı Başvuru & Performa'!H4:H9,"N/A") | J36: =COUNTIF('A09 - Satıcı Başvuru & Performa'!H4:H9,"Beklemede")
A37: 33 | B37: A10 - Üyelik Tier Yönetimi | C37: A10 — Membership Tier Yönetimi | D37: 4 | E37: =COUNTIF('A10 - Üyelik Tier Yönetimi'!H4:H7,"Geçti") | F37: =COUNTIF('A10 - Üyelik Tier Yönetimi'!H4:H7,"Kaldı") | G37: =COUNTIF('A10 - Üyelik Tier Yönetimi'!H4:H7,"Bloke") | H37: =COUNTIF('A10 - Üyelik Tier Yönetimi'!H4:H7,"Yapılamadı") | I37: =COUNTIF('A10 - Üyelik Tier Yönetimi'!H4:H7,"N/A") | J37: =COUNTIF('A10 - Üyelik Tier Yönetimi'!H4:H7,"Beklemede")
A38: 34 | B38: A11 - İndirim & Kupon | C38: A11 — Discount / Coupon Yönetimi | D38: 9 | E38: =COUNTIF('A11 - İndirim & Kupon'!H4:H12,"Geçti") | F38: =COUNTIF('A11 - İndirim & Kupon'!H4:H12,"Kaldı") | G38: =COUNTIF('A11 - İndirim & Kupon'!H4:H12,"Bloke") | H38: =COUNTIF('A11 - İndirim & Kupon'!H4:H12,"Yapılamadı") | I38: =COUNTIF('A11 - İndirim & Kupon'!H4:H12,"N/A") | J38: =COUNTIF('A11 - İndirim & Kupon'!H4:H12,"Beklemede")
A39: 35 | B39: A12 - Email Şablonları | C39: A12 — E-posta Şablon Yönetimi | D39: 5 | E39: =COUNTIF('A12 - Email Şablonları'!H4:H8,"Geçti") | F39: =COUNTIF('A12 - Email Şablonları'!H4:H8,"Kaldı") | G39: =COUNTIF('A12 - Email Şablonları'!H4:H8,"Bloke") | H39: =COUNTIF('A12 - Email Şablonları'!H4:H8,"Yapılamadı") | I39: =COUNTIF('A12 - Email Şablonları'!H4:H8,"N/A") | J39: =COUNTIF('A12 - Email Şablonları'!H4:H8,"Beklemede")
A40: 36 | B40: A13 - Yorum & Moderasyon | C40: A13 — Yorum ve Moderasyon Kuyruğu | D40: 5 | E40: =COUNTIF('A13 - Yorum & Moderasyon'!H4:H8,"Geçti") | F40: =COUNTIF('A13 - Yorum & Moderasyon'!H4:H8,"Kaldı") | G40: =COUNTIF('A13 - Yorum & Moderasyon'!H4:H8,"Bloke") | H40: =COUNTIF('A13 - Yorum & Moderasyon'!H4:H8,"Yapılamadı") | I40: =COUNTIF('A13 - Yorum & Moderasyon'!H4:H8,"N/A") | J40: =COUNTIF('A13 - Yorum & Moderasyon'!H4:H8,"Beklemede")
A41: 37 | B41: A14 - Reklamlar | C41: A14 — Reklam ve Sponsorlu İçerik | D41: 4 | E41: =COUNTIF('A14 - Reklamlar'!H4:H7,"Geçti") | F41: =COUNTIF('A14 - Reklamlar'!H4:H7,"Kaldı") | G41: =COUNTIF('A14 - Reklamlar'!H4:H7,"Bloke") | H41: =COUNTIF('A14 - Reklamlar'!H4:H7,"Yapılamadı") | I41: =COUNTIF('A14 - Reklamlar'!H4:H7,"N/A") | J41: =COUNTIF('A14 - Reklamlar'!H4:H7,"Beklemede")
A42: 38 | B42: A15 - Takas Yönetimi | C42: A15 — Admin: Takas (Trade) Yönetimi | D42: 6 | E42: =COUNTIF('A15 - Takas Yönetimi'!H4:H9,"Geçti") | F42: =COUNTIF('A15 - Takas Yönetimi'!H4:H9,"Kaldı") | G42: =COUNTIF('A15 - Takas Yönetimi'!H4:H9,"Bloke") | H42: =COUNTIF('A15 - Takas Yönetimi'!H4:H9,"Yapılamadı") | I42: =COUNTIF('A15 - Takas Yönetimi'!H4:H9,"N/A") | J42: =COUNTIF('A15 - Takas Yönetimi'!H4:H9,"Beklemede")
A43: 39 | B43: A16 - Destek (Support) | C43: A16 — Destek Talepleri | D43: 6 | E43: =COUNTIF('A16 - Destek (Support)'!H4:H9,"Geçti") | F43: =COUNTIF('A16 - Destek (Support)'!H4:H9,"Kaldı") | G43: =COUNTIF('A16 - Destek (Support)'!H4:H9,"Bloke") | H43: =COUNTIF('A16 - Destek (Support)'!H4:H9,"Yapılamadı") | I43: =COUNTIF('A16 - Destek (Support)'!H4:H9,"N/A") | J43: =COUNTIF('A16 - Destek (Support)'!H4:H9,"Beklemede")
A44: 40 | B44: A17 - Roller & İzinler | C44: A17 — Rol ve İzin Yönetimi | D44: 6 | E44: =COUNTIF('A17 - Roller & İzinler'!H4:H9,"Geçti") | F44: =COUNTIF('A17 - Roller & İzinler'!H4:H9,"Kaldı") | G44: =COUNTIF('A17 - Roller & İzinler'!H4:H9,"Bloke") | H44: =COUNTIF('A17 - Roller & İzinler'!H4:H9,"Yapılamadı") | I44: =COUNTIF('A17 - Roller & İzinler'!H4:H9,"N/A") | J44: =COUNTIF('A17 - Roller & İzinler'!H4:H9,"Beklemede")
A45: 41 | B45: A18 - Platform Ayarları | C45: A18 — Genel Ayarlar, İlan, Takas, Mesaj, Üyelik, Ödeme | D45: 7 | E45: =COUNTIF('A18 - Platform Ayarları'!H4:H10,"Geçti") | F45: =COUNTIF('A18 - Platform Ayarları'!H4:H10,"Kaldı") | G45: =COUNTIF('A18 - Platform Ayarları'!H4:H10,"Bloke") | H45: =COUNTIF('A18 - Platform Ayarları'!H4:H10,"Yapılamadı") | I45: =COUNTIF('A18 - Platform Ayarları'!H4:H10,"N/A") | J45: =COUNTIF('A18 - Platform Ayarları'!H4:H10,"Beklemede")
A46: 42 | B46: A19 - Audit & Sistem Logları | C46: A19 — Audit ve Sistem Logları | D46: 4 | E46: =COUNTIF('A19 - Audit & Sistem Logları'!H4:H7,"Geçti") | F46: =COUNTIF('A19 - Audit & Sistem Logları'!H4:H7,"Kaldı") | G46: =COUNTIF('A19 - Audit & Sistem Logları'!H4:H7,"Bloke") | H46: =COUNTIF('A19 - Audit & Sistem Logları'!H4:H7,"Yapılamadı") | I46: =COUNTIF('A19 - Audit & Sistem Logları'!H4:H7,"N/A") | J46: =COUNTIF('A19 - Audit & Sistem Logları'!H4:H7,"Beklemede")
A47: 43 | B47: E01 - E2E Misafir Satın Al | C47: E01 — Uçtan Uca: Misafir Satın Alma → Teslimat | D47: 13 | E47: =COUNTIF('E01 - E2E Misafir Satın Al'!H4:H16,"Geçti") | F47: =COUNTIF('E01 - E2E Misafir Satın Al'!H4:H16,"Kaldı") | G47: =COUNTIF('E01 - E2E Misafir Satın Al'!H4:H16,"Bloke") | H47: =COUNTIF('E01 - E2E Misafir Satın Al'!H4:H16,"Yapılamadı") | I47: =COUNTIF('E01 - E2E Misafir Satın Al'!H4:H16,"N/A") | J47: =COUNTIF('E01 - E2E Misafir Satın Al'!H4:H16,"Beklemede")
A48: 44 | B48: E02 - E2E Üye İade | C48: E02 — Uçtan Uca: Üye Satın Alma → İade | D48: 9 | E48: =COUNTIF('E02 - E2E Üye İade'!H4:H12,"Geçti") | F48: =COUNTIF('E02 - E2E Üye İade'!H4:H12,"Kaldı") | G48: =COUNTIF('E02 - E2E Üye İade'!H4:H12,"Bloke") | H48: =COUNTIF('E02 - E2E Üye İade'!H4:H12,"Yapılamadı") | I48: =COUNTIF('E02 - E2E Üye İade'!H4:H12,"N/A") | J48: =COUNTIF('E02 - E2E Üye İade'!H4:H12,"Beklemede")
A49: 45 | B49: E03 - E2E Kargolanmadan İptal | C49: E03 — Uçtan Uca: Sipariş Kargolanmadan İptal | D49: 5 | E49: =COUNTIF('E03 - E2E Kargolanmadan İptal'!H4:H8,"Geçti") | F49: =COUNTIF('E03 - E2E Kargolanmadan İptal'!H4:H8,"Kaldı") | G49: =COUNTIF('E03 - E2E Kargolanmadan İptal'!H4:H8,"Bloke") | H49: =COUNTIF('E03 - E2E Kargolanmadan İptal'!H4:H8,"Yapılamadı") | I49: =COUNTIF('E03 - E2E Kargolanmadan İptal'!H4:H8,"N/A") | J49: =COUNTIF('E03 - E2E Kargolanmadan İptal'!H4:H8,"Beklemede")
A50: 46 | B50: E04 - E2E Satıcı Yolculuğu | C50: E04 — Uçtan Uca: Satıcı: İlan → Sipariş → Kargo → Payout | D50: 9 | E50: =COUNTIF('E04 - E2E Satıcı Yolculuğu'!H4:H12,"Geçti") | F50: =COUNTIF('E04 - E2E Satıcı Yolculuğu'!H4:H12,"Kaldı") | G50: =COUNTIF('E04 - E2E Satıcı Yolculuğu'!H4:H12,"Bloke") | H50: =COUNTIF('E04 - E2E Satıcı Yolculuğu'!H4:H12,"Yapılamadı") | I50: =COUNTIF('E04 - E2E Satıcı Yolculuğu'!H4:H12,"N/A") | J50: =COUNTIF('E04 - E2E Satıcı Yolculuğu'!H4:H12,"Beklemede")
A51: 47 | B51: E05 - E2E Teklif Akışı | C51: E05 — Uçtan Uca: Teklif → Karşı Teklif → Kabul → Ödeme | D51: 5 | E51: =COUNTIF('E05 - E2E Teklif Akışı'!H4:H8,"Geçti") | F51: =COUNTIF('E05 - E2E Teklif Akışı'!H4:H8,"Kaldı") | G51: =COUNTIF('E05 - E2E Teklif Akışı'!H4:H8,"Bloke") | H51: =COUNTIF('E05 - E2E Teklif Akışı'!H4:H8,"Yapılamadı") | I51: =COUNTIF('E05 - E2E Teklif Akışı'!H4:H8,"N/A") | J51: =COUNTIF('E05 - E2E Teklif Akışı'!H4:H8,"Beklemede")
A52: 48 | B52: E06 - E2E Takas | C52: E06 — Uçtan Uca: Takas (Trade) Tam Akışı | D52: 6 | E52: =COUNTIF('E06 - E2E Takas'!H4:H9,"Geçti") | F52: =COUNTIF('E06 - E2E Takas'!H4:H9,"Kaldı") | G52: =COUNTIF('E06 - E2E Takas'!H4:H9,"Bloke") | H52: =COUNTIF('E06 - E2E Takas'!H4:H9,"Yapılamadı") | I52: =COUNTIF('E06 - E2E Takas'!H4:H9,"N/A") | J52: =COUNTIF('E06 - E2E Takas'!H4:H9,"Beklemede")
A53: 49 | B53: E07 - E2E Üyelik | C53: E07 — Uçtan Uca: Üyelik Satın Al → Yenile → İptal | D53: 7 | E53: =COUNTIF('E07 - E2E Üyelik'!H4:H10,"Geçti") | F53: =COUNTIF('E07 - E2E Üyelik'!H4:H10,"Kaldı") | G53: =COUNTIF('E07 - E2E Üyelik'!H4:H10,"Bloke") | H53: =COUNTIF('E07 - E2E Üyelik'!H4:H10,"Yapılamadı") | I53: =COUNTIF('E07 - E2E Üyelik'!H4:H10,"N/A") | J53: =COUNTIF('E07 - E2E Üyelik'!H4:H10,"Beklemede")
A54: 50 | B54: E08 - E2E Şifre Sıfırlama | C54: E08 — Uçtan Uca: Şifre Unuttum → Sıfırla → Giriş | D54: 5 | E54: =COUNTIF('E08 - E2E Şifre Sıfırlama'!H4:H8,"Geçti") | F54: =COUNTIF('E08 - E2E Şifre Sıfırlama'!H4:H8,"Kaldı") | G54: =COUNTIF('E08 - E2E Şifre Sıfırlama'!H4:H8,"Bloke") | H54: =COUNTIF('E08 - E2E Şifre Sıfırlama'!H4:H8,"Yapılamadı") | I54: =COUNTIF('E08 - E2E Şifre Sıfırlama'!H4:H8,"N/A") | J54: =COUNTIF('E08 - E2E Şifre Sıfırlama'!H4:H8,"Beklemede")
A55: 51 | B55: E09 - E2E Stok Yarış | C55: E09 — Uçtan Uca: Stok Race Condition Testi | D55: 4 | E55: =COUNTIF('E09 - E2E Stok Yarış'!H4:H7,"Geçti") | F55: =COUNTIF('E09 - E2E Stok Yarış'!H4:H7,"Kaldı") | G55: =COUNTIF('E09 - E2E Stok Yarış'!H4:H7,"Bloke") | H55: =COUNTIF('E09 - E2E Stok Yarış'!H4:H7,"Yapılamadı") | I55: =COUNTIF('E09 - E2E Stok Yarış'!H4:H7,"N/A") | J55: =COUNTIF('E09 - E2E Stok Yarış'!H4:H7,"Beklemede")
A56: 52 | B56: E10 - E2E Bildirim Akışı | C56: E10 — Uçtan Uca: Tüm Bildirim Kanalları Doğrulama | D56: 8 | E56: =COUNTIF('E10 - E2E Bildirim Akışı'!H4:H11,"Geçti") | F56: =COUNTIF('E10 - E2E Bildirim Akışı'!H4:H11,"Kaldı") | G56: =COUNTIF('E10 - E2E Bildirim Akışı'!H4:H11,"Bloke") | H56: =COUNTIF('E10 - E2E Bildirim Akışı'!H4:H11,"Yapılamadı") | I56: =COUNTIF('E10 - E2E Bildirim Akışı'!H4:H11,"N/A") | J56: =COUNTIF('E10 - E2E Bildirim Akışı'!H4:H11,"Beklemede")
A57: 53 | B57: C01 - Mail Bildirim Listesi | C57: C01 — Tüm Mail Bildirimleri Matrisi | D57: 28 | E57: =COUNTIF('C01 - Mail Bildirim Listesi'!H4:H31,"Geçti") | F57: =COUNTIF('C01 - Mail Bildirim Listesi'!H4:H31,"Kaldı") | G57: =COUNTIF('C01 - Mail Bildirim Listesi'!H4:H31,"Bloke") | H57: =COUNTIF('C01 - Mail Bildirim Listesi'!H4:H31,"Yapılamadı") | I57: =COUNTIF('C01 - Mail Bildirim Listesi'!H4:H31,"N/A") | J57: =COUNTIF('C01 - Mail Bildirim Listesi'!H4:H31,"Beklemede")
A58: 54 | B58: C02 - Push InApp Bildirim | C58: C02 — Push ve In-App Bildirim Doğrulamaları | D58: 5 | E58: =COUNTIF('C02 - Push InApp Bildirim'!H4:H8,"Geçti") | F58: =COUNTIF('C02 - Push InApp Bildirim'!H4:H8,"Kaldı") | G58: =COUNTIF('C02 - Push InApp Bildirim'!H4:H8,"Bloke") | H58: =COUNTIF('C02 - Push InApp Bildirim'!H4:H8,"Yapılamadı") | I58: =COUNTIF('C02 - Push InApp Bildirim'!H4:H8,"N/A") | J58: =COUNTIF('C02 - Push InApp Bildirim'!H4:H8,"Beklemede")
A59: 55 | B59: C03 - Cron Otomatik İşler | C59: C03 — Cron / Scheduled Job Doğrulamaları | D59: 14 | E59: =COUNTIF('C03 - Cron Otomatik İşler'!H4:H17,"Geçti") | F59: =COUNTIF('C03 - Cron Otomatik İşler'!H4:H17,"Kaldı") | G59: =COUNTIF('C03 - Cron Otomatik İşler'!H4:H17,"Bloke") | H59: =COUNTIF('C03 - Cron Otomatik İşler'!H4:H17,"Yapılamadı") | I59: =COUNTIF('C03 - Cron Otomatik İşler'!H4:H17,"N/A") | J59: =COUNTIF('C03 - Cron Otomatik İşler'!H4:H17,"Beklemede")
A60: 56 | B60: C04 - Edge Cases | C60: C04 — Edge Cases ve Hata Senaryoları | D60: 13 | E60: =COUNTIF('C04 - Edge Cases'!H4:H16,"Geçti") | F60: =COUNTIF('C04 - Edge Cases'!H4:H16,"Kaldı") | G60: =COUNTIF('C04 - Edge Cases'!H4:H16,"Bloke") | H60: =COUNTIF('C04 - Edge Cases'!H4:H16,"Yapılamadı") | I60: =COUNTIF('C04 - Edge Cases'!H4:H16,"N/A") | J60: =COUNTIF('C04 - Edge Cases'!H4:H16,"Beklemede")
A61: 57 | B61: C05 - Performans Yük | C61: C05 — Performans ve Yük (Smoke) | D61: 5 | E61: =COUNTIF('C05 - Performans Yük'!H4:H8,"Geçti") | F61: =COUNTIF('C05 - Performans Yük'!H4:H8,"Kaldı") | G61: =COUNTIF('C05 - Performans Yük'!H4:H8,"Bloke") | H61: =COUNTIF('C05 - Performans Yük'!H4:H8,"Yapılamadı") | I61: =COUNTIF('C05 - Performans Yük'!H4:H8,"N/A") | J61: =COUNTIF('C05 - Performans Yük'!H4:H8,"Beklemede")
A62: 58 | B62: C06 - Güvenlik | C62: C06 — Güvenlik ve Yetki Sınırları | D62: 10 | E62: =COUNTIF('C06 - Güvenlik'!H4:H13,"Geçti") | F62: =COUNTIF('C06 - Güvenlik'!H4:H13,"Kaldı") | G62: =COUNTIF('C06 - Güvenlik'!H4:H13,"Bloke") | H62: =COUNTIF('C06 - Güvenlik'!H4:H13,"Yapılamadı") | I62: =COUNTIF('C06 - Güvenlik'!H4:H13,"N/A") | J62: =COUNTIF('C06 - Güvenlik'!H4:H13,"Beklemede")
A63: 59 | B63: C08 - Escrow Release Kuralları | C63: C08 — Escrow / Para Release Kuralları (KRİTİK) | D63: 18 | E63: =COUNTIF('C08 - Escrow Release Kuralları'!H4:H21,"Geçti") | F63: =COUNTIF('C08 - Escrow Release Kuralları'!H4:H21,"Kaldı") | G63: =COUNTIF('C08 - Escrow Release Kuralları'!H4:H21,"Bloke") | H63: =COUNTIF('C08 - Escrow Release Kuralları'!H4:H21,"Yapılamadı") | I63: =COUNTIF('C08 - Escrow Release Kuralları'!H4:H21,"N/A") | J63: =COUNTIF('C08 - Escrow Release Kuralları'!H4:H21,"Beklemede")
A64: 60 | B64: C07 - Tarayıcı Cihaz Uyumu | C64: C07 — Tarayıcı ve Cihaz Uyum Matrisi | D64: 8 | E64: =COUNTIF('C07 - Tarayıcı Cihaz Uyumu'!H4:H11,"Geçti") | F64: =COUNTIF('C07 - Tarayıcı Cihaz Uyumu'!H4:H11,"Kaldı") | G64: =COUNTIF('C07 - Tarayıcı Cihaz Uyumu'!H4:H11,"Bloke") | H64: =COUNTIF('C07 - Tarayıcı Cihaz Uyumu'!H4:H11,"Yapılamadı") | I64: =COUNTIF('C07 - Tarayıcı Cihaz Uyumu'!H4:H11,"N/A") | J64: =COUNTIF('C07 - Tarayıcı Cihaz Uyumu'!H4:H11,"Beklemede")
B65: TOPLAM | D65: =SUM(D5:D64) | E65: =SUM(E5:E64) | F65: =SUM(F5:F64) | G65: =SUM(G5:G64) | H65: =SUM(H5:H64) | I65: =SUM(I5:I64) | J65: =SUM(J5:J64)
B68: Toplam Senaryo | C68: =D65
B69: Geçti % | C69: =E65/D65
B70: Kaldı % | C70: =F65/D65
B71: Beklemede % | C71: =J65/D65
B72: Tamamlanma % | C72: =(D65-J65)/D65
B77: MÜŞTERİ ONAYI
B78: Yukarıdaki sheet bazlı test sonuçlarını ve detaylı senaryoları inceledim. Tarodan platformunun (web ve admin) belirtilen tüm fonksiyonları sözleşmeye uygun şekilde teslim edilmiştir.
B81: Tarodan — Proje Sorumlusu | G81: Müşteri — Yetkili
B82: Ad Soyad | G82: Ad Soyad
B83: Tarih | G83: Tarih
B84: İmza | G84: İmza

Sheet 02 - Yönergeler
A1: TEST PLANI KULLANIM YÖNERGELERİ
B4: Belge Yapısı
B5: 00 - Kapak | C5: Proje bilgileri, doküman versiyonu ve resmi imza alanı.
B6: 01 - Özet | C6: Tüm sheet'lerin sonuç dağılımı (otomatik formüllerle güncellenir).
B7: 02 - Yönergeler | C7: Bu sayfa: kullanım, kolon açıklamaları, durum kodları.
B8: W## - Web | C8: Web platformu test sayfaları (kullanıcı tarafı).
B9: A## - Admin | C9: Admin paneli test sayfaları.
B10: E## - E2E | C10: Uçtan uca (end-to-end) iş akışı senaryoları.
B11: C## - Cross | C11: Mail bildirimleri, otomatik işler, edge case, güvenlik gibi yatay konular.
B12: ZZ - İmza | C12: Tüm sheet sonuçlarının özet imza ve kabul beyanı sayfası.
B14: Sütun Açıklamaları
B15: Test ID | C15: Sheet bazlı tekil tanımlayıcı (örn. W01-005).
B16: Modül / Sayfa | C16: Senaryonun ait olduğu sayfa veya iş alanı.
B17: Senaryo / Test Adı | C17: Yapılacak testin başlığı (kısa).
B18: Önkoşullar | C18: Test başlamadan önce sağlanması gereken durum.
B19: Adımlar | C19: Test eden tarafından sırayla uygulanacak adımlar.
B20: Beklenen Sonuç | C20: Adımlar tamamlandığında olması gereken davranış.
B21: Gerçek Sonuç | C21: Test eden gözlemini buraya yazar.
B22: Durum | C22: Beklemede / Geçti / Kaldı / Bloke / Yapılamadı / N/A — dropdown.
B23: Test Eden | C23: Senaryoyu yürüten kişinin adı.
B24: Test Tarihi | C24: Senaryonun çalıştırıldığı tarih (gg.aa.yyyy).
B25: Tarayıcı / Cihaz | C25: Hangi tarayıcı veya cihazla test edildi — dropdown.
B26: Öncelik | C26: Kritik / Yüksek / Orta / Düşük — senaryo önemi.
B27: Notlar / Hata Linki | C27: Bug tracker linki, ekran görüntüsü adı, ek not.
B29: Durum Kodları
B30: Beklemede | C30: Henüz test edilmedi (varsayılan).
B31: Geçti | C31: Beklenen sonuç eksiksiz gözlemlendi.
B32: Kaldı | C32: Beklenen sonuç gözlemlenmedi → bug. Notlar alanına detay/link eklenmeli.
B33: Bloke | C33: Başka bir hata veya eksik nedeniyle test başlatılamadı/sürdürülemedi.
B34: Yapılamadı | C34: Test ortamında ilgili özellik henüz hazır değil.
B35: N/A | C35: Bu projede uygulanmıyor (örn. opsiyonel feature kapsam dışı).
B37: Test Süreci
B38: 1. | C38: Tarodan ekibi tüm senaryoları yürütür ve sonuçları işaretler.
B39: 2. | C39: Müşteri kendi ortamında aynı senaryoları yürütür ve doğrular.
B40: 3. | C40: Bug bulunursa 'Notlar' kolonuna issue linki/açıklaması yazılır.
B41: 4. | C41: Tüm 'Kaldı' senaryolar için düzeltme yapılıp yeniden test edilir.
B42: 5. | C42: Sheet sonundaki imza alanları her iki taraf tarafından imzalanır.
B43: 6. | C43: Kapak ve 'ZZ - İmza' sayfaları nihai onay olarak imzalanır.

Sheet W01 - Auth Kayıt-Giriş
A1: W01 — Kayıt, Giriş ve Çıkış
A2: Bireysel kayıt, kurumsal kayıt, giriş, çıkış ve form doğrulamaları.
A3: Test ID | B3: Modül / Sayfa | C3: Senaryo / Test Adı | D3: Önkoşullar | E3: Adımlar (numaralı) | F3: Beklenen Sonuç | G3: Gerçek Sonuç | H3: Durum | I3: Test Eden | J3: Test Tarihi | K3: Tarayıcı / Cihaz | L3: Öncelik | M3: Notlar / Hata Linki
A4: W01-001 | B4: W01 | C4: Yeni bireysel kullanıcı kaydı (geçerli bilgilerle) | D4: Hiç kayıt olmamış e-posta hazır. | E4: 1. /register sayfasına git 2. Ad, soyad, e-posta, telefon, doğum tarihi, şifre gir 3. KVKK ve sözleşme onayını işaretle 4. Kayıt Ol'a bas | F4: Hesap oluşturulur, e-posta doğrulama maili tetiklenir, kullanıcı yönlendirilir. | H4: Beklemede | L4: Kritik
A5: W01-002 | B5: W01 | C5: Aynı e-posta ile ikinci kez kayıt | D5: Daha önce kayıtlı bir e-posta var. | E5: 1. /register sayfasına git 2. Mevcut e-postayı gir, formu doldur 3. Kayıt Ol'a bas | F5: “Bu e-posta zaten kullanılıyor” hatası, giriş sayfasına link gösterilir. | H5: Beklemede | L5: Yüksek
A6: W01-003 | B6: W01 | C6: Şifre güvenlik kuralı (zayıf şifre reddi) | D6: — | E6: 1. Kayıt formunu doldur, şifreye '123456' gir 2. Kayıt Ol'a bas | F6: Şifre yetersiz hatası; kabul edilmiyor. | H6: Beklemede | L6: Yüksek
A7: W01-004 | B7: W01 | C7: Telefon numarası formatı doğrulama | D7: — | E7: 1. Telefonu '12345' olarak gir, formu gönder | F7: Geçersiz telefon hatası; submit engellenir. | H7: Beklemede | L7: Orta
A8: W01-005 | B8: W01 | C8: KVKK onayı işaretlenmeden kayıt denenmesi | D8: — | E8: 1. Tüm alanları doldur, KVKK onayını işaretleme 2. Kayıt Ol'a bas | F8: Form gönderilemez; KVKK uyarısı gösterilir. | H8: Beklemede | L8: Yüksek
A9: W01-006 | B9: W01 | C9: Kurumsal (business) hesap kaydı | D9: — | E9: 1. /register/business sayfasına git 2. Şirket adı, vergi numarası, KVKK onayı, kişisel bilgiler gir 3. Kayıt Ol'a bas | F9: Kurumsal hesap oluşturulur, satıcı uygunluk başvurusu kuyruğa alınır. | H9: Beklemede | L9: Yüksek
A10: W01-007 | B10: W01 | C10: Vergi numarası geçersiz format | D10: — | E10: 1. Kurumsal kayıtta vergi numarasına 'abc' gir 2. Submit | F10: Vergi numarası format hatası gösterilir. | H10: Beklemede | L10: Orta
A11: W01-008 | B11: W01 | C11: Geçerli bilgilerle giriş | D11: Doğrulanmış kullanıcı. | E11: 1. /login sayfasına git 2. E-posta + şifre gir 3. Giriş Yap'a bas | F11: Anasayfa veya yönlendirme hedefine giriş yapılmış olarak ulaşılır; üst menüde profil görünür. | H11: Beklemede | L11: Kritik
A12: W01-009 | B12: W01 | C12: Yanlış şifre ile giriş | D12: Mevcut hesap. | E12: 1. E-postayı doğru, şifreyi yanlış gir 2. Giriş Yap'a bas | F12: Hata mesajı; sayfa giriş sayfasında kalır; sayaç artar. | H12: Beklemede | L12: Yüksek
A13: W01-010 | B13: W01 | C13: 5 başarısız denemeden sonra hesap kilidi | D13: Aynı kullanıcıya 5 yanlış şifre denemesi yapıldı. | E13: 1. 6. denemeyi yap | F13: Hesap geçici kilitlenir (30 dk) veya rate-limit uyarısı verilir. | H13: Beklemede | L13: Yüksek
A14: W01-011 | B14: W01 | C14: Çıkış (logout) | D14: Giriş yapılmış oturum. | E14: 1. Profil menüsünden 'Çıkış'a bas | F14: Oturum sonlandırılır, anasayfaya yönlendirilir, korumalı sayfalara erişim engellenir. | H14: Beklemede | L14: Yüksek
A15: W01-012 | B15: W01 | C15: Korumalı sayfaya misafir erişimi | D15: Çıkış yapılmış. | E15: 1. /orders veya /profile adresine git | F15: /login?redirect=... adresine yönlendirme yapılır; giriş sonrası asıl sayfaya döner. | H15: Beklemede | L15: Kritik
A16: W01-013 | B16: W01 | C16: Beni Hatırla seçeneği | D16: — | E16: 1. Beni Hatırla işaretli giriş yap 2. Tarayıcıyı kapatıp yeniden aç | F16: Oturum hala açıktır. | H16: Beklemede | L16: Orta
A19: Bu sayfadaki tüm senaryolar test edilmiş ve sonuçlar yukarıda işaretlenmiştir.
A20: Test Eden (Tarodan) | D20: Tarih | G20: Onaylayan (Müşteri) | J20: Tarih

Sheet W02 - Şifre & Email Doğrulama
A1: W02 — Şifre Sıfırlama, E-posta ve OTP Doğrulama
A2: Şifre unuttum akışı, e-posta doğrulama, misafir e-posta OTP, rate-limit.
A3: Test ID | B3: Modül / Sayfa | C3: Senaryo / Test Adı | D3: Önkoşullar | E3: Adımlar (numaralı) | F3: Beklenen Sonuç | G3: Gerçek Sonuç | H3: Durum | I3: Test Eden | J3: Test Tarihi | K3: Tarayıcı / Cihaz | L3: Öncelik | M3: Notlar / Hata Linki
A4: W02-001 | B4: W02 | C4: Şifremi Unuttum maili gönderme | D4: Kayıtlı e-posta. | E4: 1. /forgot-password sayfasına git 2. E-postayı gir, Gönder'e bas | F4: “Mail gönderildi” bilgisi; e-postaya 1 saat geçerli sıfırlama linki düşer. | H4: Beklemede | L4: Kritik
A5: W02-002 | B5: W02 | C5: Şifre sıfırlama linkine tıklama (geçerli token) | D5: Yeni gönderilmiş sıfırlama maili. | E5: 1. Maildeki linke tıkla 2. /reset-password açılır 3. Yeni şifre + tekrar gir, Gönder | F5: Şifre güncellenir; giriş sayfasına yönlendirir; yeni şifre ile giriş çalışır. | H5: Beklemede | L5: Kritik
A6: W02-003 | B6: W02 | C6: Süresi dolmuş token ile sıfırlama | D6: 1 saatten eski token. | E6: 1. Eski token'lı linke tıkla | F6: “Link süresi dolmuş” mesajı; yeniden gönder seçeneği sunulur. | H6: Beklemede | L6: Yüksek
A7: W02-004 | B7: W02 | C7: Aynı token ile ikinci kez sıfırlama | D7: Daha önce kullanılmış token. | E7: 1. Aynı linke ikinci kez tıkla | F7: Token tek kullanımlık; geçersiz token mesajı. | H7: Beklemede | L7: Yüksek
A8: W02-005 | B8: W02 | C8: Kayıtsız e-posta ile şifre sıfırlama isteği | D8: — | E8: 1. Sistemde olmayan bir e-posta gir, Gönder | F8: Kullanıcı yanıltma için aynı genel mesaj gösterilir; mail gönderilmez (enumeration koruması). | H8: Beklemede | L8: Yüksek
A9: W02-006 | B9: W02 | C9: Yeni kullanıcı e-posta doğrulama maili | D9: Yeni kayıtlı, doğrulanmamış kullanıcı. | E9: 1. Maildeki doğrulama linkine tıkla | F9: E-posta doğrulanır, profilde 'doğrulandı' rozeti görünür. | H9: Beklemede | L9: Kritik
A10: W02-007 | B10: W02 | C10: Doğrulanmamış kullanıcı satışa çıkmaya çalışır | D10: E-posta doğrulanmamış. | E10: 1. /listings/new veya /sell sayfasına git | F10: “Önce e-postanızı doğrulayın” uyarısı; doğrulama maili tekrar gönder linki. | H10: Beklemede | L10: Yüksek
A11: W02-008 | B11: W02 | C11: Misafir checkout — e-posta OTP gönder | D11: Misafir checkout adımına gelinmiş. | E11: 1. E-postayı gir 2. 'Kod Gönder' butonuna bas | F11: “Kod gönderildi” bilgisi; e-postaya 6 haneli kod düşer (TTL ~10dk). | H11: Beklemede | L11: Kritik
A12: W02-009 | B12: W02 | C12: Misafir OTP — geçerli kod ile doğrulama | D12: OTP gönderilmiş. | E12: 1. 6 haneli doğru kodu gir 2. Doğrula | F12: Doğrulama başarılı; ödeme adımına geçilir. | H12: Beklemede | L12: Kritik
A13: W02-010 | B13: W02 | C13: Misafir OTP — yanlış kod denemesi | D13: OTP gönderilmiş. | E13: 1. Yanlış kod gir, Doğrula | F13: Hata mesajı; deneme hakkı azalır. | H13: Beklemede | L13: Orta
A14: W02-011 | B14: W02 | C14: Misafir OTP — 5 yanlış denemeden sonra rate-limit | D14: 5 yanlış deneme yapıldı. | E14: 1. 6. denemeyi yap | F14: “Çok fazla deneme, lütfen sonra tekrar deneyin” mesajı; 1 saat blok. | H14: Beklemede | L14: Yüksek
A15: W02-012 | B15: W02 | C15: OTP yeniden gönder cooldown | D15: Az önce kod gönderildi. | E15: 1. Hemen yeniden 'Kod Gönder'e bas | F15: 60 sn cooldown; sayaç görünür. | H15: Beklemede | L15: Orta
A16: W02-013 | B16: W02 | C16: Süresi dolmuş OTP | D16: 10+ dakika beklenmiş. | E16: 1. Eski kodu gir | F16: “Kodun süresi doldu, yeniden talep edin.” | H16: Beklemede | L16: Orta
A19: Bu sayfadaki tüm senaryolar test edilmiş ve sonuçlar yukarıda işaretlenmiştir.
A20: Test Eden (Tarodan) | D20: Tarih | G20: Onaylayan (Müşteri) | J20: Tarih

Sheet W03 - Anasayfa & Keşif
A1: W03 — Anasayfa, Listeleme, Arama, Kategori, Marka, Üretici
A2: Misafir/üye gezinme, filtreleme, sıralama, sonuç listeleri.
A3: Test ID | B3: Modül / Sayfa | C3: Senaryo / Test Adı | D3: Önkoşullar | E3: Adımlar (numaralı) | F3: Beklenen Sonuç | G3: Gerçek Sonuç | H3: Durum | I3: Test Eden | J3: Test Tarihi | K3: Tarayıcı / Cihaz | L3: Öncelik | M3: Notlar / Hata Linki
A4: W03-001 | B4: W03 | C4: Anasayfa açılışı | D4: — | E4: 1. / adresine git | F4: Hero, marka carousel, indirimli ürünler, popüler ilanlar, koleksiyonlar yüklenir; kırılma yok. | H4: Beklemede | L4: Kritik
A5: W03-002 | B5: W03 | C5: Genel arama (üst bar) | D5: — | E5: 1. Üst arama kutusuna anahtar kelime gir, Enter | F5: /search sayfası açılır, sonuçlar relevansa göre listelenir. | H5: Beklemede | L5: Orta
A6: W03-003 | B6: W03 | C6: Boş sonuçlu arama | D6: — | E6: 1. Var olmayan bir kelime ara | F6: “Sonuç bulunamadı” boş durum kartı; öneriler gösterilir. | H6: Beklemede | L6: Orta
A7: W03-004 | B7: W03 | C7: Kategori sayfasını açma | D7: Aktif bir kategori var. | E7: 1. /category/[slug] aç | F7: Kategori başlığı, ürünler ve filtre paneli görünür. | H7: Beklemede | L7: Orta
A8: W03-005 | B8: W03 | C8: Filtre uygulama (marka, fiyat, durum) | D8: Kategori sayfasında. | E8: 1. Filtreden marka seç 2. Min-max fiyat gir 3. Durum seç | F8: Liste gerçek zamanlı güncellenir; URL'ye filtre query'si eklenir. | H8: Beklemede | L8: Orta
A9: W03-006 | B9: W03 | C9: Filtreleri temizle | D9: Birkaç filtre aktif. | E9: 1. 'Filtreleri Temizle'ye bas | F9: Tüm filtreler kalkar, tüm liste döner. | H9: Beklemede | L9: Orta
A10: W03-007 | B10: W03 | C10: Sıralama (yeni, popüler, fiyat artan/azalan) | D10: Liste sayfası açık. | E10: 1. Sıralama dropdown'undan farklı seçenekleri dene | F10: Liste her seçimde doğru sıralanır. | H10: Beklemede | L10: Orta
A11: W03-008 | B11: W03 | C11: Grid / liste görünüm değiştirme | D11: — | E11: 1. Grid → Liste, Liste → Grid butonlarına bas | F11: Görünüm değişir, kullanıcı tercihi sayfa yenilense bile (mümkünse) korunur. | H11: Beklemede | L11: Orta
A12: W03-009 | B12: W03 | C12: Sayfalama (pagination) | D12: Çok ürünlü kategori. | E12: 1. Alttan ileri/geri sayfa butonlarını kullan | F12: Sayfa numarası ve URL güncellenir; ürünler değişir; scroll üste döner. | H12: Beklemede | L12: Orta
A13: W03-010 | B13: W03 | C13: Marka detay sayfası | D13: — | E13: 1. /brands listesinden bir markaya tıkla | F13: /brands/[slug] açılır; markanın ürünleri görünür. | H13: Beklemede | L13: Orta
A14: W03-011 | B14: W03 | C14: Üretici detay sayfası (TR slug) | D14: — | E14: 1. /ureticiler aç, bir üreticiye tıkla | F14: /ureticiler/[slug] açılır. | H14: Beklemede | L14: Orta
A15: W03-012 | B15: W03 | C15: Model detay sayfası | D15: — | E15: 1. /models aç, bir modele tıkla | F15: /models/[slug] açılır. | H15: Beklemede | L15: Orta
... A17: W03-014 | B17: W03 | C17: Son aramalar | D17: Birkaç kez arama yapılmış. | E17: 1. Arama kutusuna odaklan | F17: Son arama önerileri dropdown'da listelenir. | H17: Beklemede | L17: Orta
A20: Bu sayfadaki tüm senaryolar test edilmiş ve sonuçlar yukarıda işaretlenmiştir.
A21: Test Eden (Tarodan) | D21: Tarih | G21: Onaylayan (Müşteri) | J21: Tarih

Sheet W04 - Ürün Detay
A1: W04 — Ürün Detay Sayfası
A2: Ürün galerisi, satıcı bilgisi, sepete ekleme, teklif, mesaj, favori.
A3: Test ID | B3: Modül / Sayfa | C3: Senaryo / Test Adı | D3: Önkoşullar | E3: Adımlar (numaralı) | F3: Beklenen Sonuç | G3: Gerçek Sonuç | H3: Durum | I3: Test Eden | J3: Test Tarihi | K3: Tarayıcı / Cihaz | L3: Öncelik | M3: Notlar / Hata Linki
A4: W04-001 | B4: W04 | C4: Ürün detayı yükleme | D4: Aktif bir ürün ID'si. | E4: 1. /listings/[id] aç | F4: Tüm görseller, başlık, fiyat, satıcı kartı, açıklama eksiksiz yüklenir. | H4: Beklemede | L4: Kritik
A5: W04-002 | B5: W04 | C5: Görsel galeri ve zoom | D5: Çoklu görselli ürün. | E5: 1. Küçük görsellere tıkla, ana görsel değişir 2. Görselin üzerine gel — zoom çalışır | F5: Galeri sorunsuz çalışır; mobilde swipe destekler. | H5: Beklemede | L5: Orta
A6: W04-003 | B6: W04 | C6: Sepete ekle (üye) | D6: Giriş yapmış kullanıcı. | E6: 1. Sepete Ekle butonuna bas | F6: Sepet sayacı 1 artar; toast bildirim görünür. | H6: Beklemede | L6: Kritik
A7: W04-004 | B7: W04 | C7: Sepete ekle (misafir) | D7: Çıkış yapılmış oturum. | E7: 1. Sepete Ekle | F7: Misafir sepetine eklenir (localStorage); sayaç güncellenir. | H7: Beklemede | L7: Orta
A8: W04-005 | B8: W04 | C8: Stok tükenmiş ürün | D8: Quantity = 0. | E8: 1. Ürün detayını aç | F8: “Satıldı” rozeti görünür; sepete ekle disabled; teklif/mesaj hala mümkün. | H8: Beklemede | L8: Orta
A9: W04-006 | B9: W04 | C9: Kendi ürününü görüntüleme | D9: Satıcı, kendi ilanına bakıyor. | E9: 1. Kendi ilanını aç | F9: Sepete Ekle/Teklif yerine 'Düzenle' / 'İlanı Kapat' butonları görünür. | H9: Beklemede | L9: Orta
A10: W04-007 | B10: W04 | C10: Favorilere ekle/çıkar | D10: Üye giriş. | E10: 1. Kalp ikonuna bas 2. Tekrar bas | F10: Eklenir, çıkarılır; sayaç ve favori sayfası güncellenir. | H10: Beklemede | L10: Orta
A11: W04-008 | B11: W04 | C11: Teklif Ver modalı (üye) | D11: Üye, başkasının ürünü. | E11: 1. 'Teklif Ver' butonuna bas 2. Modal'da fiyat gir 3. Gönder | F11: Min %50 vb. validasyonlar geçilir, teklif gönderilir, satıcıya bildirim/mail tetiklenir. | H11: Beklemede | L11: Kritik
A12: W04-009 | B12: W04 | C12: Çok düşük teklif | D12: — | E12: 1. Ürün fiyatının %10'unu teklif et | F12: “Minimum teklif” uyarısı; gönderilmez. | H12: Beklemede | L12: Orta
A13: W04-010 | B13: W04 | C13: Satıcıya mesaj gönder | D13: Üye giriş, başka satıcının ürünü. | E13: 1. 'Mesaj Gönder' butonuna bas, mesajı yaz, gönder | F13: Mesaj başarıyla gönderilir; /messages sayfasında thread oluşur. | H13: Beklemede | L13: Orta
A14: W04-011 | B14: W04 | C14: Mesajda telefon/IBAN içerik filtresi | D14: — | E14: 1. Mesaj kutusuna telefon numarası yaz, gönder | F14: Filtre tetiklenir; mesaj engellenir veya maskelenir; uyarı gösterilir. | H14: Beklemede | L14: Yüksek
A15: W04-012 | B15: W04 | C15: Takas başlat | D15: Üye, takasa açık ürün. | E15: 1. 'Takas Öner' butonuna bas, kendi ürününü seç, gönder | F15: Trade taslağı oluşur, /trades altında listelenir. | H15: Beklemede | L15: Orta
... A17: W04-014 | B17: W04 | C17: Yorumlar tabı | D17: Yorumu olan ürün. | E17: 1. Yorumlar bölümüne in | F17: Yorumlar listelenir; sıralama (yeni/eski/yıldız) çalışır. | H17: Beklemede | L17: Orta
A20: Bu sayfadaki tüm senaryolar test edilmiş ve sonuçlar yukarıda işaretlenmiştir.
A21: Test Eden (Tarodan) | D21: Tarih | G21: Onaylayan (Müşteri) | J21: Tarih

Sheet W05 - Sepet
A1: W05 — Sepet İşlemleri
A2: Ekleme, miktar değişimi, kupon, kargo, boş sepet, oturum birleştirme.
A3: Test ID | B3: Modül / Sayfa | C3: Senaryo / Test Adı | D3: Önkoşullar | E3: Adımlar (numaralı) | F3: Beklenen Sonuç | G3: Gerçek Sonuç | H3: Durum | I3: Test Eden | J3: Test Tarihi | K3: Tarayıcı / Cihaz | L3: Öncelik | M3: Notlar / Hata Linki
A4: W05-001 | B4: W05 | C4: Sepet yükleme (üye) | D4: Üye, sepete önceden eklenmiş ürünler. | E4: 1. /cart sayfasını aç | F4: Tüm ürünler, satıcı, fiyat ve özet panel doğru görünür. | H4: Beklemede | L4: Kritik
A5: W05-002 | B5: W05 | C5: Boş sepet ekranı | D5: Hiç ürün eklenmemiş. | E5: 1. /cart aç | F5: “Sepetiniz boş” mesajı + 'Alışverişe Devam Et' butonu. | H5: Beklemede | L5: Orta
A6: W05-003 | B6: W05 | C6: Ürün miktarı artırma/azaltma | D6: Sepette ürün var. | E6: 1. + ve - butonlarıyla miktarı değiştir | F6: Toplam ve KDV anlık güncellenir; stok limitini aşmaya izin vermez. | H6: Beklemede | L6: Orta
A7: W05-004 | B7: W05 | C7: Sepetten ürün çıkarma | D7: — | E7: 1. Çöp kutusu/Kaldır butonuna bas | F7: Ürün kalkar; toplam yeniden hesaplanır; toast onay. | H7: Beklemede | L7: Orta
A8: W05-005 | B8: W05 | C8: Kupon kodu uygulama (geçerli) | D8: Aktif bir kupon kodu. | E8: 1. Kupon alanına kodu gir, Uygula | F8: İndirim satırı eklenir; toplam azalır; kupon kuralları geçerli. | H8: Beklemede | L8: Orta
A9: W05-006 | B9: W05 | C9: Geçersiz kupon | D9: — | E9: 1. Olmayan bir kod gir, Uygula | F9: Hata mesajı; toplam değişmez. | H9: Beklemede | L9: Orta
A10: W05-007 | B10: W05 | C10: Kargo eşiği (örn. 500 TL üstü ücretsiz) | D10: Yapılandırma değeri biliniyor. | E10: 1. Tutarı eşiğin altında ve üstünde dene | F10: Eşik altında kargo ücreti, üstünde 'Ücretsiz' görünür. | H10: Beklemede | L10: Orta
A11: W05-008 | B11: W05 | C11: Misafir → giriş yapınca sepet birleşmesi | D11: Misafir olarak ürün eklenmiş. | E11: 1. Giriş yap | F11: Misafir sepeti üye sepetiyle birleşir; çift kayıt oluşmaz. | H11: Beklemede | L11: Orta
A12: W05-009 | B12: W05 | C12: Stok düşmüş ürün uyarısı | D12: Sepetteki üründen başkası satın aldı. | E12: 1. Sepeti yenile | F12: “Stok azaldı/satıldı” uyarısı; checkout'a geçişe izin verilmez. | H12: Beklemede | L12: Orta
A13: W05-010 | B13: W05 | C13: Devam Et — Checkout'a yönlendir | D13: Sepette ürün var. | E13: 1. 'Ödemeye Geç' butonuna bas | F13: /checkout sayfasına geçilir; üye için adres adımı, misafir için e-posta adımı. | H13: Beklemede | L13: Orta
A16: Bu sayfadaki tüm senaryolar test edilmiş ve sonuçlar yukarıda işaretlenmiştir.
A17: Test Eden (Tarodan) | D17: Tarih | G17: Onaylayan (Müşteri) | J17: Tarih

Sheet W06 - Misafir Checkout
A1: W06 — Misafir Checkout Akışı (E-posta OTP)
A2: Misafir kullanıcının kayıt olmadan satın alma süreci.
A3: Test ID | B3: Modül / Sayfa | C3: Senaryo / Test Adı | D3: Önkoşullar | E3: Adımlar (numaralı) | F3: Beklenen Sonuç | G3: Gerçek Sonuç | H3: Durum | I3: Test Eden | J3: Test Tarihi | K3: Tarayıcı / Cihaz | L3: Öncelik | M3: Notlar / Hata Linki
A4: W06-001 | B4: W06 | C4: Misafir e-posta + OTP doğrulama | D4: Sepet dolu, çıkış yapılmış. | E4: 1. /checkout aç 2. E-posta gir, Kod Gönder 3. Maildeki kodu gir, Doğrula | F4: Doğrulama OK; adres adımına geçer. | H4: Beklemede | L4: Kritik
A5: W06-002 | B5: W06 | C5: Yeni teslimat adresi girme | D5: OTP doğrulandı. | E5: 1. Ad, telefon, il, ilçe, adres, posta kodu gir 2. Devam et | F5: Adres validasyonları geçer; ödeme adımına geçilir. | H5: Beklemede | L5: Orta
A6: W06-003 | B6: W06 | C6: Faturalandırma adresi farklı seçeneği | D6: Adres adımında. | E6: 1. 'Faturalandırma adresi farklı' işaretle 2. Yeni fatura adresi gir | F6: İki ayrı adres kaydedilir; sipariş özetinde görünür. | H6: Beklemede | L6: Orta
A7: W06-004 | B7: W06 | C7: Kurumsal fatura talebi | D7: — | E7: 1. Kurumsal fatura işaretle, vergi dairesi/no gir | F7: Kurumsal fatura bilgileri kaydedilir. | H7: Beklemede | L7: Orta
A8: W06-005 | B8: W06 | C8: Sipariş özeti doğrulama | D8: Adres + ödeme seçildi. | E8: 1. Özet ekranını incele | F8: Ürünler, kargo, vergi, kupon, toplam doğru gösterilir. | H8: Beklemede | L8: Orta
A9: W06-006 | B9: W06 | C9: Mesafeli satış sözleşmesi onayı | D9: Özet ekranda. | E9: 1. Onay kutusunu işaretle, Siparişi Onayla'ya bas | F9: Onaysız ödeme başlatılamaz; onay sonrası PayTR iframe'ine geçer. | H9: Beklemede | L9: Yüksek
A10: W06-007 | B10: W06 | C10: Misafir sipariş takip linki | D10: Misafir siparişi tamamlandı. | E10: 1. Mailde gelen takip linkine tıkla 2. /track-order sayfası | F10: E-posta + sipariş no ile sipariş detayına erişilir. | H10: Beklemede | L10: Orta
A11: W06-008 | B11: W06 | C11: Misafir sipariş için iade talebi | D11: Teslim edilmiş misafir siparişi. | E11: 1. /track-order üzerinden detaya git 2. İade Talebi başlat | F11: İade talebi oluşur; e-postayla durum güncellemeleri gelir. | H11: Beklemede | L11: Orta
A14: Bu sayfadaki tüm senaryolar test edilmiş ve sonuçlar yukarıda işaretlenmiştir.
A15: Test Eden (Tarodan) | D15: Tarih | G15: Onaylayan (Müşteri) | J15: Tarih

Sheet W07 - Üye Checkout
A1: W07 — Üye Checkout Akışı
A2: Kayıtlı kullanıcı için adres seçimi, ödeme, sipariş onayı.
A3: Test ID | B3: Modül / Sayfa | C3: Senaryo / Test Adı | D3: Önkoşullar | E3: Adımlar (numaralı) | F3: Beklenen Sonuç | G3: Gerçek Sonuç | H3: Durum | I3: Test Eden | J3: Test Tarihi | K3: Tarayıcı / Cihaz | L3: Öncelik | M3: Notlar / Hata Linki
A4: W07-001 | B4: W07 | C4: Kayıtlı adres seçimi | D4: Üye, kayıtlı adres var. | E4: 1. /checkout aç 2. Adresler listesinden seç 3. Devam et | F4: Adres seçilir; ödeme adımına geçer. | H4: Beklemede | L4: Kritik
A5: W07-002 | B5: W07 | C5: Adres yokken yeni adres ekle | D5: Hiç adres yok. | E5: 1. Yeni Adres formunu doldur, kaydet | F5: Adres profil hesabına da kaydedilir; checkout devam eder. | H5: Beklemede | L5: Orta
A6: W07-003 | B6: W07 | C6: Varsayılan adres seçimi | D6: Çok adres var. | E6: 1. Bir adresi 'Varsayılan' yap | F6: Sonraki checkout'larda otomatik seçili gelir. | H6: Beklemede | L6: Orta
A7: W07-004 | B7: W07 | C7: Kayıtlı kart kullanma (varsa) | D7: Daha önce kart kaydedilmiş. | E7: 1. Ödeme adımında kayıtlı kartı seç | F7: PayTR ile uyumlu şekilde kullanılır; CVV istenebilir. | H7: Beklemede | L7: Orta
A8: W07-005 | B8: W07 | C8: Sipariş onayı sonrası yönlendirme | D8: Ödeme başarılı. | E8: 1. PayTR sonrası yönlendirmeyi bekle | F8: /checkout/success sayfası açılır; sipariş no, e-posta bildirimi gelir. | H8: Beklemede | L8: Orta
A9: W07-006 | B9: W07 | C9: İndirim kuponunu checkout'ta uygulama | D9: Aktif kupon. | E9: 1. Kupon alanına kodu gir, Uygula | F9: İndirim toplamdan düşülür; kullanım limiti varsa kontrol edilir. | H9: Beklemede | L9: Orta
A10: W07-007 | B10: W07 | C10: Üyelik tier indirimi otomatik uygulanır | D10: Premium/Business üye. | E10: 1. Sipariş özetini incele | F10: Tier indirimi açıkça gösterilir. | H10: Beklemede | L10: Orta
A13: Bu sayfadaki tüm senaryolar test edilmiş ve sonuçlar yukarıda işaretlenmiştir.
A14: Test Eden (Tarodan) | D14: Tarih | G14: Onaylayan (Müşteri) | J14: Tarih

Sheet W08 - Ödeme PayTR
A1: W08 — PayTR Ödeme Akışı
A2: iFrame ödeme, 3D Secure, başarısız ödeme, callback.
A3: Test ID | B3: Modül / Sayfa | C3: Senaryo / Test Adı | D3: Önkoşullar | E3: Adımlar (numaralı) | F3: Beklenen Sonuç | G3: Gerçek Sonuç | H3: Durum | I3: Test Eden | J3: Test Tarihi | K3: Tarayıcı / Cihaz | L3: Öncelik | M3: Notlar / Hata Linki
A4: W08-001 | B4: W08 | C4: PayTR iFrame yüklenmesi | D4: Sipariş onaylandı. | E4: 1. Onay sonrası iFrame'i bekle | F4: PayTR iFrame sorunsuz açılır; sipariş tutarı görünür. | H4: Beklemede | L4: Kritik
A5: W08-002 | B5: W08 | C5: Geçerli test kartı ile ödeme | D5: Test ortamı, PayTR test kartı. | E5: 1. Kart bilgilerini gir 2. 3D Secure adımını tamamla | F5: Başarılı; /checkout/success'e yönlendirme; webhook'la sipariş 'preparing' olur. | H5: Beklemede | L5: Kritik
A6: W08-003 | B6: W08 | C6: Yetersiz bakiye / ret kart | D6: Test ret kartı. | E6: 1. Reddedilen kart ile dene | F6: /payment/fail veya hata; sipariş pending; sepet korunur. | H6: Beklemede | L6: Orta
A7: W08-004 | B7: W08 | C7: 3D Secure'da kullanıcı iptal | D7: — | E7: 1. Banka SMS'inde iptal et | F7: Hata; tekrar dene seçeneği; stok rezervi geri verilir. | H7: Beklemede | L7: Orta
A8: W08-005 | B8: W08 | C8: iFrame ortasında pencere kapatma | D8: Ödeme başlatıldı. | E8: 1. Tarayıcı sekmesini kapat | F8: Sipariş 15 dk pending kalır; otomatik iptal cron'u tetiklenir; stok serbest bırakılır. | H8: Beklemede | L8: Orta
A9: W08-006 | B9: W08 | C9: Callback hash doğrulama (negatif) | D9: Manuel webhook hash bozuk. | E9: 1. Backend manuel test ile geçersiz callback gönder | F9: Webhook reddedilir; sipariş güncellenmez; log'a düşer. | H9: Beklemede | L9: Kritik
A10: W08-007 | B10: W08 | C10: Ödeme retry akışı | D10: Bir kez başarısız ödeme. | E10: 1. Sepete dön, tekrar checkout | F10: Yeni ödeme başlatılabilir; eski payment failed olarak kalır. | H10: Beklemede | L10: Orta
A11: W08-008 | B11: W08 | C11: Ödeme timeout reconciliation | D11: Pending ödeme 15+ dk. | E11: 1. Cron'un sonucunu bekle | F11: Sistem PayTR API'den durumu sorgular; sonuca göre günceller. | H11: Beklemede | L11: Orta
A14: Bu sayfadaki tüm senaryolar test edilmiş ve sonuçlar yukarıda işaretlenmiştir.
A15: Test Eden (Tarodan) | D15: Tarih | G15: Onaylayan (Müşteri) | J15: Tarih

Sheet W09 - Siparişlerim Listesi
A1: W09 — Siparişlerim (Alıcı) Listesi
A2: Sipariş listesi, filtre, durum rozetleri, satıcı/alıcı sekmesi.
A3: Test ID | B3: Modül / Sayfa | C3: Senaryo / Test Adı | D3: Önkoşullar | E3: Adımlar (numaralı) | F3: Beklenen Sonuç | G3: Gerçek Sonuç | H3: Durum | I3: Test Eden | J3: Test Tarihi | K3: Tarayıcı / Cihaz | L3: Öncelik | M3: Notlar / Hata Linki
A4: W09-001 | B4: W09 | C4: Sipariş listesi yükleme | D4: Üye, en az 1 sipariş. | E4: 1. /orders aç | F4: Tüm siparişler tarihe göre listelenir; durum rozetleri renkli. | H4: Beklemede | L4: Kritik
A5: W09-002 | B5: W09 | C5: Alıcı / Satıcı sekme geçişi | D5: Hem alıcı hem satıcı kullanıcı. | E5: 1. Sekmeleri değiştir | F5: Liste filtrelenir; sayaçlar doğru. | H5: Beklemede | L5: Orta
A6: W09-003 | B6: W09 | C6: Durum filtresi | D6: Farklı durumlu siparişler. | E6: 1. Filtre dropdown'undan 'Kargoda' seç | F6: Sadece kargoda olanlar listelenir. | H6: Beklemede | L6: Orta
A7: W09-004 | B7: W09 | C7: Sipariş ara (no veya ürün adı) | D7: — | E7: 1. Arama kutusuna sipariş no yaz | F7: İlgili sipariş(ler) bulunur. | H7: Beklemede | L7: Orta
A8: W09-005 | B8: W09 | C8: Boş liste durumu (yeni hesap) | D8: Hiç sipariş yok. | E8: 1. /orders aç | F8: “Henüz siparişiniz yok” + alışverişe başla butonu. | H8: Beklemede | L8: Orta
A9: W09-006 | B9: W09 | C9: Sayfalama veya sonsuz scroll | D9: Çok sipariş. | E9: 1. Aşağı scroll / sonraki sayfa | F9: Eski siparişler yüklenir; performans kabul edilebilir. | H9: Beklemede | L9: Orta
A12: Bu sayfadaki tüm senaryolar test edilmiş ve sonuçlar yukarıda işaretlenmiştir.
A13: Test Eden (Tarodan) | D13: Tarih | G13: Onaylayan (Müşteri) | J13: Tarih

Sheet W10 - Sipariş Detay & Takip
A1: W10 — Sipariş Detayı, Kargo Takibi, Yorum
A2: Sipariş timeline, kargo takip, satıcıya mesaj, yorum yazma.
A3: Test ID | B3: Modül / Sayfa | C3: Senaryo / Test Adı | D3: Önkoşullar | E3: Adımlar (numaralı) | F3: Beklenen Sonuç | G3: Gerçek Sonuç | H3: Durum | I3: Test Eden | J3: Test Tarihi | K3: Tarayıcı / Cihaz | L3: Öncelik | M3: Notlar / Hata Linki
A4: W10-001 | B4: W10 | C4: Sipariş detay sayfası | D4: Aktif bir sipariş. | E4: 1. /orders/[id] aç | F4: Ürünler, kargo, ödeme, satıcı, durum timeline eksiksiz. | H4: Beklemede | L4: Kritik
A5: W10-002 | B5: W10 | C5: Durum timeline | D5: — | E5: 1. Timeline'ı incele | F5: Durum geçişleri kronolojik, tarih/saat ile görünür. | H5: Beklemede | L5: Orta
A6: W10-003 | B6: W10 | C6: Kargo takip linkine tıklama | D6: Kargolanmış sipariş, tracking no var. | E6: 1. 'Kargoyu Takip Et'e bas | F6: Kargo şirketi sitesi açılır veya gömülü iframe; doğru tracking no. | H6: Beklemede | L6: Orta
A7: W10-004 | B7: W10 | C7: Sipariş özeti PDF / yazdırma | D7: — | E7: 1. 'Yazdır' butonuna bas | F7: Yazdırılabilir özet açılır. | H7: Beklemede | L7: Orta
A8: W10-005 | B8: W10 | C8: Satıcıya mesaj atma | D8: — | E8: 1. 'Satıcıya Mesaj' linkine bas | F8: /messages thread'i açılır, sipariş bağlamı eklenir. | H8: Beklemede | L8: Orta
A9: W10-006 | B9: W10 | C9: Teslim alındıktan sonra yorum yazma | D9: Sipariş 'delivered'. | E9: 1. 'Yorum Yap'a bas, yıldız ver, metin yaz, gönder | F9: Yorum gönderilir; satıcının ürün sayfasında moderasyon sonrası görünür. | H9: Beklemede | L9: Orta
A10: W10-007 | B10: W10 | C10: Fatura indirme | D10: Fatura oluşturulmuş. | E10: 1. 'Fatura İndir' linkine bas | F10: PDF açılır/indirir; vergi, KDV, kalemler doğru. | H10: Beklemede | L10: Orta
A13: Bu sayfadaki tüm senaryolar test edilmiş ve sonuçlar yukarıda işaretlenmiştir.
A14: Test Eden (Tarodan) | D14: Tarih | G14: Onaylayan (Müşteri) | J14: Tarih

Sheet W11 - Sipariş İptal
A1: W11 — Sipariş İptal Akışı
A2: Kargolanmadan önce/sonra iptal, satıcı onayı, otomatik iade.
A3: Test ID | B3: Modül / Sayfa | C3: Senaryo / Test Adı | D3: Önkoşullar | E3: Adımlar (numaralı) | F3: Beklenen Sonuç | G3: Gerçek Sonuç | H3: Durum | I3: Test Eden | J3: Test Tarihi | K3: Tarayıcı / Cihaz | L3: Öncelik | M3: Notlar / Hata Linki
A4: W11-001 | B4: W11 | C4: Ödeme bekleyen siparişi iptal | D4: Sipariş 'pending_payment'. | E4: 1. Detayda 'Siparişi İptal Et'e bas | F4: Sipariş anında iptal; stok serbest; herhangi bir ücret yok. | H4: Beklemede | L4: Yüksek
A5: W11-002 | B5: W11 | C5: Hazırlanıyor durumunda iptal isteği | D5: Sipariş 'preparing'. | E5: 1. İptal İsteği Oluştur | F5: Satıcıya iptal talebi gider; durum 'cancel_requested'. | H5: Beklemede | L5: Orta
A6: W11-003 | B6: W11 | C6: Satıcı iptal talebini kabul | D6: Cancel-requested sipariş. | E6: 1. (Satıcı tarafında) Onayla | F6: Sipariş iptal; PayTR otomatik refund tetiklenir; alıcıya mail. | H6: Beklemede | L6: Orta
A7: W11-004 | B7: W11 | C7: Satıcı iptal talebini reddetti | D7: — | E7: 1. Satıcı reddeder | F7: Talep kapanır; alıcıya bilgi maili; iade için teslimat sonrasını beklemesi gerekir. | H7: Beklemede | L7: Orta
A8: W11-005 | B8: W11 | C8: Kargolanmış sipariş için iptal denemesi | D8: Sipariş 'shipped'. | E8: 1. İptal butonu aramak | F8: İptal mevcut değil; 'İade Talebi' yönlendirmesi gösterilir. | H8: Beklemede | L8: Yüksek
A9: W11-006 | B9: W11 | C9: İptal sonrası mail bildirimi | D9: — | E9: 1. İptali tamamla | F9: Hem alıcı hem satıcıya iptal maili gider. | H9: Beklemede | L9: Orta
A12: Bu sayfadaki tüm senaryolar test edilmiş ve sonuçlar yukarıda işaretlenmiştir.
A13: Test Eden (Tarodan) | D13: Tarih | G13: Onaylayan (Müşteri) | J13: Tarih

Sheet W12 - İade Talebi
A1: W12 — İade ve Değişim Akışı
A2: Talep oluşturma, kanıt yükleme, satıcı onayı, kargo, refund.
A3: Test ID | B3: Modül / Sayfa | C3: Senaryo / Test Adı | D3: Önkoşullar | E3: Adımlar (numaralı) | F3: Beklenen Sonuç | G3: Gerçek Sonuç | H3: Durum | I3: Test Eden | J3: Test Tarihi | K3: Tarayıcı / Cihaz | L3: Öncelik | M3: Notlar / Hata Linki
A4: W12-001 | B4: W12 | C4: İade talebi oluşturma (delivered) | D4: Teslim edilmiş sipariş, 14 gün içinde. | E4: 1. /orders/[id] aç 2. 'İade Talebi Aç'a bas 3. Sebep seç, açıklama yaz, fotoğraf yükle, gönder | F4: Talep oluşur; satıcıya bildirim/mail; durum 'pending_review'. | H4: Beklemede | L4: Kritik
A5: W12-002 | B5: W12 | C5: Hasar/tanım uyumsuzluğu için fotoğraf zorunluluğu | D5: Sebep 'hasarlı' seçildi. | E5: 1. Fotoğraf yüklemeden gönderme deneme | F5: Form geçmez; fotoğraf zorunlu uyarısı. | H5: Beklemede | L5: Orta
A6: W12-003 | B6: W12 | C6: İade taleplerim listesi | D6: — | E6: 1. /refund-requests aç | F6: Tüm talepler listelenir; durum filtreleri çalışır. | H6: Beklemede | L6: Orta
A7: W12-004 | B7: W12 | C7: Satıcı iadeyi onayladı — kargo bilgisi | D7: Durum 'approved'. | E7: 1. Detayı aç | F7: İade kargo etiketi/yönergeleri görünür; takip no girilebilir. | H7: Beklemede | L7: Orta
A8: W12-005 | B8: W12 | C8: İade kargo gönderme | D8: — | E8: 1. Tracking no gir, gönder | F8: Durum 'return_in_transit'; satıcıya bilgi. | H8: Beklemede | L8: Orta
A9: W12-006 | B9: W12 | C9: Satıcı iade ürünü teslim aldı | D9: — | E9: 1. Satıcı tarafında 'Teslim Aldım' işaretle | F9: Durum 'received'; refund cron'u tetiklenir. | H9: Beklemede | L9: Orta
A10: W12-007 | B10: W12 | C10: Refund tamamlandı (PayTR) | D10: Refund işlendi. | E10: 1. Mail kontrol | F10: “Para iadeniz yapıldı” maili; durum 'refunded'; tutar PayTR refund'la geri. | H10: Beklemede | L10: Orta
A11: W12-008 | B11: W12 | C11: İade talebi reddetildi | D11: Satıcı reddetti. | E11: 1. Detayı aç | F11: Sebep gösterilir; itiraz/destek yönlendirmesi. | H11: Beklemede | L11: Orta
A12: W12-009 | B12: W12 | C12: İade süresi dolmuş | D12: Teslimat üzerinden 14+ gün. | E12: 1. İade Talebi açmaya çalış | F12: Buton disabled; süre dolmuş bilgisi. | H12: Beklemede | L12: Orta
A13: W12-010 | B13: W12 | C13: Trade (takas) iadesi nakit refund | D13: Cash diff'li takasta iade kabul. | E13: 1. Takas iadesini başlat | F13: Sadece nakit fark refund edilir; takas durumu güncellenir. | H13: Beklemede | L13: Yüksek
A16: Bu sayfadaki tüm senaryolar test edilmiş ve sonuçlar yukarıda işaretlenmiştir.
A17: Test Eden (Tarodan) | D17: Tarih | G17: Onaylayan (Müşteri) | J17: Tarih

Sheet W13 - Profil & Ayarlar
A1: W13 — Profil, Adres, Şifre, Ödeme Yöntemleri
A2: Kullanıcı kendi hesabını yönetir.
A3: Test ID | B3: Modül / Sayfa | C3: Senaryo / Test Adı | D3: Önkoşullar | E3: Adımlar (numaralı) | F3: Beklenen Sonuç | G3: Gerçek Sonuç | H3: Durum | I3: Test Eden | J3: Test Tarihi | K3: Tarayıcı / Cihaz | L3: Öncelik | M3: Notlar / Hata Linki
A4: W13-001 | B4: W13 | C4: Profil sayfası açılışı | D4: Üye giriş. | E4: 1. /profile aç | F4: Avatar, ad, e-posta, telefon, üyelik, istatistikler görünür. | H4: Beklemede | L4: Orta
A5: W13-002 | B5: W13 | C5: Avatar yükleme | D5: — | E5: 1. Avatar resmini değiştir, kaydet | F5: Resim yüklenir, profil ve yorumlarda görünür. | H5: Beklemede | L5: Orta
A6: W13-003 | B6: W13 | C6: Ad/Soyad/Bio güncelleme | D6: — | E6: 1. Edit profil → bilgileri değiştir, kaydet | F6: Değişiklikler kalıcı; refresh sonrası korunur. | H6: Beklemede | L6: Orta
A7: W13-004 | B7: W13 | C7: Adres ekleme/düzenleme/silme | D7: — | E7: 1. /profile/addresses aç 2. Yeni adres ekle, düzenle, sil | F7: Tüm CRUD çalışır; varsayılan adres seçilebilir. | H7: Beklemede | L7: Orta
A8: W13-005 | B8: W13 | C8: Şifre değiştir | D8: — | E8: 1. /profile/change-password 2. Eski şifre + yeni şifre x2 gir, kaydet | F8: Başarılı; yeni şifre ile login çalışır; tüm oturumlar opsiyonel sonlanır. | H8: Beklemede | L8: Yüksek
A9: W13-006 | B9: W13 | C9: Eski şifre yanlış | D9: — | E9: 1. Eski şifreyi yanlış gir | F9: Hata; değişiklik kaydedilmez. | H9: Beklemede | L9: Orta
A10: W13-007 | B10: W13 | C10: Ödeme yöntemleri yönetimi | D10: — | E10: 1. /profile/payments aç 2. Kayıtlı kartları gör, yenisini ekle, sil | F10: Tokenize edilmiş kart bilgileri görünür; CVV asla saklanmaz. | H10: Beklemede | L10: Orta
A11: W13-008 | B11: W13 | C11: İndirim kuponları listesi | D11: — | E11: 1. /profile/discounts aç | F11: Aktif/kullanılmış kuponlar; kopyala butonu çalışır. | H11: Beklemede | L11: Orta
A12: W13-009 | B12: W13 | C12: İstatistikler | D12: — | E12: 1. /profile/statistics aç | F12: Satış, görüntülenme, beğeni metrikleri görünür. | H12: Beklemede | L12: Orta
A13: W13-010 | B13: W13 | C13: Kurumsal hesap detayları | D13: Kurumsal kullanıcı. | E13: 1. /profile/business aç | F13: Şirket, vergi, fatura bilgileri görüntü/düzenleme. | H13: Beklemede | L13: Orta
A14: W13-011 | B14: W13 | C14: İlanlarım sayfası | D14: Satıcı. | E14: 1. /profile/listings aç | F14: Aktif/satılan/silinmiş sekmeleri çalışır; düzenleme/silme/devre dışı. | H14: Beklemede | L14: Orta
A15: W13-012 | B15: W13 | C15: Hesabı sil / dondur | D15: — | E15: 1. Ayarlardan 'Hesabımı Sil'e bas | F15: Onay modali; KVKK gereği veri silme/anonimleştirme süreci başlar. | H15: Beklemede | L15: Yüksek
A18: Bu sayfadaki tüm senaryolar test edilmiş ve sonuçlar yukarıda işaretlenmiştir.
A19: Test Eden (Tarodan) | D19: Tarih | G19: Onaylayan (Müşteri) | J19: Tarih

Sheet W14 - Satıcı İlan Yönetimi
A1: W14 — Satıcı: İlan Oluşturma ve Yönetimi
A2: Yeni ilan, görsel yükleme, kategori, fiyat, üyelik limit.
A3: Test ID | B3: Modül / Sayfa | C3: Senaryo / Test Adı | D3: Önkoşullar | E3: Adımlar (numaralı) | F3: Beklenen Sonuç | G3: Gerçek Sonuç | H3: Durum | I3: Test Eden | J3: Test Tarihi | K3: Tarayıcı / Cihaz | L3: Öncelik | M3: Notlar / Hata Linki
A4: W14-001 | B4: W14 | C4: Yeni ilan oluşturma (satıcı) | D4: Onaylı satıcı. | E4: 1. /listings/new aç 2. Kategori, marka, başlık, açıklama, fiyat, görsel yükle 3. Yayınla | F4: İlan moderasyon kuyruğuna düşer; satıcıya bilgi maili. | H4: Beklemede | L4: Kritik
A5: W14-002 | B5: W14 | C5: Görsel boyut/format kontrolü | D5: — | E5: 1. 10MB üstü veya .exe yüklemeye çalış | F5: Reddedilir; hata mesajı gösterilir. | H5: Beklemede | L5: Orta
A6: W14-003 | B6: W14 | C6: Sürükle-bırak görsel sıralama | D6: Çoklu görsel. | E6: 1. Görselleri yeniden sırala | F6: Sıralama kaydedilir; ilk görsel kapak olur. | H6: Beklemede | L6: Orta
A7: W14-004 | B7: W14 | C7: Üyelik ilan limiti aşımı | D7: Free tier, limit dolmuş. | E7: 1. Yeni ilan denemesi | F7: “Limitiniz doldu, yükseltin” uyarısı + Premium CTA. | H7: Beklemede | L7: Orta
A8: W14-005 | B8: W14 | C8: Taslak olarak kaydet | D8: — | E8: 1. Form yarıda 'Taslak Kaydet' | F8: İlan taslak olarak listelenir; sonradan düzenlenebilir. | H8: Beklemede | L8: Orta
A9: W14-006 | B9: W14 | C9: İlan düzenleme | D9: Aktif ilan. | E9: 1. İlanı düzenle, fiyat değiştir, kaydet | F9: Değişiklikler anında yansır; sepetteki kullanıcılar uyarılır. | H9: Beklemede | L9: Orta
A10: W14-007 | B10: W14 | C10: İlanı devre dışı bırakma | D10: — | E10: 1. 'Pasif Yap'a bas | F10: İlan listelerde görünmez; satıcı paneline pasif olarak gelir. | H10: Beklemede | L10: Orta
A11: W14-008 | B11: W14 | C11: İlanı silme | D11: — | E11: 1. 'Sil'e bas, onayla | F11: İlan kalıcı silinir veya soft-delete; sipariş geçmişi kalır. | H11: Beklemede | L11: Orta
A12: W14-009 | B12: W14 | C12: Reddedilen ilan akışı | D12: Admin reddetti. | E12: 1. Mail oku, ilanı düzelt, tekrar yayınla | F12: Ret sebebi maile düşer; düzeltip tekrar moderasyona gönderilir. | H12: Beklemede | L12: Orta
A15: Bu sayfadaki tüm senaryolar test edilmiş ve sonuçlar yukarıda işaretlenmiştir.
A16: Test Eden (Tarodan) | D16: Tarih | G16: Onaylayan (Müşteri) | J16: Tarih

Sheet W15 - Satıcı Sipariş Yönetimi
A1: W15 — Satıcı: Sipariş İşleme ve Kargolama
A2: Satıcının sipariş alıp kargolaması, payout takibi.
A3: Test ID | B3: Modül / Sayfa | C3: Senaryo / Test Adı | D3: Önkoşullar | E3: Adımlar (numaralı) | F3: Beklenen Sonuç | G3: Gerçek Sonuç | H3: Durum | I3: Test Eden | J3: Test Tarihi | K3: Tarayıcı / Cihaz | L3: Öncelik | M3: Notlar / Hata Linki
A4: W15-001 | B4: W15 | C4: Satıcı dashboard | D4: Satıcı, sipariş var. | E4: 1. /seller/dashboard aç | F4: İstatistikler, bekleyen siparişler, performans görünür. | H4: Beklemede | L4: Orta
A5: W15-002 | B5: W15 | C5: Yeni sipariş bildirimi | D5: Yeni sipariş geldi. | E5: 1. Bildirim maili ve in-app bildirim kontrol | F5: Mail + in-app + push tetiklenir; dashboard'da 'bekliyor' sayacı artar. | H5: Beklemede | L5: Kritik
A6: W15-003 | B6: W15 | C6: Sipariş detayı (satıcı) | D6: — | E6: 1. /seller/orders/[id] aç | F6: Kargo girişi, alıcı bilgisi, ödeme özeti, kargo deadline görünür. | H6: Beklemede | L6: Orta
A7: W15-004 | B7: W15 | C7: Kargo bilgisi girme | D7: — | E7: 1. Kargo şirketi seç, takip no gir, kaydet | F7: Sipariş 'shipped' olur; alıcıya tracking maili gider. | H7: Beklemede | L7: Kritik
A8: W15-005 | B8: W15 | C8: Kargo deadline geçme uyarısı | D8: Sipariş üzerinden 3 iş günü geçti. | E8: 1. Dashboard kontrol | F8: Uyarı maili; satıcı performans skoru etkilenir. | H8: Beklemede | L8: Orta
A9: W15-006 | B9: W15 | C9: Kargo deadline geçti — otomatik iptal | D9: Çok geç kalındı. | E9: 1. Cron tetiklenmesini bekle | F9: Sipariş otomatik iptal; alıcıya iade; satıcıya bildirim. | H9: Beklemede | L9: Orta
A10: W15-007 | B10: W15 | C10: Banka hesabı eklenmemiş — payout uyarısı | D10: Yeni satıcı, IBAN yok. | E10: 1. Dashboard kontrol | F10: “Banka bilgilerini ekleyin” uyarısı; payout pending. | H10: Beklemede | L10: Orta
A11: W15-008 | B11: W15 | C11: Payout başarılı | D11: Teslimat + 7 gün geçti, IBAN var. | E11: 1. Payout cron tetiklenir | F11: Payout 'completed'; mail bildirimi; bakiye 0. | H11: Beklemede | L11: Orta
A14: Bu sayfadaki tüm senaryolar test edilmiş ve sonuçlar yukarıda işaretlenmiştir.
A15: Test Eden (Tarodan) | D15: Tarih | G15: Onaylayan (Müşteri) | J15: Tarih

Sheet W16 - Teklifler
A1: W16 — Teklif (Offer) Akışı
A2: Teklif ver, karşı teklif, kabul/red, expire, ödeme.
A3: Test ID | B3: Modül / Sayfa | C3: Senaryo / Test Adı | D3: Önkoşullar | E3: Adımlar (numaralı) | F3: Beklenen Sonuç | G3: Gerçek Sonuç | H3: Durum | I3: Test Eden | J3: Test Tarihi | K3: Tarayıcı / Cihaz | L3: Öncelik | M3: Notlar / Hata Linki
A4: W16-001 | B4: W16 | C4: Alınan teklifleri görüntüle | D4: Satıcı, gelen teklif var. | E4: 1. /offers (Alınan sekmesi) aç | F4: Tüm teklifler listelenir; durum, miktar, alıcı görünür. | H4: Beklemede | L4: Orta
A5: W16-002 | B5: W16 | C5: Teklifi kabul et | D5: Pending teklif. | E5: 1. Kabul Et'e bas | F5: Sipariş otomatik oluşur; alıcıya 'ödeme yapın' maili (30dk). | H5: Beklemede | L5: Kritik
A6: W16-003 | B6: W16 | C6: Teklifi reddet | D6: — | E6: 1. Reddet'e bas | F6: Teklif 'rejected'; alıcıya bildirim. | H6: Beklemede | L6: Orta
A7: W16-004 | B7: W16 | C7: Karşı teklif gönder | D7: — | E7: 1. 'Karşı Teklif' modalı, yeni fiyat gir, gönder | F7: Teklif 'countered'; alıcıya yeni teklif gider. | H7: Beklemede | L7: Orta
A8: W16-005 | B8: W16 | C8: Teklifin süresinin dolması (24 saat) | D8: Yanıt verilmedi. | E8: 1. 24 saat bekle / cron tetikle | F8: Teklif 'expired'; iki tarafa bildirim. | H8: Beklemede | L8: Orta
A9: W16-006 | B9: W16 | C9: Kabul edilen teklif için ödeme | D9: Teklif kabul, sipariş oluşmuş. | E9: 1. Mailden ödeme linkine git, PayTR ile öde | F9: Sipariş normal akışa girer. | H9: Beklemede | L9: Orta
A10: W16-007 | B10: W16 | C10: Kabul edilen teklif ödeme yapılmadı | D10: 30 dk geçti. | E10: 1. Cron'u bekle | F10: Sipariş iptal; teklif 'expired_unpaid'; satıcıya bildirim. | H10: Beklemede | L10: Orta
A11: W16-008 | B11: W16 | C11: Gönderilen teklifler sekmesi | D11: Alıcı, teklif vermiş. | E11: 1. /offers (Gönderilen) aç | F11: Verdiği tüm teklifler durumlarıyla listelenir. | H11: Beklemede | L11: Orta
A12: W16-009 | B12: W16 | C12: Teklifi geri çekme | D12: Pending teklif. | E12: 1. İptal Et | F12: Teklif 'cancelled'; satıcıya bildirim. | H12: Beklemede | L12: Orta
A15: Bu sayfadaki tüm senaryolar test edilmiş ve sonuçlar yukarıda işaretlenmiştir.
A16: Test Eden (Tarodan) | D16: Tarih | G16: Onaylayan (Müşteri) | J16: Tarih

Sheet W17 - Takas Trade
A1: W17 — Takas (Trade) Akışı
A2: Takas teklifi, kabul, çift kargo, depo, tamamlama, anlaşmazlık.
A3: Test ID | B3: Modül / Sayfa | C3: Senaryo / Test Adı | D3: Önkoşullar | E3: Adımlar (numaralı) | F3: Beklenen Sonuç | G3: Gerçek Sonuç | H3: Durum | I3: Test Eden | J3: Test Tarihi | K3: Tarayıcı / Cihaz | L3: Öncelik | M3: Notlar / Hata Linki
A4: W17-001 | B4: W17 | C4: Takas teklifi oluşturma | D4: İki tarafın takas-uygun ürünü. | E4: 1. Hedef ürünün sayfasında 'Takas Öner' 2. Kendi ürününü seç, nakit fark gir (opsiyonel), gönder | F4: Takas oluşur; karşı tarafa bildirim; durum 'pending'. | H4: Beklemede | L4: Kritik
A5: W17-002 | B5: W17 | C5: Takas kabul | D5: — | E5: 1. /trades aç, kabul et | F5: Durum 'accepted'; ürünler kilitlenir (reservedQuantity). | H5: Beklemede | L5: Orta
A6: W17-003 | B6: W17 | C6: Nakit fark için ödeme | D6: Cash diff > 0. | E6: 1. Ödeme adımına git, PayTR ile öde | F6: Cash payment 'completed'; takas 'shipping' aşamasına geçer. | H6: Beklemede | L6: Orta
A7: W17-004 | B7: W17 | C7: Her iki taraf kargo bilgisi girişi | D7: — | E7: 1. Tarafların kargo no girmesi | F7: İki taraf da kargo girer; durum 'in_transit'. | H7: Beklemede | L7: Orta
A8: W17-005 | B8: W17 | C8: Depo seçeneği (varsa) | D8: Depo modu aktif takas. | E8: 1. Ürünleri Tarodan deposuna gönder | F8: Admin deposu inceler; karşı tarafa gönderilir. | H8: Beklemede | L8: Orta
A9: W17-006 | B9: W17 | C9: Her iki taraf teslim aldı işaretleme | D9: Kargolar teslim. | E9: 1. Her iki taraf teslim onaylar | F9: Takas 'completed'; rating verme imkanı açılır. | H9: Beklemede | L9: Orta
A10: W17-007 | B10: W17 | C10: Takas anlaşmazlığı (dispute) | D10: Bir taraf anlaşmazlık başlatır. | E10: 1. Dispute Aç → açıklama | F10: Durum 'disputed'; admin paneline düşer; mail bildirimi. | H10: Beklemede | L10: Orta
A11: W17-008 | B11: W17 | C11: Takas süresi dolması | D11: Yanıt deadline aşıldı. | E11: 1. Cron'u bekle | F11: Otomatik iptal; nakit fark refund; rezerv serbest. | H11: Beklemede | L11: Orta
A14: Bu sayfadaki tüm senaryolar test edilmiş ve sonuçlar yukarıda işaretlenmiştir.
A15: Test Eden (Tarodan) | D15: Tarih | G15: Onaylayan (Müşteri) | J15: Tarih

Sheet W18 - Mesajlar
A1: W18 — Mesajlaşma
A2: Sohbet, içerik filtresi, bloke, arşiv, görsel paylaşımı.
A3: Test ID | B3: Modül / Sayfa | C3: Senaryo / Test Adı | D3: Önkoşullar | E3: Adımlar (numaralı) | F3: Beklenen Sonuç | G3: Gerçek Sonuç | H3: Durum | I3: Test Eden | J3: Test Tarihi | K3: Tarayıcı / Cihaz | L3: Öncelik | M3: Notlar / Hata Linki
A4: W18-001 | B4: W18 | C4: Mesaj listesi | D4: Üye, mevcut threadler. | E4: 1. /messages aç | F4: Sol panelde threadler, sağda boş veya seçili sohbet. | H4: Beklemede | L4: Orta
A5: W18-002 | B5: W18 | C5: Yeni mesaj gönderme | D5: — | E5: 1. Bir thread aç, mesaj yaz, gönder | F5: Mesaj anında görünür; karşı tarafa bildirim/mail. | H5: Beklemede | L5: Yüksek
A6: W18-003 | B6: W18 | C6: Görsel paylaşma | D6: — | E6: 1. Resim yükle, gönder | F6: Görsel yüklenir; preview açılır. | H6: Beklemede | L6: Orta
A7: W18-004 | B7: W18 | C7: Telefon/IBAN/email içerik filtresi | D7: — | E7: 1. Mesaja telefon yaz, gönder | F7: Filtre tetiklenir; gönderim engellenir veya maskelenir. | H7: Beklemede | L7: Kritik
A8: W18-005 | B8: W18 | C8: Kullanıcıyı bloke etme | D8: — | E8: 1. Thread → 3 nokta → Bloke Et | F8: Karşı taraf mesaj gönderemez; bloke listesinde görünür. | H8: Beklemede | L8: Orta
A9: W18-006 | B9: W18 | C9: Bloke kaldırma | D9: Bloke kullanıcı. | E9: 1. Profil ayarlarından bloke kaldır | F9: Kullanıcı yeniden mesaj gönderebilir. | H9: Beklemede | L9: Orta
A10: W18-007 | B10: W18 | C10: Threadi arşivle | D10: — | E10: 1. Thread → Arşivle | F10: Ana listeden kalkar; arşiv sekmesinde görünür. | H10: Beklemede | L10: Orta
A11: W18-008 | B11: W18 | C11: Okunmamış sayacı | D11: Yeni mesaj geldi. | E11: 1. Üst menüye bak | F11: Sayaç doğru; okunduktan sonra sıfırlanır. | H11: Beklemede | L11: Orta
A12: W18-009 | B12: W18 | C12: Realtime mesaj geldi | D12: İki sekmede iki kullanıcı. | E12: 1. Birinden mesaj gönder | F12: Diğer sekme websocket ile anında gösterir. | H12: Beklemede | L12: Orta
A15: Bu sayfadaki tüm senaryolar test edilmiş ve sonuçlar yukarıda işaretlenmiştir.
A16: Test Eden (Tarodan) | D16: Tarih | G16: Onaylayan (Müşteri) | J16: Tarih

Sheet W19 - Bildirimler
A1: W19 — Bildirim Merkezi
A2: Bildirim listesi, filtreleme, okundu işaretleme, ayarlar.
A3: Test ID | B3: Modül / Sayfa | C3: Senaryo / Test Adı | D3: Önkoşullar | E3: Adımlar (numaralı) | F3: Beklenen Sonuç | G3: Gerçek Sonuç | H3: Durum | I3: Test Eden | J3: Test Tarihi | K3: Tarayıcı / Cihaz | L3: Öncelik | M3: Notlar / Hata Linki
A4: W19-001 | B4: W19 | C4: Bildirim listesi | D4: Birden fazla bildirim. | E4: 1. /notifications aç | F4: En yeni en üstte; ikon, başlık, zaman görünür. | H4: Beklemede | L4: Orta
A5: W19-002 | B5: W19 | C5: Filtreleme (sipariş/teklif/mesaj) | D5: — | E5: 1. Üst sekmeleri kullan | F5: Liste filtrelenir; sayaç güncellenir. | H5: Beklemede | L5: Orta
A6: W19-003 | B6: W19 | C6: Okundu / okunmadı işaretleme | D6: — | E6: 1. Bir bildirimi okundu işaretle | F6: Görsel olarak fade; tüm cihazlarda senkron. | H6: Beklemede | L6: Orta
A7: W19-004 | B7: W19 | C7: Tümünü temizle | D7: — | E7: 1. 'Tümünü Okundu Yap' | F7: Tüm bildirimler okunmuş; sayaç sıfır. | H7: Beklemede | L7: Orta
A8: W19-005 | B8: W19 | C8: Bildirim tıklama → ilgili sayfa | D8: — | E8: 1. Sipariş bildirimine tıkla | F8: İlgili sipariş detay sayfasına yönlendirir. | H8: Beklemede | L8: Orta
A9: W19-006 | B9: W19 | C9: Bildirim ayarları (mail/push aç-kapat) | D9: — | E9: 1. Ayarlara git, kategorileri değiştir | F9: Ayarlar kaydedilir; sonraki olaylarda uygulanır. | H9: Beklemede | L9: Orta
A12: Bu sayfadaki tüm senaryolar test edilmiş ve sonuçlar yukarıda işaretlenmiştir.
A13: Test Eden (Tarodan) | D13: Tarih | G13: Onaylayan (Müşteri) | J13: Tarih

Sheet W20 - Favori Wishlist Koleksiyo
A1: W20 — Favoriler, Wishlist, Koleksiyonlar
A2: Beğenme, koleksiyon oluşturma, paylaşım, fiyat düşüş takibi.
A3: Test ID | B3: Modül / Sayfa | C3: Senaryo / Test Adı | D3: Önkoşullar | E3: Adımlar (numaralı) | F3: Beklenen Sonuç | G3: Gerçek Sonuç | H3: Durum | I3: Test Eden | J3: Test Tarihi | K3: Tarayıcı / Cihaz | L3: Öncelik | M3: Notlar / Hata Linki
A4: W20-001 | B4: W20 | C4: Favorilere ürün ekle | D4: — | E4: 1. Üründe kalp ikonuna bas | F4: /favorites listesinde görünür. | H4: Beklemede | L4: Orta
A5: W20-002 | B5: W20 | C5: Favorilerden çıkar | D5: — | E5: 1. Tekrar kalp | F5: Listeden kalkar. | H5: Beklemede | L5: Orta
A6: W20-003 | B6: W20 | C6: Wishlist'e ekle | D6: — | E6: 1. İstek listesi butonu | F6: /wishlist'te görünür; satıcıya bilgi opsiyonel. | H6: Beklemede | L6: Orta
A7: W20-004 | B7: W20 | C7: Wishlist'te fiyat düşüş bildirimi | D7: Wishlist'teki ürün fiyatı düştü. | E7: 1. Mail/push bekle | F7: Fiyat düştü bildirimi tetiklenir. | H7: Beklemede | L7: Orta
A8: W20-005 | B8: W20 | C8: Yeni koleksiyon oluştur | D8: — | E8: 1. /collections aç, Yeni Koleksiyon 2. İsim, açıklama, görsel ekle, kaydet | F8: Koleksiyon oluşur; profilde görünür. | H8: Beklemede | L8: Orta
A9: W20-006 | B9: W20 | C9: Koleksiyona ürün ekleme | D9: — | E9: 1. Koleksiyonu aç, 'Ürün Ekle' | F9: Seçilen ürünler eklenir. | H9: Beklemede | L9: Orta
A10: W20-007 | B10: W20 | C10: Koleksiyonu paylaş | D10: Public koleksiyon. | E10: 1. Paylaş linkini kopyala | F10: Link açılınca koleksiyon görünür. | H10: Beklemede | L10: Orta
A11: W20-008 | B11: W20 | C11: Beğendiğim koleksiyonlar | D11: Başkalarının kol. beğenildi. | E11: 1. /collections/liked aç | F11: Beğenilenler listelenir. | H11: Beklemede | L11: Orta
A14: Bu sayfadaki tüm senaryolar test edilmiş ve sonuçlar yukarıda işaretlenmiştir.
A15: Test Eden (Tarodan) | D15: Tarih | G15: Onaylayan (Müşteri) | J15: Tarih

Sheet W21 - Üyelik Membership
A1: W21 — Üyelik Planları
A2: Plan seçimi, satın alma, yenileme, iptal, downgrade.
A3: Test ID | B3: Modül / Sayfa | C3: Senaryo / Test Adı | D3: Önkoşullar | E3: Adımlar (numaralı) | F3: Beklenen Sonuç | G3: Gerçek Sonuç | H3: Durum | I3: Test Eden | J3: Test Tarihi | K3: Tarayıcı / Cihaz | L3: Öncelik | M3: Notlar / Hata Linki
A4: W21-001 | B4: W21 | C4: Üyelik planları sayfası | D4: — | E4: 1. /pricing aç | F4: Free / Basic / Premium / Business kartları, özellikler tablosu görünür. | H4: Beklemede | L4: Orta
A5: W21-002 | B5: W21 | C5: Plan satın alma | D5: Üye giriş. | E5: 1. Premium 'Seç'e bas 2. /membership/checkout aç 3. PayTR ile öde | F5: Üyelik aktif; başarı sayfası; mail. | H5: Beklemede | L5: Kritik
A6: W21-003 | B6: W21 | C6: Üyelik avantajları yansıması | D6: Premium aktif. | E6: 1. İlanlar, ödemeler kontrol | F6: Komisyon oranı düşer, ilan limiti artar, featured imkan açılır. | H6: Beklemede | L6: Orta
A7: W21-004 | B7: W21 | C7: Yenileme uyarısı (7 gün kala) | D7: Premium 7 gün sonra bitiyor. | E7: 1. Cron'u bekle | F7: Mail + in-app uyarı. | H7: Beklemede | L7: Orta
A8: W21-005 | B8: W21 | C8: Yenileme uyarısı (1 gün kala) | D8: 1 gün kaldı. | E8: 1. Cron'u bekle | F8: Acil yenileme maili. | H8: Beklemede | L8: Orta
A9: W21-006 | B9: W21 | C9: Üyelik iptal | D9: Aktif üyelik. | E9: 1. /membership/manage → İptal | F9: Mevcut periyot sonuna kadar aktif; yenileme yok; mail. | H9: Beklemede | L9: Orta
A10: W21-007 | B10: W21 | C10: Üyelik bitti — otomatik downgrade | D10: Periyot doldu. | E10: 1. — | F10: Free tier'a düşer; ilan limiti uygulanır; mail. | H10: Beklemede | L10: Orta
A11: W21-008 | B11: W21 | C11: Yıllık plan ile ödeme | D11: Yıllık seçenek. | E11: 1. Yıllık 'Seç', öde | F11: İndirimli yıllık fiyat uygulanır; periyot 1 yıl. | H11: Beklemede | L11: Orta
A14: Bu sayfadaki tüm senaryolar test edilmiş ve sonuçlar yukarıda işaretlenmiştir.
A15: Test Eden (Tarodan) | D15: Tarih | G15: Onaylayan (Müşteri) | J15: Tarih

Sheet W22 - Statik & Yasal
A1: W22 — Statik ve Yasal Sayfalar
A2: KVKK, gizlilik, mesafeli satış, kargo politikası, FAQ vs.
A3: Test ID | B3: Modül / Sayfa | C3: Senaryo / Test Adı | D3: Önkoşullar | E3: Adımlar (numaralı) | F3: Beklenen Sonuç | G3: Gerçek Sonuç | H3: Durum | I3: Test Eden | J3: Test Tarihi | K3: Tarayıcı / Cihaz | L3: Öncelik | M3: Notlar / Hata Linki
A4: W22-001 | B4: W22 | C4: Gizlilik politikası | D4: — | E4: 1. /privacy aç | F4: Sayfa açılır; içerik güncel. | H4: Beklemede | L4: Orta
A5: W22-002 | B5: W22 | C5: Kullanım şartları | D5: — | E5: 1. /terms aç | F5: Sayfa açılır. | H5: Beklemede | L5: Orta
A6: W22-003 | B6: W22 | C6: Mesafeli satış sözleşmesi | D6: — | E6: 1. /distance-sales aç | F6: Sayfa açılır; checkout'tan link çalışır. | H6: Beklemede | L6: Orta
A7: W22-004 | B7: W22 | C7: İade politikası | D7: — | E7: 1. /refund-policy aç | F7: Sayfa açılır. | H7: Beklemede | L7: Orta
A8: W22-005 | B8: W22 | C8: Kargo & teslimat | D8: — | E8: 1. /shipping-delivery aç | F8: Sayfa açılır. | H8: Beklemede | L8: Orta
A9: W22-006 | B9: W22 | C9: FAQ | D9: — | E9: 1. /faq aç | F9: Akordeon çalışır; kategoriler doğru. | H9: Beklemede | L9: Orta
A10: W22-007 | B10: W22 | C10: Çerez bildirimi banner | D10: İlk ziyaret. | E10: 1. Anasayfayı aç | F10: Çerez banner görünür; kabul/red kalıcı. | H10: Beklemede | L10: Orta
A11: W22-008 | B11: W22 | C11: İletişim formu | D11: — | E11: 1. /contact aç, formu doldur, gönder | F11: Mail tetiklenir; teşekkür mesajı. | H11: Beklemede | L11: Orta
A12: W22-009 | B12: W22 | C12: Newsletter aboneliği | D12: — | E12: 1. /newsletter aç, e-posta gir | F12: Onay maili (double opt-in); abonelik aktif. | H12: Beklemede | L12: Orta
A13: W22-010 | B13: W22 | C13: Newsletter çıkış | D13: Abone. | E13: 1. /newsletter/unsubscribe linki | F13: Abonelik kalkar. | H13: Beklemede | L13: Orta
A16: Bu sayfadaki tüm senaryolar test edilmiş ve sonuçlar yukarıda işaretlenmiştir.
A17: Test Eden (Tarodan) | D17: Tarih | G17: Onaylayan (Müşteri) | J17: Tarih

Sheet W23 - Mobil & Responsive
A1: W23 — Mobil Görünüm ve Responsive
A2: Mobil tarayıcıda kritik akışlar.
A3: Test ID | B3: Modül / Sayfa | C3: Senaryo / Test Adı | D3: Önkoşullar | E3: Adımlar (numaralı) | F3: Beklenen Sonuç | G3: Gerçek Sonuç | H3: Durum | I3: Test Eden | J3: Test Tarihi | K3: Tarayıcı / Cihaz | L3: Öncelik | M3: Notlar / Hata Linki
A4: W23-001 | B4: W23 | C4: Anasayfa mobil görünüm | D4: 375px genişlik. | E4: 1. Mobilde / aç | F4: Hamburger menü, hero ve carousel düzgün; horizontal scroll yok. | H4: Beklemede | L4: Orta
A5: W23-002 | B5: W23 | C5: Mobil menü ve arama | D5: — | E5: 1. Hamburger aç, arama kullan | F5: Tüm linkler erişilebilir; arama çalışır. | H5: Beklemede | L5: Orta
A6: W23-003 | B6: W23 | C6: Ürün galerisi swipe | D6: — | E6: 1. Ürün detayında galeri kaydır | F6: Touch swipe sorunsuz. | H6: Beklemede | L6: Orta
A7: W23-004 | B7: W23 | C7: Mobil checkout flow | D7: — | E7: 1. Mobilde sepet → checkout → ödeme | F7: Form alanları erişilebilir; klavye uygun (numerik, e-posta). | H7: Beklemede | L7: Orta
A8: W23-005 | B8: W23 | C8: PayTR iframe mobil uyumu | D8: — | E8: 1. Ödeme sayfasını mobilde tamamla | F8: iFrame full-width; 3D Secure çalışır. | H8: Beklemede | L8: Orta
A9: W23-006 | B9: W23 | C9: Tablet (iPad) görünümü | D9: 768px genişlik. | E9: 1. Birkaç sayfayı incele | F9: Layout uygun; grid kolon sayısı doğru. | H9: Beklemede | L9: Orta
A12: Bu sayfadaki tüm senaryolar test edilmiş ve sonuçlar yukarıda işaretlenmiştir.
A13: Test Eden (Tarodan) | D13: Tarih | G13: Onaylayan (Müşteri) | J13: Tarih

Sheet A01 - Admin Login & Yetki
A1: A01 — Admin Girişi ve Yetkilendirme
A2: Admin login, 2FA, role-based access, oturum yönetimi.
A3: Test ID | B3: Modül / Sayfa | C3: Senaryo / Test Adı | D3: Önkoşullar | E3: Adımlar (numaralı) | F3: Beklenen Sonuç | G3: Gerçek Sonuç | H3: Durum | I3: Test Eden | J3: Test Tarihi | K3: Tarayıcı / Cihaz | L3: Öncelik | M3: Notlar / Hata Linki
A4: A01-001 | B4: A01 | C4: Admin girişi | D4: Geçerli admin hesabı. | E4: 1. admin.tarodan.shop /login aç 2. E-posta + şifre + (varsa) 2FA gir | F4: Dashboard'a yönlendirilir; menü rolüne göre filtrelenir. | H4: Beklemede | L4: Kritik
A5: A01-002 | B5: A01 | C5: Yanlış şifre | D5: — | E5: 1. Yanlış şifre dene | F5: Hata; rate-limit; kilit eşiği uygulanır. | H5: Beklemede | L5: Orta
A6: A01-003 | B6: A01 | C6: Web kullanıcısının admin'e erişim denemesi | D6: Normal kullanıcı. | E6: 1. admin.tarodan.shop'a git | F6: Yetkisiz hatası; girişe yönlendirme. | H6: Beklemede | L6: Orta
A7: A01-004 | B7: A01 | C7: Moderatör rolü ile yetkisiz endpoint denemesi | D7: Moderatör login. | E7: 1. /settings sayfasına gitmeye çalış | F7: 403 / sayfa bulunamadı / menüde görünmez. | H7: Beklemede | L7: Orta
A8: A01-005 | B8: A01 | C8: Süper admin tüm sayfalara erişim | D8: Süper admin. | E8: 1. Tüm üst menü öğelerini dolaş | F8: Tüm sayfalar açılır. | H8: Beklemede | L8: Orta
A9: A01-006 | B9: A01 | C9: Oturum süresi dolması | D9: Inaktif 30+ dk. | E9: 1. Sayfa yenile | F9: Login'e yönlendirir. | H9: Beklemede | L9: Orta
A10: A01-007 | B10: A01 | C10: Admin çıkış | D10: — | E10: 1. Çıkış'a bas | F10: Oturum sonlanır; login sayfası. | H10: Beklemede | L10: Orta
A13: Bu sayfadaki tüm senaryolar test edilmiş ve sonuçlar yukarıda işaretlenmiştir.
A14: Test Eden (Tarodan) | D14: Tarih | G14: Onaylayan (Müşteri) | J14: Tarih

Sheet A02 - Dashboard & Analitik
A1: A02 — Dashboard, Analytics, Raporlar
A2: İstatistik kartları, grafikler, tarih aralığı, export.
A3: Test ID | B3: Modül / Sayfa | C3: Senaryo / Test Adı | D3: Önkoşullar | E3: Adımlar (numaralı) | F3: Beklenen Sonuç | G3: Gerçek Sonuç | H3: Durum | I3: Test Eden | J3: Test Tarihi | K3: Tarayıcı / Cihaz | L3: Öncelik | M3: Notlar / Hata Linki
A4: A02-001 | B4: A02 | C4: Dashboard kart sayıları | D4: — | E4: 1. /dashboard aç | F4: Toplam satış, sipariş, kullanıcı, komisyon kartları doğru. | H4: Beklemede | L4: Yüksek
A5: A02-002 | B5: A02 | C5: Dönem filtresi (gün/hafta/ay/özel) | D5: — | E5: 1. Dönem dropdown'undan seç | F5: Tüm metrikler ve grafikler güncellenir. | H5: Beklemede | L5: Orta
A6: A02-003 | B6: A02 | C6: Bekleyen işler paneli | D6: Pending ürün, sipariş, başvuru var. | E6: 1. — | F6: Sayılar gerçek zamanlı; tıklayınca ilgili sayfa açılır. | H6: Beklemede | L6: Orta
A7: A02-004 | B7: A02 | C7: Analytics sayfası | D7: — | E7: 1. /analytics aç | F7: Satış grafiği, kategori breakdown, trend görünür. | H7: Beklemede | L7: Orta
A8: A02-005 | B8: A02 | C8: Rapor export (CSV/Excel) | D8: — | E8: 1. Export butonu | F8: İndirilen dosya açılır; tüm sütunlar doğru. | H8: Beklemede | L8: Orta
A11: Bu sayfadaki tüm senaryolar test edilmiş ve sonuçlar yukarıda işaretlenmiştir.
A12: Test Eden (Tarodan) | D12: Tarih | G12: Onaylayan (Müşteri) | J12: Tarih

Sheet A03 - Ürün Yönetimi
A1: A03 — Ürün Listesi, Detay, Onay, Yorum
A2: Ürün moderasyonu, stok düzenleme, yorum yönetimi.
A3: Test ID | B3: Modül / Sayfa | C3: Senaryo / Test Adı | D3: Önkoşullar | E3: Adımlar (numaralı) | F3: Beklenen Sonuç | G3: Gerçek Sonuç | H3: Durum | I3: Test Eden | J3: Test Tarihi | K3: Tarayıcı / Cihaz | L3: Öncelik | M3: Notlar / Hata Linki
A4: A03-001 | B4: A03 | C4: Ürün listesi yükleme | D4: — | E4: 1. /products aç | F4: Tüm ürünler tabloda; filtre, sayfalama çalışır. | H4: Beklemede | L4: Kritik
A5: A03-002 | B5: A03 | C5: Pending ürünleri filtreleme | D5: — | E5: 1. Durum filtresi 'Beklemede' | F5: Sadece pending'ler listelenir. | H5: Beklemede | L5: Orta
A6: A03-003 | B6: A03 | C6: Ürün detay görüntüleme | D6: — | E6: 1. Bir ürünün detayını aç | F6: Tüm görseller, açıklama, fiyat, satıcı bilgileri görünür. | H6: Beklemede | L6: Orta
A7: A03-004 | B7: A03 | C7: Ürün onaylama | D7: Pending ürün. | E7: 1. 'Onayla' modal, onay yaz, kaydet | F7: Status 'active'; satıcıya onay maili gider; web'de görünür. | H7: Beklemede | L7: Kritik
A8: A03-005 | B8: A03 | C8: Ürün reddetme (sebep zorunlu) | D8: — | E8: 1. 'Reddet' modal, sebep yaz, kaydet | F8: Status 'rejected'; satıcıya sebepli mail; webde görünmez. | H8: Beklemede | L8: Kritik
A9: A03-006 | B9: A03 | C9: Toplu onay/red | D9: Birden fazla ürün seçili. | E9: 1. Toplu Onayla'ya bas | F9: Tümü işlenir; toplu mail gönderilir. | H9: Beklemede | L9: Orta
A10: A03-007 | B10: A03 | C10: Ürün silme | D10: — | E10: 1. Sil → onay | F10: Ürün soft-delete; satıcıya bildirim. | H10: Beklemede | L10: Orta
A11: A03-008 | B11: A03 | C11: Yorum onaylama / silme | D11: Pending yorum. | E11: 1. Yorum tab → onayla / sil | F11: Yorum görünür / kalkar; alıcıya bildirim. | H11: Beklemede | L11: Orta
A12: A03-009 | B12: A03 | C12: Admin yorum yanıtı | D12: — | E12: 1. Yorum altına admin yanıt yaz | F12: Yorumun altında 'Tarodan' cevabı görünür. | H12: Beklemede | L12: Orta
A13: A03-010 | B13: A03 | C13: Stok düzenleme | D13: — | E13: 1. Ürün detayında quantity değiştir | F13: Stok güncellenir; audit log düşer. | H13: Beklemede | L13: Orta
A16: Bu sayfadaki tüm senaryolar test edilmiş ve sonuçlar yukarıda işaretlenmiştir.
A17: Test Eden (Tarodan) | D17: Tarih | G17: Onaylayan (Müşteri) | J17: Tarih

Sheet A04 - Katalog Master
A1: A04 — Kategori, Marka, Attribute, Tag, Üretici, Model
A2: Master data CRUD işlemleri.
A3: Test ID | B3: Modül / Sayfa | C3: Senaryo / Test Adı | D3: Önkoşullar | E3: Adımlar (numaralı) | F3: Beklenen Sonuç | G3: Gerçek Sonuç | H3: Durum | I3: Test Eden | J3: Test Tarihi | K3: Tarayıcı / Cihaz | L3: Öncelik | M3: Notlar / Hata Linki
A4: A04-001 | B4: A04 | C4: Kategori CRUD | D4: — | E4: 1. /categories aç, ekle, düzenle, sil | F4: Tüm CRUD çalışır; ağaç yapı korunur. | H4: Beklemede | L4: Orta
A5: A04-002 | B5: A04 | C5: Marka CRUD ve logo yükleme | D5: — | E5: 1. /brands aç, marka ekle, logo yükle | F5: Marka oluşur; logo görünür. | H5: Beklemede | L5: Orta
A6: A04-003 | B6: A04 | C6: Attribute (özellik) ekleme | D6: — | E6: 1. /attributes aç, yeni attribute | F6: Ürün formunda yeni alan görünür. | H6: Beklemede | L6: Orta
A7: A04-004 | B7: A04 | C7: Tag yönetimi | D7: — | E7: 1. /tags ekle/sil | F7: Etiketler ürünlere atanabilir. | H7: Beklemede | L7: Orta
A8: A04-005 | B8: A04 | C8: Üretici (manufacturer) ekleme | D8: — | E8: 1. /manufacturers ekle | F8: /ureticiler/[slug] sayfası oluşur. | H8: Beklemede | L8: Orta
A9: A04-006 | B9: A04 | C9: Otomobil modeli | D9: — | E9: 1. /car-models ekle | F9: /models/[slug] oluşur. | H9: Beklemede | L9: Orta
A10: A04-007 | B10: A04 | C10: Koleksiyon oluşturma (admin) | D10: — | E10: 1. /collections (admin) aç, koleksiyon yarat, ürün seç | F10: Anasayfada featured görünür. | H10: Beklemede | L10: Orta
A11: A04-008 | B11: A04 | C11: CMS sayfa düzenleme | D11: — | E11: 1. /pages aç, gizlilik metnini güncelle | F11: Web tarafında /privacy güncellenmiş içerik gösterir. | H11: Beklemede | L11: Orta
A14: Bu sayfadaki tüm senaryolar test edilmiş ve sonuçlar yukarıda işaretlenmiştir.
A15: Test Eden (Tarodan) | D15: Tarih | G15: Onaylayan (Müşteri) | J15: Tarih

Sheet A05 - Sipariş Yönetimi
A1: A05 — Admin: Sipariş Listesi ve İşlemler
A2: Sipariş arama, filtre, durum güncelleme, kargo, fatura, manuel bildirim.
A3: Test ID | B3: Modül / Sayfa | C3: Senaryo / Test Adı | D3: Önkoşullar | E3: Adımlar (numaralı) | F3: Beklenen Sonuç | G3: Gerçek Sonuç | H3: Durum | I3: Test Eden | J3: Test Tarihi | K3: Tarayıcı / Cihaz | L3: Öncelik | M3: Notlar / Hata Linki
A4: A05-001 | B4: A05 | C4: Sipariş listesi | D4: — | E4: 1. /orders aç | F4: Tüm siparişler; filtre/arama çalışır. | H4: Beklemede | L4: Kritik
A5: A05-002 | B5: A05 | C5: Sipariş arama (no, alıcı) | D5: — | E5: 1. Arama kutusunu kullan | F5: Doğru sonuçlar. | H5: Beklemede | L5: Orta
A6: A05-003 | B6: A05 | C6: Sipariş detay açma | D6: — | E6: 1. /orders/[id] aç | F6: Tüm bilgiler; alıcı/satıcı linkleri. | H6: Beklemede | L6: Orta
A7: A05-004 | B7: A05 | C7: Manuel durum güncelleme | D7: — | E7: 1. Durum dropdown değiştir, kaydet | F7: Status değişir; ilgili otomatik bildirimler tetiklenir. | H7: Beklemede | L7: Yüksek
A8: A05-005 | B8: A05 | C8: Manuel kargo bilgisi girişi | D8: — | E8: 1. Kargo modalı → firma + tracking gir | F8: Alıcıya tracking maili. | H8: Beklemede | L8: Orta
A9: A05-006 | B9: A05 | C9: Fatura yazdırma / indirme | D9: — | E9: 1. Fatura PDF butonu | F9: PDF indirilir; vergi bilgileri doğru. | H9: Beklemede | L9: Orta
A10: A05-007 | B10: A05 | C10: Manuel bildirim gönderme | D10: — | E10: 1. 'Bildirim Gönder' modal, mesaj yaz, gönder | F10: Custom mail alıcıya gider. | H10: Beklemede | L10: Orta
A11: A05-008 | B11: A05 | C11: Komisyon ve vergi özeti | D11: — | E11: 1. Sipariş detayda finansal özeti incele | F11: Subtotal, KDV, komisyon, satıcı net tutarı doğru. | H11: Beklemede | L11: Orta
A14: Bu sayfadaki tüm senaryolar test edilmiş ve sonuçlar yukarıda işaretlenmiştir.
A15: Test Eden (Tarodan) | D15: Tarih | G15: Onaylayan (Müşteri) | J15: Tarih

Sheet A06 - Ödeme & İade & Payout
A1: A06 — Admin: Ödeme, İade, Payout Yönetimi
A2: Ödeme listesi, iade işlemi, satıcı payout süreçleri.
A3: Test ID | B3: Modül / Sayfa | C3: Senaryo / Test Adı | D3: Önkoşullar | E3: Adımlar (numaralı) | F3: Beklenen Sonuç | G3: Gerçek Sonuç | H3: Durum | I3: Test Eden | J3: Test Tarihi | K3: Tarayıcı / Cihaz | L3: Öncelik | M3: Notlar / Hata Linki
A4: A06-001 | B4: A06 | C4: Ödeme listesi | D4: — | E4: 1. /payments aç | F4: Tüm ödemeler durumları ile listelenir. | H4: Beklemede | L4: Orta
A5: A06-002 | B5: A06 | C5: Başarısız ödemeleri filtrele | D5: — | E5: 1. Durum 'failed' filtresi | F5: Sadece başarısızlar. | H5: Beklemede | L5: Orta
A6: A06-003 | B6: A06 | C6: Ödeme detayı / reconcile | D6: — | E6: 1. /payments/[id] aç | F6: Ödeme provider bilgileri, callback log; reconcile butonu. | H6: Beklemede | L6: Orta
A7: A06-004 | B7: A06 | C7: Ödeme istatistikleri | D7: — | E7: 1. /payments/statistics aç | F7: Başarı oranı, sağlayıcı dağılımı. | H7: Beklemede | L7: Orta
A8: A06-005 | B8: A06 | C8: İadeler listesi | D8: — | E8: 1. /refunds aç | F8: Tüm iadeler tarihe göre; filtre. | H8: Beklemede | L8: Orta
A9: A06-006 | B9: A06 | C9: Manuel iade tetikleme | D9: Sipariş detayda. | E9: 1. 'Manuel İade' butonu | F9: Tutar gir, sebep yaz; PayTR refund tetiklenir. | H9: Beklemede | L9: Yüksek
A10: A06-007 | B10: A06 | C10: Payout listesi | D10: — | E10: 1. /payouts aç | F10: Pending/processing/completed/failed payoutlar. | H10: Beklemede | L10: Orta
A11: A06-008 | B11: A06 | C11: Manuel payout oluşturma | D11: — | E11: 1. Yeni payout, satıcı seç, tutar gir | F11: Payout queue'ya eklenir. | H11: Beklemede | L11: Orta
A12: A06-009 | B12: A06 | C12: Failed payout retry | D12: Hata almış payout. | E12: 1. Retry butonu | F12: Yeniden denenir; başarılıysa completed. | H12: Beklemede | L12: Orta
A15: Bu sayfadaki tüm senaryolar test edilmiş ve sonuçlar yukarıda işaretlenmiştir.
A16: Test Eden (Tarodan) | D16: Tarih | G16: Onaylayan (Müşteri) | J16: Tarih

Sheet A07 - Komisyon Vergi Kargo
A1: A07 — Komisyon, Vergi, Kargo Ayarları
A2: Platform finansal ve operasyonel ayarları.
A3: Test ID | B3: Modül / Sayfa | C3: Senaryo / Test Adı | D3: Önkoşullar | E3: Adımlar (numaralı) | F3: Beklenen Sonuç | G3: Gerçek Sonuç | H3: Durum | I3: Test Eden | J3: Test Tarihi | K3: Tarayıcı / Cihaz | L3: Öncelik | M3: Notlar / Hata Linki
A4: A07-001 | B4: A07 | C4: Komisyon oranı düzenleme | D4: — | E4: 1. /commission aç, oranı değiştir, kaydet | F4: Yeni oran sonraki siparişlere uygulanır. | H4: Beklemede | L4: Orta
A5: A07-002 | B5: A07 | C5: Kategori bazlı komisyon | D5: — | E5: 1. Kategori-spesifik oran ekle | F5: İlgili kategori siparişlerinde özel oran kullanılır. | H5: Beklemede | L5: Orta
A6: A07-003 | B6: A07 | C6: Vergi (KDV) oranı | D6: — | E6: 1. /tax aç, oran değiştir | F6: Yeni siparişlerde uygulanır. | H6: Beklemede | L6: Orta
A7: A07-004 | B7: A07 | C7: Kargo şirketi yönetimi | D7: — | E7: 1. /shipping aç, firma ekle/devre dışı | F7: Listede güncellenir; sipariş kargo dropdown'unda görünür. | H7: Beklemede | L7: Orta
A8: A07-005 | B8: A07 | C8: Kargo ücreti tarifesi | D8: — | E8: 1. Ücret kuralları (eşik, ağırlık) | F8: Checkout'ta doğru hesaplanır. | H8: Beklemede | L8: Orta
A11: Bu sayfadaki tüm senaryolar test edilmiş ve sonuçlar yukarıda işaretlenmiştir.
A12: Test Eden (Tarodan) | D12: Tarih | G12: Onaylayan (Müşteri) | J12: Tarih

Sheet A08 - Kullanıcı Yönetimi
A1: A08 — Kullanıcı Listesi ve Detayı
A2: Arama, filtre, ban/unban, kullanıcı geçmişi.
A3: Test ID | B3: Modül / Sayfa | C3: Senaryo / Test Adı | D3: Önkoşullar | E3: Adımlar (numaralı) | F3: Beklenen Sonuç | G3: Gerçek Sonuç | H3: Durum | I3: Test Eden | J3: Test Tarihi | K3: Tarayıcı / Cihaz | L3: Öncelik | M3: Notlar / Hata Linki
A4: A08-001 | B4: A08 | C4: Kullanıcı listesi | D4: — | E4: 1. /users aç | F4: Tüm kullanıcılar; filtre/arama. | H4: Beklemede | L4: Orta
A5: A08-002 | B5: A08 | C5: Kullanıcı arama (e-posta/ad) | D5: — | E5: 1. Arama yap | F5: Doğru kullanıcı bulunur. | H5: Beklemede | L5: Orta
A6: A08-003 | B6: A08 | C6: Kullanıcı detayı | D6: — | E6: 1. Detay aç | F6: Kişisel bilgi, üyelik, son sipariş/ürün/takas/mesaj. | H6: Beklemede | L6: Orta
A7: A08-004 | B7: A08 | C7: Kullanıcı banlama (sebep) | D7: — | E7: 1. 'Banla' modal, sebep yaz, onayla | F7: Kullanıcı login olamaz; tüm aksiyonlar engellenir; mail bildirimi. | H7: Beklemede | L7: Yüksek
A8: A08-005 | B8: A08 | C8: Ban kaldırma | D8: Banlı kullanıcı. | E8: 1. Unban butonu | F8: Hesap aktif olur. | H8: Beklemede | L8: Orta
A9: A08-006 | B9: A08 | C9: Banlı satıcı ürünleri | D9: — | E9: 1. Banlı satıcının ilanlarını kontrol | F9: İlanlar pasifleştirilir/gizlenir. | H9: Beklemede | L9: Orta
A10: A08-007 | B10: A08 | C10: Kullanıcı şifresini sıfırlama (admin) | D10: — | E10: 1. Admin → 'Şifre sıfırlama maili gönder' | F10: Mail gider; admin şifreyi göremez. | H10: Beklemede | L10: Orta
A13: Bu sayfadaki tüm senaryolar test edilmiş ve sonuçlar yukarıda işaretlenmiştir.
A14: Test Eden (Tarodan) | D14: Tarih | G14: Onaylayan (Müşteri) | J14: Tarih

Sheet A09 - Satıcı Başvuru & Performa
A1: A09 — Satıcı Başvuruları ve Performans
A2: Satıcı başvurusu inceleme, onay, performans metrikleri.
A3: Test ID | B3: Modül / Sayfa | C3: Senaryo / Test Adı | D3: Önkoşullar | E3: Adımlar (numaralı) | F3: Beklenen Sonuç | G3: Gerçek Sonuç | H3: Durum | I3: Test Eden | J3: Test Tarihi | K3: Tarayıcı / Cihaz | L3: Öncelik | M3: Notlar / Hata Linki
A4: A09-001 | B4: A09 | C4: Satıcı başvuru listesi | D4: — | E4: 1. /sellers/applications aç | F4: Pending başvurular; belge linkleri. | H4: Beklemede | L4: Orta
A5: A09-002 | B5: A09 | C5: Başvuru detayı inceleme | D5: — | E5: 1. Bir başvuruyu seç | F5: Vergi no, KVKK belgesi, kimlik vs. görünür. | H5: Beklemede | L5: Orta
A6: A09-003 | B6: A09 | C6: Başvuru onayı | D6: — | E6: 1. Onayla butonu | F6: User.isSeller=true; satıcıya 'hesabınız aktif' maili. | H6: Beklemede | L6: Kritik
A7: A09-004 | B7: A09 | C7: Başvuru reddi (sebep) | D7: — | E7: 1. Reddet modal, sebep yaz, kaydet | F7: Sebep maille bildirilir; başvuru cancelled. | H7: Beklemede | L7: Orta
A8: A09-005 | B8: A09 | C8: Satıcı performans sayfası | D8: — | E8: 1. /sellers/performance aç | F8: Tamamlama oranı, itiraz oranı, rating, kargo hızı görünür. | H8: Beklemede | L8: Orta
A9: A09-006 | B9: A09 | C9: Düşük performans satıcı uyarısı | D9: Eşik altı satıcı. | E9: 1. — | F9: Listeyle işaretlenir; uyarı maili otomatik. | H9: Beklemede | L9: Orta
A12: Bu sayfadaki tüm senaryolar test edilmiş ve sonuçlar yukarıda işaretlenmiştir.
A13: Test Eden (Tarodan) | D13: Tarih | G13: Onaylayan (Müşteri) | J13: Tarih

Sheet A10 - Üyelik Tier Yönetimi
A1: A10 — Membership Tier Yönetimi
A2: Plan tanımı, fiyat, özellikler, geçerlilik.
A3: Test ID | B3: Modül / Sayfa | C3: Senaryo / Test Adı | D3: Önkoşullar | E3: Adımlar (numaralı) | F3: Beklenen Sonuç | G3: Gerçek Sonuç | H3: Durum | I3: Test Eden | J3: Test Tarihi | K3: Tarayıcı / Cihaz | L3: Öncelik | M3: Notlar / Hata Linki
A4: A10-001 | B4: A10 | C4: Mevcut tier'ları listele | D4: — | E4: 1. /membership-tiers aç | F4: Free, Basic, Premium, Business görünür. | H4: Beklemede | L4: Orta
A5: A10-002 | B5: A10 | C5: Tier fiyatı değiştirme | D5: — | E5: 1. Premium fiyatını güncelle | F5: Yeni satın almalarda yeni fiyat geçerli; mevcut üyeler etkilenmez. | H5: Beklemede | L5: Orta
A6: A10-003 | B6: A10 | C6: Tier özelliği güncelleme (ilan limiti) | D6: — | E6: 1. Ilan limitini değiştir | F6: Mevcut üyelerin limiti güncellenir. | H6: Beklemede | L6: Orta
A7: A10-004 | B7: A10 | C7: Yeni tier oluşturma | D7: — | E7: 1. + Yeni Tier | F7: Pricing sayfasında listelenir. | H7: Beklemede | L7: Orta
A10: Bu sayfadaki tüm senaryolar test edilmiş ve sonuçlar yukarıda işaretlenmiştir.
A11: Test Eden (Tarodan) | D11: Tarih | G11: Onaylayan (Müşteri) | J11: Tarih

Sheet A11 - İndirim & Kupon
A1: A11 — Discount / Coupon Yönetimi
A2: Kupon oluşturma, kapsam, limit, flash sale.
A3: Test ID | B3: Modül / Sayfa | C3: Senaryo / Test Adı | D3: Önkoşullar | E3: Adımlar (numaralı) | F3: Beklenen Sonuç | G3: Gerçek Sonuç | H3: Durum | I3: Test Eden | J3: Test Tarihi | K3: Tarayıcı / Cihaz | L3: Öncelik | M3: Notlar / Hata Linki
A4: A11-001 | B4: A11 | C4: Yeni kupon oluştur (yüzde) | D4: — | E4: 1. /discounts → Yeni 2. Kod, %, kapsam, tarih, limit gir, kaydet | F4: Kupon aktif; web'de uygulanabilir. | H4: Beklemede | L4: Yüksek
A5: A11-002 | B5: A11 | C5: Sabit tutar kuponu | D5: — | E5: 1. Sabit tutar tipinde oluştur | F5: Sepetten sabit miktar düşer. | H5: Beklemede | L5: Orta
A6: A11-003 | B6: A11 | C6: BOGO / çoklu alım kuponu | D6: — | E6: 1. BOGO seç, kategoriler tanımla | F6: Sepete uygun ürünler eklenince otomatik uygulanır. | H6: Beklemede | L6: Orta
A7: A11-004 | B7: A11 | C7: Kategori bazlı kupon | D7: — | E7: 1. Kapsam: Kategori, kategori seç | F7: Sadece o kategoride uygulanır. | H7: Beklemede | L7: Orta
A8: A11-005 | B8: A11 | C8: Min sepet eşiği | D8: — | E8: 1. Min sepet tutarı tanımla | F8: Eşik altında kupon uygulanmaz. | H8: Beklemede | L8: Orta
A9: A11-006 | B9: A11 | C9: Kullanım limiti (kişi başı) | D9: — | E9: 1. Kişi başı 1 limit | F9: İkinci kullanımda hata. | H9: Beklemede | L9: Orta
A10: A11-007 | B10: A11 | C10: Kupon devre dışı bırakma | D10: Aktif kupon. | E10: 1. Pasif yap | F10: Kullanılamaz; web'de hata. | H10: Beklemede | L10: Orta
A11: A11-008 | B11: A11 | C11: Flash sale işareti | D11: — | E11: 1. Flash sale checkbox | F11: Anasayfada özel banner; geri sayım. | H11: Beklemede | L11: Orta
A12: A11-009 | B12: A11 | C12: Kupon istatistikleri | D12: Kullanılmış kupon. | E12: 1. Detay aç | F12: Kullanım sayısı, toplam indirim tutarı. | H12: Beklemede | L12: Orta
A15: Bu sayfadaki tüm senaryolar test edilmiş ve sonuçlar yukarıda işaretlenmiştir.
A16: Test Eden (Tarodan) | D16: Tarih | G16: Onaylayan (Müşteri) | J16: Tarih

Sheet A12 - Email Şablonları
A1: A12 — E-posta Şablon Yönetimi
A2: Mail içeriklerinin admin tarafından düzenlenmesi.
A3: Test ID | B3: Modül / Sayfa | C3: Senaryo / Test Adı | D3: Önkoşullar | E3: Adımlar (numaralı) | F3: Beklenen Sonuç | G3: Gerçek Sonuç | H3: Durum | I3: Test Eden | J3: Test Tarihi | K3: Tarayıcı / Cihaz | L3: Öncelik | M3: Notlar / Hata Linki
A4: A12-001 | B4: A12 | C4: Şablon listesi | D4: — | E4: 1. /email-templates aç | F4: Tüm template key'leri listelenir. | H4: Beklemede | L4: Orta
A5: A12-002 | B5: A12 | C5: Şablon düzenleme | D5: — | E5: 1. Bir template aç, subject + bodyHtml düzenle, kaydet | F5: Sonraki maillerde yeni içerik kullanılır. | H5: Beklemede | L5: Orta
A6: A12-003 | B6: A12 | C6: Şablon önizleme | D6: — | E6: 1. Preview butonu, sample data gir | F6: Render edilmiş HTML görünür. | H6: Beklemede | L6: Orta
A7: A12-004 | B7: A12 | C7: Şablon değişkenleri ({{var}}) | D7: — | E7: 1. Şablona {{customerName}} ekle, kaydet | F7: Mailde değişken gerçek değerle değişir. | H7: Beklemede | L7: Orta
A8: A12-005 | B8: A12 | C8: Geçersiz HTML | D8: — | E8: 1. Bozuk HTML kaydetmeyi dene | F8: Validasyon uyarısı; kaydetmez. | H8: Beklemede | L8: Orta
A11: Bu sayfadaki tüm senaryolar test edilmiş ve sonuçlar yukarıda işaretlenmiştir.
A12: Test Eden (Tarodan) | D12: Tarih | G12: Onaylayan (Müşteri) | J12: Tarih

Sheet A13 - Yorum & Moderasyon
A1: A13 — Yorum ve Moderasyon Kuyruğu
A2: Yorum onayı, spam tespiti, moderasyon işleyişi.
A3: Test ID | B3: Modül / Sayfa | C3: Senaryo / Test Adı | D3: Önkoşullar | E3: Adımlar (numaralı) | F3: Beklenen Sonuç | G3: Gerçek Sonuç | H3: Durum | I3: Test Eden | J3: Test Tarihi | K3: Tarayıcı / Cihaz | L3: Öncelik | M3: Notlar / Hata Linki
A4: A13-001 | B4: A13 | C4: Yorum kuyruğu | D4: Pending yorumlar. | E4: 1. /reviews aç | F4: Pending yorumlar; ürün/satıcı/alıcı bilgisi görünür. | H4: Beklemede | L4: Orta
A5: A13-002 | B5: A13 | C5: Yorum onayla / reddet / sil / spam | D5: — | E5: 1. Aksiyonları tek tek dene | F5: Her aksiyon doğru sonuç verir; bildirimler gider. | H5: Beklemede | L5: Orta
A6: A13-003 | B6: A13 | C6: Admin yanıt verme | D6: — | E6: 1. Yoruma admin yanıt | F6: Web'de 'Tarodan' yanıtı görünür. | H6: Beklemede | L6: Orta
A7: A13-004 | B7: A13 | C7: Moderasyon kuyruğu | D7: Şikayet edilmiş ürün/mesaj. | E7: 1. /moderation aç | F7: Şikayetler listelenir; aksiyon menüsü çalışır. | H7: Beklemede | L7: Orta
A8: A13-005 | B8: A13 | C8: Şikayet → ürün gizleme | D8: — | E8: 1. Şikayet sonrası ürün gizle | F8: Ürün web'de görünmez; satıcıya bildirim. | H8: Beklemede | L8: Orta
A11: Bu sayfadaki tüm senaryolar test edilmiş ve sonuçlar yukarıda işaretlenmiştir.
A12: Test Eden (Tarodan) | D12: Tarih | G12: Onaylayan (Müşteri) | J12: Tarih

Sheet A14 - Reklamlar
A1: A14 — Reklam ve Sponsorlu İçerik
A2: Banner, sponsorlu ürün, görünürlük yönetimi.
A3: Test ID | B3: Modül / Sayfa | C3: Senaryo / Test Adı | D3: Önkoşullar | E3: Adımlar (numaralı) | F3: Beklenen Sonuç | G3: Gerçek Sonuç | H3: Durum | I3: Test Eden | J3: Test Tarihi | K3: Tarayıcı / Cihaz | L3: Öncelik | M3: Notlar / Hata Linki
A4: A14-001 | B4: A14 | C4: Reklam listesi | D4: — | E4: 1. /ads aç | F4: Aktif/pasif reklamlar listelenir. | H4: Beklemede | L4: Orta
A5: A14-002 | B5: A14 | C5: Yeni reklam oluştur | D5: — | E5: 1. Yeni reklam, görsel, link, tarih | F5: Web'de hedef konumda görünür. | H5: Beklemede | L5: Orta
A6: A14-003 | B6: A14 | C6: Reklam pasifleştirme | D6: Aktif reklam. | E6: 1. Pasif yap | F6: Web'den kalkar. | H6: Beklemede | L6: Orta
A7: A14-004 | B7: A14 | C7: Reklam tıklanma istatistiği | D7: — | E7: 1. Detay aç | F7: Görüntülenme/tıklanma sayıları. | H7: Beklemede | L7: Orta
A10: Bu sayfadaki tüm senaryolar test edilmiş ve sonuçlar yukarıda işaretlenmiştir.
A11: Test Eden (Tarodan) | D11: Tarih | G11: Onaylayan (Müşteri) | J11: Tarih

Sheet A15 - Takas Yönetimi
A1: A15 — Admin: Takas (Trade) Yönetimi
A2: Takas listesi, depo akışı, anlaşmazlık çözümü.
A3: Test ID | B3: Modül / Sayfa | C3: Senaryo / Test Adı | D3: Önkoşullar | E3: Adımlar (numaralı) | F3: Beklenen Sonuç | G3: Gerçek Sonuç | H3: Durum | I3: Test Eden | J3: Test Tarihi | K3: Tarayıcı / Cihaz | L3: Öncelik | M3: Notlar / Hata Linki
A4: A15-001 | B4: A15 | C4: Takas listesi | D4: — | E4: 1. /trades aç | F4: Tüm takaslar durumlarıyla. | H4: Beklemede | L4: Orta
A5: A15-002 | B5: A15 | C5: Disputed takasları filtrele | D5: — | E5: 1. Durum: Disputed | F5: Anlaşmazlık olanlar listelenir. | H5: Beklemede | L5: Orta
A6: A15-003 | B6: A15 | C6: Takas detayı | D6: — | E6: 1. /trades/[id] aç | F6: Iki tarafın ürünleri, kargo bilgileri, mesaj geçmişi. | H6: Beklemede | L6: Orta
A7: A15-004 | B7: A15 | C7: Depo akışı: alındı işaretleme | D7: Ürünler depoya geldi. | E7: 1. 'Depoda Alındı' işaretle | F7: Status 'admin_reviewing'. | H7: Beklemede | L7: Orta
A8: A15-005 | B8: A15 | C8: Depo onay / red | D8: Reviewing. | E8: 1. Onay → karşıya gönder; red → iade | F8: İlgili akış başlar. | H8: Beklemede | L8: Orta
A9: A15-006 | B9: A15 | C9: Anlaşmazlık çözümü | D9: Disputed. | E9: 1. Karar ver: Tamamla / İptal | F9: Takas sonlanır; gerekirse refund tetiklenir. | H9: Beklemede | L9: Yüksek
A12: Bu sayfadaki tüm senaryolar test edilmiş ve sonuçlar yukarıda işaretlenmiştir.
A13: Test Eden (Tarodan) | D13: Tarih | G13: Onaylayan (Müşteri) | J13: Tarih

Sheet A16 - Destek (Support)
A1: A16 — Destek Talepleri
A2: Bilet listesi, yanıt, durum, iç not.
A3: Test ID | B3: Modül / Sayfa | C3: Senaryo / Test Adı | D3: Önkoşullar | E3: Adımlar (numaralı) | F3: Beklenen Sonuç | G3: Gerçek Sonuç | H3: Durum | I3: Test Eden | J3: Test Tarihi | K3: Tarayıcı / Cihaz | L3: Öncelik | M3: Notlar / Hata Linki
A4: A16-001 | B4: A16 | C4: Bilet listesi | D4: — | E4: 1. /support aç | F4: Filtre (durum, öncelik, kategori) çalışır. | H4: Beklemede | L4: Orta
A5: A16-002 | B5: A16 | C5: Bilet detayı | D5: — | E5: 1. /support/[id] aç | F5: Konuşma, kullanıcı bilgisi, ekler görünür. | H5: Beklemede | L5: Orta
A6: A16-003 | B6: A16 | C6: Yanıt gönderme | D6: — | E6: 1. Yanıt yaz, gönder | F6: Müşteriye mail; konuşma güncellenir. | H6: Beklemede | L6: Orta
A7: A16-004 | B7: A16 | C7: İç not (sadece admin) | D7: — | E7: 1. İç not checkbox + mesaj | F7: Sadece admin görür; müşteriye görünmez. | H7: Beklemede | L7: Orta
A8: A16-005 | B8: A16 | C8: Bilet kapatma | D8: — | E8: 1. Status: Çözüldü → Kapat | F8: Yeni mesaj alamaz; otomatik feedback maili opsiyonel. | H8: Beklemede | L8: Orta
A9: A16-006 | B9: A16 | C9: Öncelik değiştirme | D9: — | E9: 1. Acil yap | F9: Listede üste çıkar; renkli rozet. | H9: Beklemede | L9: Orta
A12: Bu sayfadaki tüm senaryolar test edilmiş ve sonuçlar yukarıda işaretlenmiştir.
A13: Test Eden (Tarodan) | D13: Tarih | G13: Onaylayan (Müşteri) | J13: Tarih

Sheet A17 - Roller & İzinler
A1: A17 — Rol ve İzin Yönetimi
A2: Rol oluşturma, izin atama, admin kullanıcı ekleme.
A3: Test ID | B3: Modül / Sayfa | C3: Senaryo / Test Adı | D3: Önkoşullar | E3: Adımlar (numaralı) | F3: Beklenen Sonuç | G3: Gerçek Sonuç | H3: Durum | I3: Test Eden | J3: Test Tarihi | K3: Tarayıcı / Cihaz | L3: Öncelik | M3: Notlar / Hata Linki
A4: A17-001 | B4: A17 | C4: Mevcut roller | D4: — | E4: 1. /roles aç | F4: Süper Admin, Yönetici, Moderatör listelenir. | H4: Beklemede | L4: Orta
A5: A17-002 | B5: A17 | C5: Yeni rol oluşturma | D5: — | E5: 1. Yeni rol, izinleri seç, kaydet | F5: Yeni rol ataması yapılabilir. | H5: Beklemede | L5: Orta
A6: A17-003 | B6: A17 | C6: Rol izinlerini değiştirme | D6: — | E6: 1. Bir rolü düzenle, izinleri kaldır/ekle | F6: Aktif kullanıcılar bir sonraki istekte yeni izinlerle çalışır. | H6: Beklemede | L6: Orta
A7: A17-004 | B7: A17 | C7: Rol silme | D7: Kimsenin atanmadığı rol. | E7: 1. Sil → onay | F7: Silinir. | H7: Beklemede | L7: Orta
A8: A17-005 | B8: A17 | C8: Atanmış rolü silmeye çalışma | D8: Kullanıcısı olan rol. | E8: 1. Silmeye çalış | F8: Hata; önce kullanıcıların rollerini değiştir uyarısı. | H8: Beklemede | L8: Orta
A9: A17-006 | B9: A17 | C9: Yeni admin kullanıcı ekleme | D9: — | E9: 1. Admin Kullanıcılar tab → Yeni | F9: Davet maili / hesap oluşur; rol atanır. | H9: Beklemede | L9: Orta
A12: Bu sayfadaki tüm senaryolar test edilmiş ve sonuçlar yukarıda işaretlenmiştir.
A13: Test Eden (Tarodan) | D13: Tarih | G13: Onaylayan (Müşteri) | J13: Tarih

Sheet A18 - Platform Ayarları
A1: A18 — Genel Ayarlar, İlan, Takas, Mesaj, Üyelik, Ödeme
A2: Tab tab tüm settings ayarları.
A3: Test ID | B3: Modül / Sayfa | C3: Senaryo / Test Adı | D3: Önkoşullar | E3: Adımlar (numaralı) | F3: Beklenen Sonuç | G3: Gerçek Sonuç | H3: Durum | I3: Test Eden | J3: Test Tarihi | K3: Tarayıcı / Cihaz | L3: Öncelik | M3: Notlar / Hata Linki
A4: A18-001 | B4: A18 | C4: Genel ayarlar (logo, dil, para birimi) | D4: — | E4: 1. /settings → Genel tab, değiştir, kaydet | F4: Web tarafında değişiklik anında veya cache TTL sonrası yansır. | H4: Beklemede | L4: Orta
A5: A18-002 | B5: A18 | C5: İlan limitleri tier başına | D5: — | E5: 1. İlan tab, limitleri değiştir | F5: Yeni limit tüm yeni ilan oluşturma denemelerinde uygulanır. | H5: Beklemede | L5: Orta
A6: A18-003 | B6: A18 | C6: Takas zamanlamaları | D6: — | E6: 1. Takas tab, response/shipping/onay sürelerini değiştir | F6: Yeni takaslarda yeni süreler kullanılır. | H6: Beklemede | L6: Orta
A7: A18-004 | B7: A18 | C7: Mesaj uzunluk sınırı | D7: — | E7: 1. Mesaj tab, max length değiştir | F7: Web mesaj kutusunda yeni sınır uygulanır. | H7: Beklemede | L7: Orta
A8: A18-005 | B8: A18 | C8: Üyelik fiyatları | D8: — | E8: 1. Üyelik tab, fiyatları değiştir | F8: /pricing sayfasında güncellenir. | H8: Beklemede | L8: Orta
A9: A18-006 | B9: A18 | C9: PayTR ayarları (Test/Canlı geçiş) | D9: — | E9: 1. /settings/payments aç, Live moda al | F9: Confirmation diyalogu; ardından canlı keys kullanılır. | H9: Beklemede | L9: Kritik
A10: A18-007 | B10: A18 | C10: PayTR test ödemesi | D10: Test mod aktif. | E10: 1. Web'den test ödeme yap | F10: Sandbox işlemi başarılı. | H10: Beklemede | L10: Orta
A13: Bu sayfadaki tüm senaryolar test edilmiş ve sonuçlar yukarıda işaretlenmiştir.
A14: Test Eden (Tarodan) | D14: Tarih | G14: Onaylayan (Müşteri) | J14: Tarih

Sheet A19 - Audit & Sistem Logları
A1: A19 — Audit ve Sistem Logları
A2: Admin işlem geçmişi, hata logları.
A3: Test ID | B3: Modül / Sayfa | C3: Senaryo / Test Adı | D3: Önkoşullar | E3: Adımlar (numaralı) | F3: Beklenen Sonuç | G3: Gerçek Sonuç | H3: Durum | I3: Test Eden | J3: Test Tarihi | K3: Tarayıcı / Cihaz | L3: Öncelik | M3: Notlar / Hata Linki
A4: A19-001 | B4: A19 | C4: Audit log listesi | D4: Geçmiş admin aksiyonları. | E4: 1. /audit-logs aç | F4: Aksiyon, kullanıcı, zaman, IP, eski/yeni değer görünür. | H4: Beklemede | L4: Yüksek
A5: A19-002 | B5: A19 | C5: Audit log filtreleme | D5: — | E5: 1. Aksiyon türü filtre | F5: Doğru filtreleme. | H5: Beklemede | L5: Orta
A6: A19-003 | B6: A19 | C6: Sistem log | D6: — | E6: 1. /logs aç | F6: Hata/uyarı log'ları, severity, stack. | H6: Beklemede | L6: Orta
A7: A19-004 | B7: A19 | C7: Genel bildirim yayınlama | D7: — | E7: 1. /notifications → broadcast | F7: Tüm kullanıcılara in-app bildirim. | H7: Beklemede | L7: Orta
A10: Bu sayfadaki tüm senaryolar test edilmiş ve sonuçlar yukarıda işaretlenmiştir.
A11: Test Eden (Tarodan) | D11: Tarih | G11: Onaylayan (Müşteri) | J11: Tarih

Sheet E01 - E2E Misafir Satın Al
A1: E01 — Uçtan Uca: Misafir Satın Alma → Teslimat
A2: Üye olmadan: ürün gör → sepet → OTP checkout → ödeme → kargo → teslim → mailler.
A3: Test ID | B3: Modül / Sayfa | C3: Senaryo / Test Adı | D3: Önkoşullar | E3: Adımlar (numaralı) | F3: Beklenen Sonuç | G3: Gerçek Sonuç | H3: Durum | I3: Test Eden | J3: Test Tarihi | K3: Tarayıcı / Cihaz | L3: Öncelik | M3: Notlar / Hata Linki
A4: E01-001 | B4: E01 | C4: Adım 1: Misafir ürün arama | D4: Çıkış yapılmış oturum. | E4: 1. Anasayfa → ürün ara → ürün detayını aç | F4: Ürün detayı sorunsuz açılır. | H4: Beklemede | L4: Kritik
A5: E01-002 | B5: E01 | C5: Adım 2: Sepete ekle (misafir) | D5: — | E5: 1. 'Sepete Ekle' butonuna bas | F5: Misafir sepetine eklenir; sayaç +1. | H5: Beklemede | L5: Orta
A6: E01-003 | B6: E01 | C6: Adım 3: Misafir checkout başlatma | D6: Sepet dolu. | E6: 1. Sepete git → 'Ödemeye Geç' | F6: Misafir e-posta adımı gösterilir. | H6: Beklemede | L6: Orta
A7: E01-004 | B7: E01 | C7: Adım 4: E-posta OTP doğrulama | D7: — | E7: 1. E-posta gir → kod al → kodu gir | F7: Doğrulama OK. | H7: Beklemede | L7: Orta
A8: E01-005 | B8: E01 | C8: Adım 5: Adres ve ödeme | D8: — | E8: 1. Adres gir, sözleşmeyi onayla, ödemeye geç, PayTR ile öde | F8: Ödeme başarılı; /checkout/success açılır. | H8: Beklemede | L8: Orta
A9: E01-006 | B9: E01 | C9: Adım 6: Sipariş onay maili | D9: — | E9: 1. E-postayı kontrol et | F9: Sipariş onay maili gelir; sipariş no, ürün, adres, takip linki içerir. | H9: Beklemede | L9: Orta
A10: E01-007 | B10: E01 | C10: Adım 7: Satıcıya bildirim | D10: — | E10: 1. Satıcı tarafında dashboard kontrol | F10: 'Yeni sipariş' bildirimi/mail. | H10: Beklemede | L10: Orta
A11: E01-008 | B11: E01 | C11: Adım 8: Satıcı kargolar | D11: — | E11: 1. Satıcı kargo no girer | F11: Sipariş 'shipped'; alıcıya tracking maili. | H11: Beklemede | L11: Orta
A12: E01-009 | B12: E01 | C12: Adım 9: Misafir kargo takip | D12: — | E12: 1. Mailden /track-order aç | F12: E-posta + sipariş no ile detay açılır; tracking görünür. | H12: Beklemede | L12: Orta
A13: E01-010 | B13: E01 | C13: Adım 10: Teslimat | D13: Kargo webhook 'delivered'. | E13: 1. — | F13: Sipariş 'delivered'; alıcıya teslim maili. | H13: Beklemede | L13: Orta
A14: E01-011 | B14: E01 | C14: Adım 11: Fatura maili | D14: — | E14: 1. Mail kontrol | F14: Fatura maili + PDF link. | H14: Beklemede | L14: Orta
A15: E01-012 | B15: E01 | C15: Adım 12: 7 gün sonra escrow release | D15: — | E15: 1. Cron'u bekle | F15: PaymentHold release; payout satıcıya tetiklenir. | H15: Beklemede | L15: Orta
A16: E01-013 | B16: E01 | C16: Adım 13: Misafir iade talebi (üye olmadan) | D16: Teslim alınmış misafir siparişi. | E16: 1. /track-order üzerinden iade aç | F16: İade talebi oluşur; sebep/foto yüklenir; satıcıya gider. | H16: Beklemede | L16: Orta
A19: Bu sayfadaki tüm senaryolar test edilmiş ve sonuçlar yukarıda işaretlenmiştir.
A20: Test Eden (Tarodan) | D20: Tarih | G20: Onaylayan (Müşteri) | J20: Tarih

Sheet E02 - E2E Üye İade
A1: E02 — Uçtan Uca: Üye Satın Alma → İade
A2: Üye satın alır → teslim alır → iade talep eder → onaylanır → para iadesi.
A3: Test ID | B3: Modül / Sayfa | C3: Senaryo / Test Adı | D3: Önkoşullar | E3: Adımlar (numaralı) | F3: Beklenen Sonuç | G3: Gerçek Sonuç | H3: Durum | I3: Test Eden | J3: Test Tarihi | K3: Tarayıcı / Cihaz | L3: Öncelik | M3: Notlar / Hata Linki
A4: E02-001 | B4: E02 | C4: Üye satın alma | D4: Üye, kayıtlı adres. | E4: 1. Sepet → checkout → ödeme | F4: Sipariş başarıyla oluşur. | H4: Beklemede | L4: Orta
A5: E02-002 | B5: E02 | C5: Satıcı kargolar | D5: — | E5: 1. Satıcı kargo girer | F5: Status 'shipped'. | H5: Beklemede | L5: Orta
A6: E02-003 | B6: E02 | C6: Teslim alındı | D6: — | E6: 1. Webhook delivered | F6: Status 'delivered'. | H6: Beklemede | L6: Orta
A7: E02-004 | B7: E02 | C7: İade talebi (foto + sebep) | D7: — | E7: 1. /orders/[id] → İade Aç | F7: Talep 'pending_review'; satıcıya bildirim. | H7: Beklemede | L7: Orta
A8: E02-005 | B8: E02 | C8: Satıcı iade onaylar | D8: — | E8: 1. Satıcı 'kabul' | F8: Talep 'approved'; alıcıya kargo bilgisi maili. | H8: Beklemede | L8: Orta
A9: E02-006 | B9: E02 | C9: Alıcı iade kargosu | D9: — | E9: 1. Tracking no gir | F9: Status 'return_in_transit'. | H9: Beklemede | L9: Orta
A10: E02-007 | B10: E02 | C10: Satıcı iade ürünü teslim aldı | D10: — | E10: 1. Satıcı 'teslim aldım' | F10: Refund cron tetiklenir. | H10: Beklemede | L10: Orta
A11: E02-008 | B11: E02 | C11: Para iadesi (PayTR refund) | D11: — | E11: 1. — | F11: Refund 'completed'; alıcıya mail; tutar PayTR refund'la geri. | H11: Beklemede | L11: Orta
A12: E02-009 | B12: E02 | C12: Sipariş final durum | D12: — | E12: 1. /orders/[id] kontrol | F12: Status 'refunded'; payout iptal/geri. | H12: Beklemede | L12: Orta
A15: Bu sayfadaki tüm senaryolar test edilmiş ve sonuçlar yukarıda işaretlenmiştir.
A16: Test Eden (Tarodan) | D16: Tarih | G16: Onaylayan (Müşteri) | J16: Tarih

Sheet E03 - E2E Kargolanmadan İptal
A1: E03 — Uçtan Uca: Sipariş Kargolanmadan İptal
A2: Ödeme yapıldı ama satıcı henüz kargolamadı; alıcı iptal eder.
A3: Test ID | B3: Modül / Sayfa | C3: Senaryo / Test Adı | D3: Önkoşullar | E3: Adımlar (numaralı) | F3: Beklenen Sonuç | G3: Gerçek Sonuç | H3: Durum | I3: Test Eden | J3: Test Tarihi | K3: Tarayıcı / Cihaz | L3: Öncelik | M3: Notlar / Hata Linki
A4: E03-001 | B4: E03 | C4: Sipariş + ödeme | D4: — | E4: 1. Sepet → ödeme tamamla | F4: Status 'paid' → 'preparing'. | H4: Beklemede | L4: Orta
A5: E03-002 | B5: E03 | C5: Hemen iptal isteği | D5: — | E5: 1. /orders/[id] → İptal İste | F5: Status 'cancel_requested'; satıcıya bildirim. | H5: Beklemede | L5: Orta
A6: E03-003 | B6: E03 | C6: Satıcı kabul | D6: — | E6: 1. Satıcı 'iptali kabul et' | F6: Status 'cancelled'; PayTR otomatik refund. | H6: Beklemede | L6: Orta
A7: E03-004 | B7: E03 | C7: Para iadesi maili | D7: — | E7: 1. Mail kontrol | F7: Refund maili gelir; tutar geri yatırılır. | H7: Beklemede | L7: Orta
A8: E03-005 | B8: E03 | C8: Stok geri verildi | D8: — | E8: 1. Ürün detayında stok kontrol | F8: Stok eski seviyesine döner. | H8: Beklemede | L8: Orta
A11: Bu sayfadaki tüm senaryolar test edilmiş ve sonuçlar yukarıda işaretlenmiştir.
A12: Test Eden (Tarodan) | D12: Tarih | G12: Onaylayan (Müşteri) | J12: Tarih

Sheet E04 - E2E Satıcı Yolculuğu
A1: E04 — Uçtan Uca: Satıcı: İlan → Sipariş → Kargo → Payout
A2: Yeni satıcı kaydı, ilan, satış, payout.
A3: Test ID | B3: Modül / Sayfa | C3: Senaryo / Test Adı | D3: Önkoşullar | E3: Adımlar (numaralı) | F3: Beklenen Sonuç | G3: Gerçek Sonuç | H3: Durum | I3: Test Eden | J3: Test Tarihi | K3: Tarayıcı / Cihaz | L3: Öncelik | M3: Notlar / Hata Linki
A4: E04-001 | B4: E04 | C4: Kurumsal kayıt | D4: — | E4: 1. /register/business doldur | F4: Hesap oluşur; başvuru pending. | H4: Beklemede | L4: Orta
A5: E04-002 | B5: E04 | C5: Admin başvuru onayı | D5: — | E5: 1. Admin onaylar | F5: Satıcı 'aktif'; mail. | H5: Beklemede | L5: Orta
A6: E04-003 | B6: E04 | C6: İlan oluşturma | D6: — | E6: 1. /listings/new doldur | F6: İlan moderasyonda. | H6: Beklemede | L6: Orta
A7: E04-004 | B7: E04 | C7: Admin ürün onayı | D7: — | E7: 1. Admin onaylar | F7: İlan webde görünür. | H7: Beklemede | L7: Orta
A8: E04-005 | B8: E04 | C8: Sipariş geldi | D8: Alıcı satın aldı. | E8: 1. Satıcı dashboard | F8: Yeni sipariş bildirimi. | H8: Beklemede | L8: Orta
A9: E04-006 | B9: E04 | C9: Kargo girişi | D9: — | E9: 1. Kargo no gir | F9: Status shipped. | H9: Beklemede | L9: Orta
A10: E04-007 | B10: E04 | C10: Teslimat + 7 gün escrow | D10: — | E10: 1. Bekle | F10: PaymentHold release. | H10: Beklemede | L10: Orta
A11: E04-008 | B11: E04 | C11: Banka bilgisi yok ise | D11: IBAN eklenmemiş. | E11: 1. — | F11: Payout 'failed - no_bank_account'; satıcıya uyarı. | H11: Beklemede | L11: Orta
A12: E04-009 | B12: E04 | C12: IBAN ekledikten sonra retry | D12: IBAN eklendi. | E12: 1. Cron retry | F12: Payout 'completed'; mail. | H12: Beklemede | L12: Orta
A15: Bu sayfadaki tüm senaryolar test edilmiş ve sonuçlar yukarıda işaretlenmiştir.
A16: Test Eden (Tarodan) | D16: Tarih | G16: Onaylayan (Müşteri) | J16: Tarih

Sheet E05 - E2E Teklif Akışı
A1: E05 — Uçtan Uca: Teklif → Karşı Teklif → Kabul → Ödeme
A2: Teklif vererek satın alma akışı.
A3: Test ID | B3: Modül / Sayfa | C3: Senaryo / Test Adı | D3: Önkoşullar | E3: Adımlar (numaralı) | F3: Beklenen Sonuç | G3: Gerçek Sonuç | H3: Durum | I3: Test Eden | J3: Test Tarihi | K3: Tarayıcı / Cihaz | L3: Öncelik | M3: Notlar / Hata Linki
A4: E05-001 | B4: E05 | C4: Teklif ver | D4: Üye, başkasının ürünü. | E4: 1. Teklif modalı, fiyat gir | F4: Teklif gönderilir. | H4: Beklemede | L4: Orta
A5: E05-002 | B5: E05 | C5: Satıcı karşı teklif | D5: — | E5: 1. Satıcı counter | F5: Yeni fiyat alıcıya gider. | H5: Beklemede | L5: Orta
A6: E05-003 | B6: E05 | C6: Alıcı kabul | D6: — | E6: 1. Karşı teklifi kabul | F6: Sipariş otomatik oluşur; ödeme bekleniyor. | H6: Beklemede | L6: Orta
A7: E05-004 | B7: E05 | C7: 30 dk içinde ödeme | D7: — | E7: 1. PayTR ile öde | F7: Sipariş normal akışa girer. | H7: Beklemede | L7: Orta
A8: E05-005 | B8: E05 | C8: Ödenmedi → expire | D8: — | E8: 1. 30 dk geç | F8: Sipariş iptal; teklif expired_unpaid. | H8: Beklemede | L8: Orta
A11: Bu sayfadaki tüm senaryolar test edilmiş ve sonuçlar yukarıda işaretlenmiştir.
A12: Test Eden (Tarodan) | D12: Tarih | G12: Onaylayan (Müşteri) | J12: Tarih

Sheet E06 - E2E Takas
A1: E06 — Uçtan Uca: Takas (Trade) Tam Akışı
A2: Takas teklifi → kabul → çift kargo → tamamlama.
A3: Test ID | B3: Modül / Sayfa | C3: Senaryo / Test Adı | D3: Önkoşullar | E3: Adımlar (numaralı) | F3: Beklenen Sonuç | G3: Gerçek Sonuç | H3: Durum | I3: Test Eden | J3: Test Tarihi | K3: Tarayıcı / Cihaz | L3: Öncelik | M3: Notlar / Hata Linki
A4: E06-001 | B4: E06 | C4: Takas teklifi | D4: — | E4: 1. Trade öner | F4: Karşı tarafa bildirim. | H4: Beklemede | L4: Orta
A5: E06-002 | B5: E06 | C5: Kabul + nakit fark ödemesi | D5: — | E5: 1. Kabul, cash diff öde | F5: Status accepted, payment completed. | H5: Beklemede | L5: Orta
A6: E06-003 | B6: E06 | C6: Çift kargo | D6: — | E6: 1. Iki taraf da kargo no girer | F6: Iki kargo da takip edilebilir. | H6: Beklemede | L6: Orta
A7: E06-004 | B7: E06 | C7: Iki taraf teslim alır | D7: — | E7: 1. Iki taraf da onay | F7: Status 'completed'. | H7: Beklemede | L7: Orta
A8: E06-005 | B8: E06 | C8: Cash diff release | D8: — | E8: 1. Escrow release | F8: Cash diff hak sahibine geçer. | H8: Beklemede | L8: Orta
A9: E06-006 | B9: E06 | C9: Anlaşmazlık akışı (alternatif) | D9: — | E9: 1. Bir taraf dispute açar | F9: Admin'e düşer; çözüme kadar para hold'da. | H9: Beklemede | L9: Orta
A12: Bu sayfadaki tüm senaryolar test edilmiş ve sonuçlar yukarıda işaretlenmiştir.
A13: Test Eden (Tarodan) | D13: Tarih | G13: Onaylayan (Müşteri) | J13: Tarih

Sheet E07 - E2E Üyelik
A1: E07 — Uçtan Uca: Üyelik Satın Al → Yenile → İptal
A2: Premium üyelik yaşam döngüsü.
A3: Test ID | B3: Modül / Sayfa | C3: Senaryo / Test Adı | D3: Önkoşullar | E3: Adımlar (numaralı) | F3: Beklenen Sonuç | G3: Gerçek Sonuç | H3: Durum | I3: Test Eden | J3: Test Tarihi | K3: Tarayıcı / Cihaz | L3: Öncelik | M3: Notlar / Hata Linki
A4: E07-001 | B4: E07 | C4: Premium satın alma | D4: — | E4: 1. /pricing → premium → öde | F4: Üyelik aktif; başarı + mail + fatura. | H4: Beklemede | L4: Orta
A5: E07-002 | B5: E07 | C5: Avantaj uygulanması | D5: — | E5: 1. İlan limit, komisyon kontrol | F5: Tier kuralları geçerli. | H5: Beklemede | L5: Orta
A6: E07-003 | B6: E07 | C6: 7 gün kala uyarı | D6: — | E6: 1. Cron | F6: Mail bildirimi. | H6: Beklemede | L6: Orta
A7: E07-004 | B7: E07 | C7: 1 gün kala uyarı | D7: — | E7: 1. Cron | F7: Acil mail. | H7: Beklemede | L7: Orta
A8: E07-005 | B8: E07 | C8: Yenileme | D8: — | E8: 1. /membership/manage → Yenile | F8: Periyot uzar; yeni fatura. | H8: Beklemede | L8: Orta
A9: E07-006 | B9: E07 | C9: İptal | D9: — | E9: 1. Yenilemeyi iptal et | F9: Süre sonuna kadar aktif kalır; mail bilgi. | H9: Beklemede | L9: Orta
A10: E07-007 | B10: E07 | C10: Süresi bitti — Free'ye düş | D10: — | E10: 1. Period end geç | F10: Free tier; ilan limiti uygulanır; mail. | H10: Beklemede | L10: Orta
A13: Bu sayfadaki tüm senaryolar test edilmiş ve sonuçlar yukarıda işaretlenmiştir.
A14: Test Eden (Tarodan) | D14: Tarih | G14: Onaylayan (Müşteri) | J14: Tarih

Sheet E08 - E2E Şifre Sıfırlama
A1: E08 — Uçtan Uca: Şifre Unuttum → Sıfırla → Giriş
A2: Şifre sıfırlama tam akışı.
A3: Test ID | B3: Modül / Sayfa | C3: Senaryo / Test Adı | D3: Önkoşullar | E3: Adımlar (numaralı) | F3: Beklenen Sonuç | G3: Gerçek Sonuç | H3: Durum | I3: Test Eden | J3: Test Tarihi | K3: Tarayıcı / Cihaz | L3: Öncelik | M3: Notlar / Hata Linki
A4: E08-001 | B4: E08 | C4: /forgot-password formu | D4: — | E4: 1. E-posta gir, gönder | F4: Mail gider (kayıtsız e-postada da generic mesaj). | H4: Beklemede | L4: Orta
A5: E08-002 | B5: E08 | C5: Linke tıklama | D5: — | E5: 1. Maildeki linke tıkla | F5: /reset-password açılır. | H5: Beklemede | L5: Orta
A6: E08-003 | B6: E08 | C6: Yeni şifre belirleme | D6: — | E6: 1. Yeni şifre x2 gir, kaydet | F6: Başarılı; login'e yönlendir. | H6: Beklemede | L6: Orta
A7: E08-004 | B7: E08 | C7: Yeni şifre ile giriş | D7: — | E7: 1. Login dene | F7: Giriş başarılı. | H7: Beklemede | L7: Orta
A8: E08-005 | B8: E08 | C8: Eski şifre artık çalışmıyor | D8: — | E8: 1. Eski şifreyle dene | F8: Hata. | H8: Beklemede | L8: Orta
A11: Bu sayfadaki tüm senaryolar test edilmiş ve sonuçlar yukarıda işaretlenmiştir.
A12: Test Eden (Tarodan) | D12: Tarih | G12: Onaylayan (Müşteri) | J12: Tarih

Sheet E09 - E2E Stok Yarış
A1: E09 — Uçtan Uca: Stok Race Condition Testi
A2: Aynı anda iki kullanıcı aynı tek-stok ürünü satın alır.
A3: Test ID | B3: Modül / Sayfa | C3: Senaryo / Test Adı | D3: Önkoşullar | E3: Adımlar (numaralı) | F3: Beklenen Sonuç | G3: Gerçek Sonuç | H3: Durum | I3: Test Eden | J3: Test Tarihi | K3: Tarayıcı / Cihaz | L3: Öncelik | M3: Notlar / Hata Linki
A4: E09-001 | B4: E09 | C4: İki sekmede aynı ürün | D4: Quantity = 1. | E4: 1. İki tarayıcıda da sepete ekle, ödemeye geç | F4: Her iki sepete de eklenir. | H4: Beklemede | L4: Orta
A5: E09-002 | B5: E09 | C5: İki ödeme aynı anda | D5: — | E5: 1. İkisi de PayTR'a yönlenip ödeme yapmaya çalışır | F5: Sadece bir tanesi başarılı; diğeri 'stok kalmadı' hatası alır. | H5: Beklemede | L5: Kritik
A6: E09-003 | B6: E09 | C6: Başarısız sipariş için iade | D6: İkincisi ödeme tamamladıysa. | E6: 1. — | F6: Otomatik refund tetiklenir; mail bilgi. | H6: Beklemede | L6: Orta
A7: E09-004 | B7: E09 | C7: Stok 0 olur | D7: — | E7: 1. Ürün detay yenile | F7: Satıldı görünür; sepete ekle disabled. | H7: Beklemede | L7: Orta
A10: Bu sayfadaki tüm senaryolar test edilmiş ve sonuçlar yukarıda işaretlenmiştir.
A11: Test Eden (Tarodan) | D11: Tarih | G11: Onaylayan (Müşteri) | J11: Tarih

Sheet E10 - E2E Bildirim Akışı
A1: E10 — Uçtan Uca: Tüm Bildirim Kanalları Doğrulama
A2: Bir sipariş yaşam döngüsünde tetiklenen tüm mail/push/in-app bildirimler.
A3: Test ID | B3: Modül / Sayfa | C3: Senaryo / Test Adı | D3: Önkoşullar | E3: Adımlar (numaralı) | F3: Beklenen Sonuç | G3: Gerçek Sonuç | H3: Durum | I3: Test Eden | J3: Test Tarihi | K3: Tarayıcı / Cihaz | L3: Öncelik | M3: Notlar / Hata Linki
A4: E10-001 | B4: E10 | C4: Sipariş oluşturuldu — alıcı maili | D4: — | E4: 1. Sipariş oluştur | F4: Alıcıya mail + in-app + (varsa) push. | H4: Beklemede | L4: Orta
A5: E10-002 | B5: E10 | C5: Sipariş oluşturuldu — satıcı maili | D5: — | E5: 1. — | F5: Satıcıya 'yeni sipariş' bildirimi. | H5: Beklemede | L5: Orta
A6: E10-003 | B6: E10 | C6: Ödeme onaylandı bildirimi | D6: — | E6: 1. — | F6: Iki tarafa da bildirim. | H6: Beklemede | L6: Orta
A7: E10-004 | B7: E10 | C7: Kargolandı bildirimi | D7: — | E7: 1. Satıcı kargo girer | F7: Alıcıya mail + tracking. | H7: Beklemede | L7: Orta
A8: E10-005 | B8: E10 | C8: Teslim edildi bildirimi | D8: — | E8: 1. Webhook delivered | F8: Alıcıya teslim maili + yorum CTA. | H8: Beklemede | L8: Orta
A9: E10-006 | B9: E10 | C9: Fatura maili | D9: — | E9: 1. — | F9: PDF link. | H9: Beklemede | L9: Orta
A10: E10-007 | B10: E10 | C10: Payout başarılı bildirimi | D10: — | E10: 1. — | F10: Satıcıya 'ödemeniz hesabınızda' maili. | H10: Beklemede | L10: Orta
A11: E10-008 | B11: E10 | C11: Mail spam klasörüne düşmeme | D11: — | E11: 1. Gmail/outlook gibi 3 farklı sağlayıcı | F11: Inbox'a düşer; SPF/DKIM/DMARC OK. | H11: Beklemede | L11: Orta
A14: Bu sayfadaki tüm senaryolar test edilmiş ve sonuçlar yukarıda işaretlenmiştir.
A15: Test Eden (Tarodan) | D15: Tarih | G15: Onaylayan (Müşteri) | J15: Tarih

Sheet C01 - Mail Bildirim Listesi
A1: C01 — Tüm Mail Bildirimleri Matrisi
A2: Hangi olay → hangi mail/şablon → kime → kanallar.
A3: Test ID | B3: Modül / Sayfa | C3: Senaryo / Test Adı | D3: Önkoşullar | E3: Adımlar (numaralı) | F3: Beklenen Sonuç | G3: Gerçek Sonuç | H3: Durum | I3: Test Eden | J3: Test Tarihi | K3: Tarayıcı / Cihaz | L3: Öncelik | M3: Notlar / Hata Linki
A4: C01-001 | B4: C01 | C4: Hoş geldiniz maili | D4: Yeni kayıt. | E4: 1. Kayıt ol | F4: Welcome maili kullanıcıya. | H4: Beklemede | L4: Orta
A5: C01-002 | B5: C01 | C5: E-posta doğrulama maili | D5: — | E5: 1. Kayıt sonrası | F5: Doğrulama linki içerir. | H5: Beklemede | L5: Orta
A6: C01-003 | B6: C01 | C6: Şifre sıfırlama maili | D6: — | E6: 1. Forgot password | F6: Token + link (1 saat). | H6: Beklemede | L6: Orta
A7: C01-004 | B7: C01 | C7: Misafir checkout OTP maili | D7: — | E7: 1. Guest checkout | F7: 6 haneli kod + TTL bilgisi. | H7: Beklemede | L7: Orta
A8: C01-005 | B8: C01 | C8: Sipariş oluştu (alıcı) | D8: — | E8: 1. — | F8: Sipariş özeti. | H8: Beklemede | L8: Orta
A9: C01-006 | B9: C01 | C9: Yeni sipariş (satıcı) | D9: — | E9: 1. — | F9: Sipariş bilgisi + kargo deadline. | H9: Beklemede | L9: Orta
A10: C01-007 | B10: C01 | C10: Ödeme onaylandı (alıcı) | D10: — | E10: 1. — | F10: Mail + tahmini teslim tarihi. | H10: Beklemede | L10: Orta
A11: C01-008 | B11: C01 | C11: Kargolandı (alıcı) | D11: — | E11: 1. — | F11: Tracking no + link. | H11: Beklemede | L11: Orta
A12: C01-009 | B12: C01 | C12: Teslim edildi (alıcı) | D12: — | E12: 1. — | F12: Yorum CTA. | H12: Beklemede | L12: Orta
A13: C01-010 | B13: C01 | C13: Fatura (alıcı + satıcı) | D13: — | E13: 1. — | F13: PDF link, KDV detay. | H13: Beklemede | L13: Orta
A14: C01-011 | B14: C01 | C14: Payout (satıcı) | D14: — | E14: 1. — | F14: Tutar, banka. | H14: Beklemede | L14: Orta
A15: C01-012 | B15: C01 | C15: İade talebi (satıcı) | D15: — | E15: 1. — | F15: 48 saat yanıt deadline. | H15: Beklemede | L15: Orta
... A31: C01-028 | B31: C01 | C31: Newsletter aboneliği onayı (double opt-in) | D31: — | E31: 1. — | F31: Onay linki. | H31: Beklemede | L31: Orta
A34: Bu sayfadaki tüm senaryolar test edilmiş ve sonuçlar yukarıda işaretlenmiştir.
A35: Test Eden (Tarodan) | D35: Tarih | G35: Onaylayan (Müşteri) | J35: Tarih

Sheet C02 - Push InApp Bildirim
A1: C02 — Push ve In-App Bildirim Doğrulamaları
A2: Browser/native push, in-app bell, websocket.
A3: Test ID | B3: Modül / Sayfa | C3: Senaryo / Test Adı | D3: Önkoşullar | E3: Adımlar (numaralı) | F3: Beklenen Sonuç | G3: Gerçek Sonuç | H3: Durum | I3: Test Eden | J3: Test Tarihi | K3: Tarayıcı / Cihaz | L3: Öncelik | M3: Notlar / Hata Linki
A4: C02-001 | B4: C02 | C4: Tarayıcı push izni | D4: — | E4: 1. İzin diyaloğunu kabul et | F4: Push token kaydedilir. | H4: Beklemede | L4: Orta
A5: C02-002 | B5: C02 | C5: Push bildirimi geldi | D5: Sipariş geldi. | E5: 1. — | F5: Push gösterilir; tıklayınca ilgili sayfa. | H5: Beklemede | L5: Orta
A6: C02-003 | B6: C02 | C6: İzin reddedildiyse fallback | D6: — | E6: 1. Sadece in-app + mail kullanılır | F6: Push gönderilmez ama diğerleri çalışır. | H6: Beklemede | L6: Orta
A7: C02-004 | B7: C02 | C7: Bell ikonu okunmamış sayacı | D7: — | E7: 1. Yeni bildirim sonrası bel ikonu | F7: Sayaç doğru artar. | H7: Beklemede | L7: Orta
A8: C02-005 | B8: C02 | C8: Realtime mesaj bildirimi (websocket) | D8: İki sekme açık. | E8: 1. Bir sekmeden mesaj at | F8: Diğer sekme anında gösterir. | H8: Beklemede | L8: Orta
A11: Bu sayfadaki tüm senaryolar test edilmiş ve sonuçlar yukarıda işaretlenmiştir.
A12: Test Eden (Tarodan) | D12: Tarih | G12: Onaylayan (Müşteri) | J12: Tarih

Sheet C03 - Cron Otomatik İşler
A1: C03 — Cron / Scheduled Job Doğrulamaları
A2: Otomatik tetiklenen tüm işler.
A3: Test ID | B3: Modül / Sayfa | C3: Senaryo / Test Adı | D3: Önkoşullar | E3: Adımlar (numaralı) | F3: Beklenen Sonuç | G3: Gerçek Sonuç | H3: Durum | I3: Test Eden | J3: Test Tarihi | K3: Tarayıcı / Cihaz | L3: Öncelik | M3: Notlar / Hata Linki
A4: C03-001 | B4: C03 | C4: Payment scheduler — expired reservations | D4: 15 dk geçmiş pending payment. | E4: 1. Cron run / bekle | F4: Sipariş iptal; stok geri. | H4: Beklemede | L4: Kritik
A5: C03-002 | B5: C03 | C5: Payment hold release (7 gün) | D5: Delivered + 7 gün. | E5: 1. Cron run | F5: Hold released → payout queue. | H5: Beklemede | L5: Orta
A6: C03-003 | B6: C03 | C6: Payout scheduler | D6: Pending payout. | E6: 1. Cron run | F6: Bank transfer; mail. | H6: Beklemede | L6: Orta
A7: C03-004 | B7: C03 | C7: Failed payout retry (24h) | D7: Failed payout. | E7: 1. Cron run | F7: Tekrar dener; max 3 retry. | H7: Beklemede | L7: Orta
A8: C03-005 | B8: C03 | C8: Offer expire (24h) | D8: Pending offer 24h+ eski. | E8: 1. Cron run | F8: Status 'expired'; bildirim. | H8: Beklemede | L8: Orta
A9: C03-006 | B9: C03 | C9: Trade auto-cancel | D9: Deadline aşımı. | E9: 1. Cron run | F9: Trade cancelled; refund. | H9: Beklemede | L9: Orta
A10: C03-007 | B10: C03 | C10: Trade auto-confirm receipt | D10: Teslim üzerinden süre dolmuş. | E10: 1. Cron run | F10: Otomatik onay. | H10: Beklemede | L10: Orta
A11: C03-008 | B11: C03 | C11: Refund scheduler — return shipments | D11: İade kargosu açık. | E11: 1. Cron run | F11: Durum güncellenir. | H11: Beklemede | L11: Orta
A12: C03-009 | B12: C03 | C12: Membership expire reminder (7 gün) | D12: — | E12: 1. Cron run | F12: Mail. | H12: Beklemede | L12: Orta
A13: C03-010 | B13: C03 | C13: Membership expire reminder (1 gün) | D13: — | E13: 1. Cron run | F13: Acil mail. | H13: Beklemede | L13: Orta
A14: C03-011 | B14: C03 | C14: Membership downgrade (period end) | D14: Period bitti. | E14: 1. Cron run | F14: Free tier'a düşer. | H14: Beklemede | L14: Orta
A15: C03-012 | B15: C03 | C15: Free user → premium öneri (aylık) | D15: — | E15: 1. Aylık cron | F15: Free kullanıcılara mail. | H15: Beklemede | L15: Orta
... A17: C03-014 | B17: C03 | C17: Shipping worker — webhook process | D17: Sürat webhook geldi. | E17: 1. — | F17: Shipment status update; mail. | H17: Beklemede | L17: Orta
A20: Bu sayfadaki tüm senaryolar test edilmiş ve sonuçlar yukarıda işaretlenmiştir.
A21: Test Eden (Tarodan) | D21: Tarih | G21: Onaylayan (Müşteri) | J21: Tarih

Sheet C04 - Edge Cases
A1: C04 — Edge Cases ve Hata Senaryoları
A2: Sınırlar, beklenmedik durumlar, hata mesajları.
A3: Test ID | B3: Modül / Sayfa | C3: Senaryo / Test Adı | D3: Önkoşullar | E3: Adımlar (numaralı) | F3: Beklenen Sonuç | G3: Gerçek Sonuç | H3: Durum | I3: Test Eden | J3: Test Tarihi | K3: Tarayıcı / Cihaz | L3: Öncelik | M3: Notlar / Hata Linki
A4: C04-001 | B4: C04 | C4: Çok büyük resim yükleme | D4: — | E4: 1. 20MB resim yükle | F4: Reddedilir; max boyut hatası. | H4: Beklemede | L4: Orta
A5: C04-002 | B5: C04 | C5: Çok uzun başlık/açıklama | D5: — | E5: 1. Karakter limitini aş | F5: Form geçmez. | H5: Beklemede | L5: Orta
A6: C04-003 | B6: C04 | C6: SQL injection denemesi | D6: — | E6: 1. Form alanına `' OR 1=1--` | F6: Sanitize edilir; hata vermez; injection olmaz. | H6: Beklemede | L6: Kritik
A7: C04-004 | B7: C04 | C7: XSS denemesi (yorum) | D7: — | E7: 1. Yorum: `<script>alert(1)</script>` | F7: Escape edilir; render edilmez. | H7: Beklemede | L7: Kritik
A8: C04-005 | B8: C04 | C8: CSRF korumalı endpoint | D8: — | E8: 1. Cookie'siz POST dene | F8: 403 reddedilir. | H8: Beklemede | L8: Orta
A9: C04-006 | B9: C04 | C9: Çok hızlı tıklama (double-submit) | D9: — | E9: 1. Sipariş Onayla'ya art arda 5 kez bas | F9: Idempotency; sadece 1 sipariş oluşur. | H9: Beklemede | L9: Yüksek
A10: C04-007 | B10: C04 | C10: İnternet kesilmesi (offline) | D10: — | E10: 1. Form gönderirken internet kes | F10: Hata mesajı; veri kaybolmaz. | H10: Beklemede | L10: Orta
A11: C04-008 | B11: C04 | C11: Tarayıcı geri butonu | D11: — | E11: 1. Checkout sırasında geri | F11: Veri korunur; uyarı çıkar. | H11: Beklemede | L11: Orta
A12: C04-009 | B12: C04 | C12: Aynı ürün iki sekmede sepete ekleme | D12: — | E12: 1. İki sekmede de ekle | F12: Quantity senkron olur veya çakışma uyarısı. | H12: Beklemede | L12: Orta
A13: C04-010 | B13: C04 | C13: Negatif fiyat / sıfır fiyat | D13: — | E13: 1. İlan oluştururken 0 veya -10 | F13: Validasyon engeller. | H13: Beklemede | L13: Orta
A14: C04-011 | B14: C04 | C14: Gelecek tarihli kupon | D14: Henüz başlamamış kupon. | E14: 1. Uygulamayı dene | F14: Henüz aktif değil hatası. | H14: Beklemede | L14: Orta
A15: C04-012 | B15: C04 | C15: Çok fazla dil desteği test | D15: — | E15: 1. Dil değiştir (TR/EN) | F15: Tüm metinler çevrilir; bozuk render yok. | H15: Beklemede | L15: Orta
A16: C04-013 | B16: C04 | C16: Yarım dolu form refresh | D16: — | E16: 1. Form doldururken sayfayı yenile | F16: Değerler kaybolur (kasten); kritik formlarda uyarı. | H16: Beklemede | L16: Orta
A19: Bu sayfadaki tüm senaryolar test edilmiş ve sonuçlar yukarıda işaretlenmiştir.
A20: Test Eden (Tarodan) | D20: Tarih | G20: Onaylayan (Müşteri) | J20: Tarih

Sheet C05 - Performans Yük
A1: C05 — Performans ve Yük (Smoke)
A2: Sayfa yükleme süresi, çok ürünlü liste, paralel sipariş.
A3: Test ID | B3: Modül / Sayfa | C3: Senaryo / Test Adı | D3: Önkoşullar | E3: Adımlar (numaralı) | F3: Beklenen Sonuç | G3: Gerçek Sonuç | H3: Durum | I3: Test Eden | J3: Test Tarihi | K3: Tarayıcı / Cihaz | L3: Öncelik | M3: Notlar / Hata Linki
A4: C05-001 | B4: C05 | C4: Anasayfa yükleme süresi | D4: Cache cold. | E4: 1. Lighthouse veya devtools | F4: FCP < 2s, LCP < 3s. | H4: Beklemede | L4: Orta
A5: C05-002 | B5: C05 | C5: Listeleme sayfası 1000+ ürün | D5: — | E5: 1. Liste açma | F5: Sayfalama veya virtualization; akıcı. | H5: Beklemede | L5: Orta
A6: C05-003 | B6: C05 | C6: Paralel 50 sipariş simülasyonu | D6: Yük testi script. | E6: 1. 50 paralel checkout | F6: Kuyruğa alınır; çakışma yok. | H6: Beklemede | L6: Orta
A7: C05-004 | B7: C05 | C7: Mail kuyruk yığılması | D7: — | E7: 1. 100 sipariş hızlıca | F7: Bull queue işler; gecikme normal sınırda. | H7: Beklemede | L7: Orta
A8: C05-005 | B8: C05 | C8: Resim CDN cache | D8: — | E8: 1. Aynı resmi 2. kez yükle | F8: Cache hit, hızlı. | H8: Beklemede | L8: Orta
A11: Bu sayfadaki tüm senaryolar test edilmiş ve sonuçlar yukarıda işaretlenmiştir.
A12: Test Eden (Tarodan) | D12: Tarih | G12: Onaylayan (Müşteri) | J12: Tarih

Sheet C06 - Güvenlik
A1: C06 — Güvenlik ve Yetki Sınırları
A2: Auth, IDOR, role escalation, CORS.
A3: Test ID | B3: Modül / Sayfa | C3: Senaryo / Test Adı | D3: Önkoşullar | E3: Adımlar (numaralı) | F3: Beklenen Sonuç | G3: Gerçek Sonuç | H3: Durum | I3: Test Eden | J3: Test Tarihi | K3: Tarayıcı / Cihaz | L3: Öncelik | M3: Notlar / Hata Linki
A4: C06-001 | B4: C06 | C4: Başkasının siparişine IDOR ile erişme | D4: Login. | E4: 1. URL'deki ID değiştir | F4: 403; erişim engellenir. | H4: Beklemede | L4: Kritik
A5: C06-002 | B5: C06 | C5: Başkasının ilanını silmeye çalışma | D5: — | E5: 1. API'ye DELETE dene | F5: 403. | H5: Beklemede | L5: Orta
A6: C06-003 | B6: C06 | C6: Admin endpoint'ine normal kullanıcı çağrısı | D6: Normal user JWT. | E6: 1. /api/admin/users çağır | F6: 403. | H6: Beklemede | L6: Orta
A7: C06-004 | B7: C06 | C7: JWT manipülasyonu | D7: — | E7: 1. Token'ın role claim'ini admin yap | F7: İmza doğrulaması başarısız; reddedilir. | H7: Beklemede | L7: Orta
A8: C06-005 | B8: C06 | C8: Şifre brute force | D8: — | E8: 1. 10 deneme | F8: Lockout uygulanır. | H8: Beklemede | L8: Orta
A9: C06-006 | B9: C06 | C9: Rate limit (genel API) | D9: — | E9: 1. Kısa süre çok istek | F9: 429 dönülür. | H9: Beklemede | L9: Orta
A10: C06-007 | B10: C06 | C10: Banlı kullanıcı login | D10: Banlı. | E10: 1. Login dene | F10: Hesap askıda hatası. | H10: Beklemede | L10: Orta
A11: C06-008 | B11: C06 | C11: CORS — yetkisiz origin | D11: — | E11: 1. evil.com'dan API çağır | F11: Reddedilir. | H11: Beklemede | L11: Orta
A12: C06-009 | B12: C06 | C12: PII maskeleme (loglarda) | D12: — | E12: 1. Log incele | F12: E-posta/IBAN/kart maskelenir. | H12: Beklemede | L12: Orta
A13: C06-010 | B13: C06 | C13: Cookie'ler Secure + HttpOnly | D13: — | E13: 1. DevTools → Application | F13: Auth cookie HttpOnly + Secure flag. | H13: Beklemede | L13: Orta
A16: Bu sayfadaki tüm senaryolar test edilmiş ve sonuçlar yukarıda işaretlenmiştir.
A17: Test Eden (Tarodan) | D17: Tarih | G17: Onaylayan (Müşteri) | J17: Tarih

Sheet C08 - Escrow Release Kuralları
A1: C08 — Escrow / Para Release Kuralları (KRİTİK)
A2: Kural: Her iki taraf 'teslim aldım' işaretler VE/VEYA 7 gün geçer — hangisi önce gerçekleşirse para satıcıya release edilir. Bu sheet hem siparişler hem takaslar için release davranışını doğrular. İlgili modüller: payment-scheduler, payment.service (PaymentHold), trade.service (confirmReceipt), order.service (confirmDelivery), shipping.worker (delivery → releasePaymentIfHeld).
A3: Test ID | B3: Modül / Sayfa | C3: Senaryo / Test Adı | D3: Önkoşullar | E3: Adımlar (numaralı) | F3: Beklenen Sonuç | G3: Gerçek Sonuç | H3: Durum | I3: Test Eden | J3: Test Tarihi | K3: Tarayıcı / Cihaz | L3: Öncelik | M3: Notlar / Hata Linki
A4: C08-001 | B4: Order Escrow | C4: SİPARİŞ — Kargo 'delivered' webhook → para anında release | D4: Sipariş 'shipped'; PaymentHold (held); kargo şirketi delivered eventi gönderiyor. | E4: 1. Kargo webhook'u 'delivered' tetikle (veya manuel sync) 2. PaymentHold tablosunu kontrol et 3. Payout queue'ya bak | F4: PaymentHold.status='released' anında; PayoutTransfer pending olarak oluşturulur; satıcıya 'ödemeniz hesabınıza geçiyor' bildirimi. | H4: Beklemede | L4: Kritik
A5: C08-002 | B5: Order Escrow | C5: SİPARİŞ — Alıcı 'Teslim Aldım' tıkladı → para anında release (KURAL) | D5: Sipariş 'delivered' (kargo webhook geldi veya alıcı manuel onayladı); PaymentHold henüz held. | E5: 1. Alıcı /orders/[id] aç 2. 'Teslim Aldım' / 'Siparişi Onayla' butonuna bas 3. Backend: PATCH /orders/:id/confirm-delivery 4. PaymentHold ve PayoutTransfer kayıtlarını kontrol et | F5: Order.status='completed' OLUR ve PaymentHold.status='released' (anında); +7 gün beklenmez. Payout queue'ya alınır. Satıcıya 'erken release' maili. | H5: Beklemede | L5: Kritik
A6: C08-003 | B6: Order Escrow | C6: SİPARİŞ — Webhook YOK + alıcı onayı YOK → 7 gün sonra otomatik release | D6: Sipariş ödeme yapıldı, kargo webhook gelmedi, alıcı onaylamadı. | E6: 1. 7 gün geçir / payment-scheduler 'handleReleaseHoldsDue' cron'unu tetikle 2. PaymentHold tablosunu kontrol et | F6: PaymentHold.releaseAt aşıldığında status='released'; PayoutTransfer oluşturulur. | H6: Beklemede | L6: Kritik
A7: C08-004 | B7: Order Escrow | C7: SİPARİŞ — Webhook YOK ama alıcı 3. günde 'Teslim Aldım' (KURAL) | D7: Webhook hiç gelmedi; alıcı manuel onaylıyor. | E7: 1. 3. günde alıcı 'Teslim Aldım' butonuna bas | F7: Para 3. günde release edilir (7 gün beklenmez). 'Hangisi önce' kuralı işler. | H7: Beklemede | L7: Kritik
A8: C08-005 | B8: Order Escrow | C8: SİPARİŞ — Erken release maili | D8: Alıcı onayı veya webhook ile erken release. | E8: 1. Mail kontrolü | F8: Satıcıya 'Ödemeniz erken release edildi (alıcı teslimatı onayladı)' bildirimi gider. | H8: Beklemede | L8: Orta
A9: C08-006 | B9: Order Escrow | C9: SİPARİŞ — İade talebi açıkken release engellenir | D9: Sipariş delivered + RefundRequest pending. | E9: 1. Cron tetiklenir veya alıcı onay tıklar | F9: Para release EDİLMEZ (iade çözülene kadar bekler). | H9: Beklemede | L9: Kritik
A10: C08-007 | B10: Order Escrow | C10: SİPARİŞ — Çift release koruması | D10: Bir kez release edilmiş PaymentHold. | E10: 1. Aynı sipariş için release tetikleme tekrar deneme | F10: İkinci release çağrısı no-op; tek payout kaydı oluşur. Idempotency korumalı. | H10: Beklemede | L10: Orta
A11: C08-008 | B11: Order Escrow | C11: SİPARİŞ — Banka hesabı eksikse release sonrası payout failed | D11: Hold released, satıcının IBAN'ı yok. | E11: 1. Payout cron'u bekle | F11: PayoutTransfer.status='failed' (no_bank_account); satıcıya uyarı; nextRetryAt set. | H11: Beklemede | L11: Orta
A12: C08-009 | B12: Trade Escrow | C12: TAKAS — Her iki taraf 'Teslim Aldım' → para anında release (KURAL) | D12: Takas 'shipped'; iki tarafa kargo teslim oldu; cash diff var. | E12: 1. Taraf A: confirmReceipt çağır 2. Taraf B: confirmReceipt çağır 3. TradeCashPayment.holdReleaseAt ve status'ü kontrol et | F12: Trade.status='completed' VE TradeCashPayment release ANINDA gerçekleşir (+7 gün hold EKLENMEZ). | H12: Beklemede | L12: Kritik
A13: C08-010 | B13: Trade Escrow | C13: TAKAS — Tek taraf onayladı, diğeri yok → 3 gün auto-confirm | D13: Bir taraf confirm, diğeri yok. | E13: 1. 3 gün geçir; trade-scheduler 'autoConfirmExpiredReceipts' tetiklensin | F13: Eksik tarafın onayı otomatik gerçekleşir; trade completed; cash release ANINDA (kuralı uygula). | H13: Beklemede | L13: Orta
A14: C08-011 | B14: Trade Escrow | C14: TAKAS — Webhook YOK, hiç onay YOK → 7 gün sonra otomatik release | D14: İki taraf da onaylamadı, hiç tetikleyici yok. | E14: 1. 7 gün geçir / cron tetikle | F14: Cash payment release edilir (max bekleme süresi tamamlandı). | H14: Beklemede | L14: Kritik
A15: C08-012 | B15: Trade Escrow | C15: TAKAS — Anlaşmazlık (dispute) açıldığında release engellenir | D15: Takas 'disputed'. | E15: 1. Cron tetiklenir veya bir taraf confirm dener | F15: Cash hold release EDİLMEZ; admin çözümleyene kadar bekler. | H15: Beklemede | L15: Kritik
... A21: C08-018 | B21: Escrow Admin | C21: Released hold için audit log | D21: — | E21: 1. Audit log'u incele | F21: Release tetikleyicisi (manuel/auto/webhook), tutar, zaman, sipariş/takas referansı kayıtlı. | H21: Beklemede | L21: Orta
A24: Bu sayfadaki tüm senaryolar test edilmiş ve sonuçlar yukarıda işaretlenmiştir.
A25: Test Eden (Tarodan) | D25: Tarih | G25: Onaylayan (Müşteri) | J25: Tarih

Sheet C07 - Tarayıcı Cihaz Uyumu
A1: C07 — Tarayıcı ve Cihaz Uyum Matrisi
A2: Chrome, Safari, Firefox, Edge — desktop & mobile.
A3: Test ID | B3: Modül / Sayfa | C3: Senaryo / Test Adı | D3: Önkoşullar | E3: Adımlar (numaralı) | F3: Beklenen Sonuç | G3: Gerçek Sonuç | H3: Durum | I3: Test Eden | J3: Test Tarihi | K3: Tarayıcı / Cihaz | L3: Öncelik | M3: Notlar / Hata Linki
A4: C07-001 | B4: C07 | C4: Chrome Desktop — happy path | D4: — | E4: 1. Tüm temel akışları çalıştır | F4: Sorunsuz. | H4: Beklemede | L4: Orta
A5: C07-002 | B5: C07 | C5: Safari Desktop | D5: — | E5: 1. Aynı | F5: Sorunsuz. | H5: Beklemede | L5: Orta
A6: C07-003 | B6: C07 | C6: Firefox Desktop | D6: — | E6: 1. Aynı | F6: Sorunsuz. | H6: Beklemede | L6: Orta
A7: C07-004 | B7: C07 | C7: Edge Desktop | D7: — | E7: 1. Aynı | F7: Sorunsuz. | H7: Beklemede | L7: Orta
A8: C07-005 | B8: C07 | C8: iOS Safari (mobil) | D8: — | E8: 1. Sepet, checkout, ödeme | F8: Sorunsuz; klavye uygun. | H8: Beklemede | L8: Orta
A9: C07-006 | B9: C07 | C9: Android Chrome (mobil) | D9: — | E9: 1. Aynı | F9: Sorunsuz. | H9: Beklemede | L9: Orta
A10: C07-007 | B10: C07 | C10: Tablet (iPad/Android) | D10: — | E10: 1. Layout incele | F10: Düzgün grid. | H10: Beklemede | L10: Orta
A11: C07-008 | B11: C07 | C11: Eski tarayıcı (Chrome -3 versiyon) | D11: — | E11: 1. Çalıştır | F11: Çalışır veya graceful uyarı. | H11: Beklemede | L11: Orta
A14: Bu sayfadaki tüm senaryolar test edilmiş ve sonuçlar yukarıda işaretlenmiştir.
A15: Test Eden (Tarodan) | D15: Tarih | G15: Onaylayan (Müşteri) | J15: Tarih

Sheet ZZ - Final İmza
A1: RESMİ TESLİM VE KABUL TUTANAĞI
B5: Tarodan e-ticaret platformunun (tarodan.shop kullanıcı sitesi ve admin paneli) Kullanıcı Kabul Testi (UAT) süreci tamamlanmıştır. Bu doküman içerisinde yer alan tüm sheet'lerdeki test senaryoları her iki tarafça yürütülmüş, sonuçlar ilgili sheet'lere işlenmiş ve sheet bazlı imzalar alınmıştır. Aşağıda imzası bulunan müşteri yetkilisi, platformun teslim alındığını ve sözleşmede tanımlanan kapsama uygun şekilde çalıştığını teyit eder.
B11: Toplam Sheet Sayısı | C11: 64
B12: Toplam Test Senaryosu | C12: 502
B13: Test Süreci Başlangıç
B14: Test Süreci Bitiş
B15: Bulunan Bug Sayısı
B16: Düzeltilen Bug Sayısı
B17: Açık Bug Sayısı
B22: TARODAN | F22: MÜŞTERİ
B23: Proje Sorumlusu | F23: Yetkili
B24: Ad Soyad | F24: Ad Soyad
B25: Ünvan | F25: Ünvan
B26: Tarih | F26: Tarih
B27: İmza / Kaşe | F27: İmza / Kaşe
